Workbook

Sheet Sheet Overview
A1: TAB | B1: DEFINITION
A2: Sheet Overview | B2: Provides an overview of all the tabs within the database
A3: Headers | B3: Defines all the headers of the columns found in CRR 2025
A4: CRR 2025 | B4: Final Coral Reef Restoration (CRR) Database, with all coral reef restoration activities listed as individual rows, including their corresponding information or details
A5: Glossary | B5: Contains definitions for all possible options appearing in the dropdown lists of CRR 2025; this also serves as the source for data validation ranges
A6: Municipality | B6: Lists all regions, provinces, municipalities, and municipality codes found in CRR 2025; this also serves as a source for data validation
A7: Panel Format | B7: Shows a panel format comparing the 2023 (final) and 2025 (draft) iterations of the CRR database; served as a draft for the final CRR 2025 database
A8: 2025 | B8: Draft 2025 iteration of the CRR database
A9: 2024 | B9: Draft 2024 iteration of the CRR database
A10: 2023 | B10: 2023 iteration of the CRR database, with most entries considered in the Matorres et al. (2024) publication
A11: 2023 PubDel Entries | B11: Contains all the entries in the CRR 2023 iteration that were deleted in the 2025 iteration
A13: HIDDEN SHEETS FOR DATA VALIDATION/DROPDOWN
A14: Interventions | B14: Contains the master list of all general and specific coral reef restoration intervention types; used as the source for dropdowns and cross-referencing
A15: [Interventions]DD1 | B15: Lists unique general intervention categories; used in dropdowns for filtering or input validation in the CRR 2025 tab
A16: [Interventions]DD2 | B16: Lists all specific restoration methods, aligned with the general intervention categories for validation purposes
A17: [Mun]DD1 | B17: Lists all Philippine regions; used as a data validation source for the Region field in CRR 2025
A18: [Mun]DD2 | B18: Lists all provinces under their corresponding regions; used to validate Province entries
A19: [Mun]DD3 | B19: Lists all municipalities under their corresponding provinces, along with the official PSGC municipal codes; used to validate Municipality entries

Sheet Headers
A1: SECTIONS | B1: HEADERS | C1: DEFINITION
A2: Entry Information | B2: ID | C2: Number indicating the order in which the restoration project was encoded into the database
B3: Unique_key | C3: Code that uniquely identifies a restoration project in the database
B4: Year_add | C4: Year in which the project was added to the database
B5: Status | C5: Indicates if the project was part of the Matorres et al. (2024)
B6: Change_type | C6: Describes what type of change was made to the entry compared to its version in Matorres et al. (2024)
B7: Recheck | C7: Indicates whether the project entry has been rechecked after standardization of database rules
A8: Project Location and Timeline | B8: Region | C8: Region where the restoration project is located
B9: Province | C9: Province where the restoration project is located
B10: Municipality | C10: Municipality where the restoration project is located
B11: Municipality_code | C11: Standardised municipality code based on the official coding system from NAMRIA
B12: Restoration_project_title | C12: The given title of the restoration project
B13: Project_locality | C13: Specific site where the project is located, which may include the barangay, named location, or geographic coordinates
B14: Year_estab | C14: Year the restoration project was established on site
B15: Project_start | C15: Start date of the project
B16: Project_end | C16: End date of the project
A17: Restoration Approach | B17: Gen_method | C17: General restoration method used by the project
B18: Specific_method | C18: Specific restoration technique applied by the project
B19: AR_material_type | C19: Type of material used in the artificial reef restoration project
B20: AR_specific_structure | C20: Specific material used in the artificial reef restoration project
B21: Nursery_type_loc | C21: Location of the coral nursery, whether in-situ or ex-situ
B22: Nursery_type_design | C22: Type of nursery used in the coral gardening restoration project
B23: Method_specifics | C23: Other specific information on the material used in ALL of the restoration projects, as indicated in the reference material
A24: Project Objectives | B24: Motivation | C24: Primary motivation or objective behind the project, based on the classification from Boström-Einarsson et al. (2020)
B25: Motivation_code | C25: Codes assigned to the primary motivation
B26: Stated_objective | C26: Project objective/motivation as indicated in the reference material; not discriminating between main and other objectives
A27: Funding and Scale | B27: Funding_agency | C27: Name of the funding agency
B28: Fund_type | C28: General purpose or intended use of the funding provided
B29: Funder_loc | C29: Indicates whether the funder is based locally or internationally
B30: Funder_sector | C30: Broad category of the organisation providing the funding, based on its institutional nature
B31: Funder_specific_entity | C31: Specific funder categorization
B32: Total_funding | C32: Amount of funding in PHP provided or total cost of restoration activity
B33: Total_area | C33: Total area covered by the restoration project
B34: Total_units | C34: Total number of individual restoration units used in the project
A35: Implementers and Partners | B35: Implement_insti | C35: Name of institution that established the restoration project
B36: Proponent_sector | C36: General type of institution that established the project
B37: Proponent_specific_entity | C37: Specific proponent categorization
B38: Partners_public | C38: Government partners -- national to local
B39: Partners_private | C39: Private, dive centers, NGO, CSOs, or academic partners that collaborated in the project
B40: Partners_communities | C40: Community partners in the project
A41: Sources and Notes | B41: Literature_type | C41: Type of literature the restoration project details were obtained from
B42: Source_type | C42: Type of reference material for the restoration project
B43: Reference | C43: Citation for the restoration project reference material
B44: Link | C44: Link to the reference material of the project, if available
B45: Contact_name | C45: Name of contact person for the restoration project/ Name of the person who heads the project and was mentioned in the article
B46: Contact_details | C46: Contact details (email and phone) of the contact person for the restoration project
B47: Remarks | C47: Pecularities that were identified for that particular project, or any points of confusion

Sheet CRR 2025
A1: ID | B1: Unique_key | C1: Year_add | D1: Status | E1: Change_type | F1: Rechecked? | G1: Region | H1: Province | I1: Municipality | J1: Municipality_code | K1: Restoration_project_title | L1: Project_locality | M1: Year_estab | N1: Project_start | O1: Project_end | P1: Gen_method | Q1: Specific_method | R1: AR_material_type | S1: AR_specific_structure | T1: Nursery_type_loc | U1: Nursery_type_design | V1: Method_specifics | W1: Motivation | X1: Motivation_code | Y1: Stated_objective | Z1: Funding_agency | AA1: Fund_type | AB1: Funder_loc | AC1: Funder_sector | AD1: Funder_specific_entity | AE1: Total_funding | AF1: Total_area | AG1: Total_units | AH1: Implement_insti | AI1: Proponent_sector | AJ1: Proponent_specific_entity | AK1: Partners_public | AL1: Partners_private | AM1: Partners_communities | AN1: Literature_type | AO1: Source_type | AP1: Reference | AQ1: Link | AR1: Contact_name | AS1: Contact_details | AT1: Remarks
A2: 0034 | B2: =CONCATENATE(C2, "-", J2, "-", M2, "-", A2) -> 2023-PH015501000-2021-0034 | C2: =IF(OR(D2="Published", D2="Unpublished"), 2023, IF(D2="New", 2025, "")) -> 2023 | D2: Published | E2: Modified | F2: Yes | G2: I | H2: Pangasinan | I2: Agno | J2: PH015501000 | K2: Abig Pangasinan | L2: Site in Brgy Boboy | M2: 2021 | N2: Unknown | O2: Unknown | P2: Substrate Enhancement | Q2: Artificial Reef | R2: Concrete | S2: Concrete tripod | T2: Not applicable | U2: Not applicable | V2: Concrete tripod | W2: "Provide alternative, sustainable livelihood opportunities", "Reestablish a self-sustaining, functioning reef ecosystem", Reduce population declines and ecosystem degradation | X2: M2, M5, M4 | Y2: Provide livelihood opportunities to fisherfolk; breeding grounds for fishes and other marine resources that will boost fish production and food security in the locality; boost aqua-tourism | Z2: PLGU | AA2: Development | AB2: Local | AC2: Government - LGU | AD2: PLGU | AE2: Unknown | AF2: Unknown | AG2: 45 units | AH2: PLGU | AI2: Government - LGU | AJ2: PLGU | AK2: BFAR; MLGU | AL2: Unknown | AM2: Local fisherfolks tapped to be "Bantay Dagat" | AN2: Grey literature | AO2: News/Press Release | AP2: Austria, H. (2021, April 9). Artificial reef project gives livelihood to Pangasinan fisherfolk. Philippine News Agency. https://www.pna.gov.ph/articles/1136282 | AQ2: https://www.pna.gov.ph/articles/1136282 | AR2: Rosario Segundina Gaerlan, BFAR Ilocos Region officer-in-charge regional director | AS2: Unknown
A3: 0362 | B3: =CONCATENATE(C3, "-", J3, "-", M3, "-", A3) -> 2023-PH104319000-2000-0362 | C3: =IF(OR(D3="Published", D3="Unpublished"), 2023, IF(D3="New", 2025, "")) -> 2023 | D3: Published | E3: Modified | F3: Yes | G3: X | H3: Misamis Oriental | I3: Medina | J3: PH104319000 | K3: Acantasia Project | L3: Site in Gingoong Bay | M3: 2000 | N3: 2000 | O3: Unknown | P3: Asexual Propagation | Q3: Direct Transplantation | R3: Not applicable | S3: Not applicable | T3: Not applicable | U3: Not applicable | V3: Coral transplantation | W3: "Reestablish a self-sustaining, functioning reef ecosystem" | X3: M2 | Y3: Restoring coral reef cover | Z3: Duka Bay Resort Inc. | AA3: Development | AB3: Local | AC3: Private | AD3: Private | AE3: Unknown | AF3: Unknown | AG3: Unknown | AH3: Duka Bay Resort Inc. | AI3: Private | AJ3: Private | AK3: Unknown | AL3: Ernesto Pelaez; Eduardo Yap | AM3: Unknown | AN3: Grey literature | AO3: News/Press Release | AP3: dela Cruz, R. (2006, April 24). Duka Bay: An ecological business paradigm. PhilStar Global. https://www.philstar.com/business/business-as-usual/2006/04/24/333050/duka-bay-ecological-business-paradigm | AQ3: https://www.philstar.com/business/business-as-usual/2006/04/24/333050/duka-bay-ecological-business-paradigm | AR3: Ernesto Pelaez | AS3: 0917 794 2759; 088-3312499
A4: 0279 | B4: =CONCATENATE(C4, "-", J4, "-", M4, "-", A4) -> 2025-PH072220000-2024-0279 | C4: =IF(OR(D4="Published", D4="Unpublished"), 2023, IF(D4="New", 2025, "")) -> 2025 | D4: New | E4: New | F4: No | G4: VII | H4: Cebu | I4: Cordova | J4: PH072220000 | K4: ACIAR Coral Reef Restoration Project | L4: Site inside Alegria MPA | M4: 2024 | N4: 2021 | O4: 2025 | P4: Sexual Propagation | Q4: Larval Enhancement | R4: Not applicable | S4: Not applicable | T4: Not applicable | U4: Not applicable | V4: Larval reseeding; "Mactan tiles" | W4: "Reestablish a self-sustaining, functioning reef ecosystem" | X4: M2 | Y4: Reef restoration | Z4: ACIAR | AA4: Research | AB4: International | AC4: Donor Agency | AD4: Donor Agency | AE4: Unknown | AF4: Unknown | AG4: Unknown | AH4: Southern Cross University | AI4: Academe | AJ4: Foreign Academic Entity | AK4: UP MSI; MLGU | AL4: Shangri-La Dive Resort | AM4: Unknown | AN4: Survey | AO4: Personal communication | AP4: Personal communication | AQ4: Unknown | AR4: Unknown | AS4: Unknown
A5: 0290 | B5: =CONCATENATE(C5, "-", J5, "-", M5, "-", A5) -> 2025-PH072226000-2024-0290 | C5: =IF(OR(D5="Published", D5="Unpublished"), 2023, IF(D5="New", 2025, "")) -> 2025 | D5: New | E5: New | F5: No | G5: VII | H5: Cebu | I5: City of Lapu-Lapu | J5: PH072226000 | K5: ACIAR Coral Reef Restoration Project | L5: Site inside MPA in Mactan Shangri-La Resort | M5: 2024 | N5: 2021 | O5: 2025 | P5: Sexual Propagation | Q5: Larval Enhancement | R5: Not applicable | S5: Not applicable | T5: Not applicable | U5: Not applicable | V5: Larval reseeding; "Mactan tiles" | W5: "Reestablish a self-sustaining, functioning reef ecosystem" | X5: M2 | Y5: Reef restoration | Z5: ACIAR | AA5: Research | AB5: International | AC5: Donor Agency | AD5: Donor Agency | AE5: Unknown | AF5: Unknown | AG5: Unknown | AH5: Southern Cross University | AI5: Academe | AJ5: Foreign Academic Entity | AK5: UP MSI; CLGU | AL5: Shangri-La Dive Resort | AM5: Unknown | AN5: Survey | AO5: Personal communication | AP5: Personal communication | AQ5: Unknown | AR5: Unknown | AS5: Unknown
A6: 0041 | B6: =CONCATENATE(C6, "-", J6, "-", M6, "-", A6) -> 2023-PH015503000-2018-0041 | C6: =IF(OR(D6="Published", D6="Unpublished"), 2023, IF(D6="New", 2025, "")) -> 2023 | D6: Published | E6: Modified | F6: No | G6: I | H6: Pangasinan | I6: City of Alaminos | J6: PH015503000 | K6: ACIAR Coral Reef Restoration Project | L6: Site in HINP | M6: 2018 | N6: Unknown | O6: Unknown | P6: Sexual Propagation | Q6: Larval Enhancement | R6: Not applicable | S6: Not applicable | T6: Not applicable | U6: Not applicable | V6: Larval reseeding | W6: "Reestablish a self-sustaining, functioning reef ecosystem" | X6: M2 | Y6: Enhanced larval supply and recruitment to replenish reef corals on degraded reefs | Z6: ACIAR | AA6: Development | AB6: International | AC6: Donor Agency | AD6: Donor Agency | AE6: Unknown | AF6: Unknown | AG6: Unknown | AH6: UP-MSI | AI6: Academe | AJ6: Public Academic Institutions | AK6: CLGU | AL6: Southern Cross University | AM6: Unknown | AN6: Survey | AO6: Personal communication | AP6: Personal communication | AQ6: Unknown | AR6: Unknown | AS6: Unknown
A7: 0048 | B7: =CONCATENATE(C7, "-", J7, "-", M7, "-", A7) -> 2023-PH015505000-2018-0048 | C7: =IF(OR(D7="Published", D7="Unpublished"), 2023, IF(D7="New", 2025, "")) -> 2023 | D7: Published | E7: Modified | F7: No | G7: I | H7: Pangasinan | I7: Anda | J7: PH015505000 | K7: ACIAR Coral Reef Restoration Project | L7: Site in Tanduyong Island | M7: 2018 | N7: Unknown | O7: Unknown | P7: Sexual Propagation | Q7: Larval Enhancement | R7: Not applicable | S7: Not applicable | T7: Not applicable | U7: Not applicable | V7: Larval reseeding | W7: "Reestablish a self-sustaining, functioning reef ecosystem" | X7: M2 | Y7: Enhanced larval supply and recruitment to replenish reef corals on degraded reefs | Z7: ACIAR | AA7: Development | AB7: International | AC7: Donor Agency | AD7: Donor Agency | AE7: Unknown | AF7: Unknown | AG7: Unknown | AH7: UP MSI | AI7: Academe | AJ7: Public Academic Institutions | AK7: Unknown | AL7: Southern Cross University | AM7: Unknown | AN7: Survey | AO7: Personal communication | AP7: Personal communication | AQ7: Unknown | AR7: Unknown | AS7: Unknown
A8: 0051 | B8: =CONCATENATE(C8, "-", J8, "-", M8, "-", A8) -> 2023-PH015505000-2013-0051 | C8: =IF(OR(D8="Published", D8="Unpublished"), 2023, IF(D8="New", 2025, "")) -> 2023 | D8: Published | E8: Modified | F8: Yes | G8: I | H8: Pangasinan | I8: Anda | J8: PH015505000 | K8: ACIAR Coral Reef Restoration Project | L8: Site in Magsaysay Reef (N 16.3213889, E 120.03388888888888) | M8: 2013 | N8: 2013 | O8: 2015 | P8: Sexual Propagation | Q8: Larval Enhancement | R8: Not applicable | S8: Not applicable | T8: Not applicable | U8: Not applicable | V8: Larval reseeding (settement tiles from larvae in fine-mesh enclosures) | W8: Scientific Research | X8: M7 | Y8: Test the effect of supplying large numbers of coral larvae on replicate degraded reef areas | Z8: ACIAR | AA8: Development | AB8: International | AC8: Donor Agency | AD8: Donor Agency | AE8: Unknown | AF8: Unknown | AG8: Unknown | AH8: Southern Cross University | AI8: Academe | AJ8: Foreign Academic Entity | AK8: University of the Philippines Diliman; UP MSI | AL8: Unknown | AM8: Unknown | AN8: Peer-reviewed | AO8: Journal Article | AP8: Dela Cruz, D. W., & Harrison, P. L. (2017). Enhanced larval supply and recruitment can replenish reef corals on degraded reefs. Scientific Reports 7(1). DOI:10.1038/s41598-017-14546-y | AQ8: https://www.researchgate.net/publication/320629634_Enhanced_larval_supply_and_recruitment_can_replenish_reef_corals_on_degraded_reefs; https://www.ncbi.nlm.nih.gov/pmc/articles/PMC7685485/ | AR8: Dr. Dexter dela Cruz | AS8: Unknown
A9: 0052 | B9: =CONCATENATE(C9, "-", J9, "-", M9, "-", A9) -> 2023-PH015505000-2016-0052 | C9: =IF(OR(D9="Published", D9="Unpublished"), 2023, IF(D9="New", 2025, "")) -> 2023 | D9: Published | E9: Modified | F9: Yes | G9: I | H9: Pangasinan | I9: Anda | J9: PH015505000 | K9: ACIAR Coral Reef Restoration Project | L9: Site in Magsaysay Reef | M9: 2016 | N9: 2016 | O9: 2019 | P9: Sexual Propagation | Q9: Larval Enhancement | R9: Not applicable | S9: Not applicable | T9: Not applicable | U9: Not applicable | V9: Larval reseeding (settement tiles from larvae in fine-mesh enclosures) | W9: Scientific Research | X9: M7 | Y9: Build on pilot study to quantify effects of increased larval supply, assess long term restoration outcomes and develop techniques for capturing large volume of coral spawns | Z9: ACIAR | AA9: Development | AB9: International | AC9: Donor Agency | AD9: Donor Agency | AE9: Unknown | AF9: Unknown | AG9: Unknown | AH9: Southern Cross University | AI9: Academe | AJ9: Foreign Academic Entity | AK9: University of the Philippines Diliman; UP MSI | AL9: Unknown | AM9: Unknown | AN9: Peer-reviewed | AO9: Journal Article | AP9: Harrison, P. L., Dela Cruz, D. W., Cameron, K., & Cabaitan, P. (2021). Increased Coral Larval Supply Enhances Recruitment for Coral and Fish Habitat Restoration. Frontiers in Marine Science, 8. DOI:10.3389/fmars.2021.750210 | AQ9: https://www.researchgate.net/publication/356725969_Increased_Coral_Larval_Supply_Enhances_Recruitment_for_Coral_and_Fish_Habitat_Restoration | AR9: Dr. Peter Harrison / Dr. Dexter dela Cruz | AS9: Unknown
A10: 0053 | B10: =CONCATENATE(C10, "-", J10, "-", M10, "-", A10) -> 2023-PH015505000-2021-0053 | C10: =IF(OR(D10="Published", D10="Unpublished"), 2023, IF(D10="New", 2025, "")) -> 2023 | D10: Published | E10: Modified | F10: No | G10: I | H10: Pangasinan | I10: Anda | J10: PH015505000 | K10: ACIAR Coral Reef Restoration Project | L10: Unknown | M10: 2021 | N10: 2021 | O10: 2025 | P10: Sexual Propagation | Q10: Larval Enhancement | R10: Not applicable | S10: Not applicable | T10: Not applicable | U10: Not applicable | V10: Larval reseeding | W10: Unknown | X10: UNK | Y10: Unknown | Z10: ACIAR | AA10: Development | AB10: International | AC10: Donor Agency | AD10: Donor Agency | AE10: Unknown | AF10: Unknown | AG10: Unknown | AH10: Southern Cross University | AI10: Academe | AJ10: Foreign Academic Entity | AK10: University of the Philippines Diliman; UP MSI | AL10: Unknown | AM10: Unknown | AN10: Survey | AO10: Personal communication | AP10: Unknown | AQ10: Unknown | AR10: Unknown | AS10: Unknown
A11: 0128 | B11: =CONCATENATE(C11, "-", J11, "-", M11, "-", A11) -> 2023-PH041019000-2012-0128 | C11: =IF(OR(D11="Published", D11="Unpublished"), 2023, IF(D11="New", 2025, "")) -> 2023 | D11: Published | E11: Modified | F11: Yes | G11: IV-A | H11: Batangas | I11: Nasugbu | J11: PH041019000 | K11: Adopt a Coral | L11: Site in Brgy Natiyuan | M11: 2012 | N11: Unknown | O11: Unknown | P11: Asexual Propagation, Substrate Enhancement | Q11: Artificial Reef, Direct Transplantation | R11: Concrete | S11: Concrete block | T11: Not applicable | U11: Not applicable | V11: Concrete block; coral transplantation | W11: "Reestablish a self-sustaining, functioning reef ecosystem", "Provide alternative, sustainable livelihood opportunities", Promote coral reef conservation stewardship | X11: M2, M6, M5 | Y11: Restore coral and marine environment; tourist attraction; promote image of the Rotary | Z11: Rotary Club of Makati Urdaneta | AA11: Development | AB11: Local | AC11: CSO | AD11: CSO | AE11: Unknown | AF11: Unknown | AG11: 200 blocks | AH11: Rotary Club of Makati Urdaneta | AI11: CSO | AJ11: CSO | AK11: MLGU; PNP; MENRO | AL11: Unknown | AM11: Unknown | AN11: Grey literature | AO11: News/Press Release | AP11: Pecayo, J. (2012, May 17). Rotary Club launches "Adopt a Coral" in Nasugbu. Manila-US Times. https://manilaustimes.wordpress.com/2012/05/17/rotary-club-launches-adopt-a-coral-in-nasugbu/ | AQ11: https://manilaustimes.wordpress.com/2012/05/17/rotary-club-launches-adopt-a-coral-in-nasugbu/; https://feed.org.ph/media-centre/press-releases-2015/adopt-a-coral-project-extends-its-outreach-through-feed/ | AR11: Unknown | AS11: Unknown
A12: 0356 | B12: =CONCATENATE(C12, "-", J12, "-", M12, "-", A12) -> 2023-PH104311000-Unknown-0356 | C12: =IF(OR(D12="Published", D12="Unpublished"), 2023, IF(D12="New", 2025, "")) -> 2023 | D12: Published | E12: Modified | F12: No | G12: X | H12: Misamis Oriental | I12: Jasaan | J12: PH104311000 | K12: Agutayan Artificial Reef Project and Giant Clam Seeding | L12: Site in Agutayan Island | M12: Unknown | N12: Unknown | O12: Unknown | P12: Substrate Enhancement | Q12: Artificial Reef | R12: Hybrid | S12: Tires, Steel frame, Unspecified concrete structure | T12: Not applicable | U12: Not applicable | V12: tires, concrete, steel | W12: Promote coral reef conservation stewardship | X12: M6 | Y12: Corporate social responsibility | Z12: Nestle | AA12: Development | AB12: Local | AC12: Private | AD12: Private | AE12: Unknown | AF12: Unknown | AG12: Unknown | AH12: Nestle | AI12: Private | AJ12: Private | AK12: Unknown | AL12: Rudy Trillanes | AM12: Unknown | AN12: Grey literature | AO12: Blog/Website | AP12: cbartazo (2008, April 16). Diving at Agutayan Island…October 13, 2007). Life in the Great Beyond [blog]. https://cbartazo.com/tag/agutayan-island/ | AQ12: https://cbartazo.com/tag/agutayan-island/; https://www.philstar.com/business/business-as-usual/2008/08/25/81412/rudy-trillanes-coffee-man; https://www.lakwatsero.com/dive-report/my-yearend-dive-at-agutayan-island-marine-sanctuary/ | AR12: Unknown | AS12: Unknown
A13: 0102 | B13: =CONCATENATE(C13, "-", J13, "-", M13, "-", A13) -> 2023-PH037105000-2022-0102 | C13: =IF(OR(D13="Published", D13="Unpublished"), 2023, IF(D13="New", 2025, "")) -> 2023 | D13: Published | E13: Modified | F13: No | G13: III | H13: Zambales | I13: Iba | J13: PH037105000 | K13: An Integrated Approach to Marine Resource Conservation and Sustainable Fisheries Management to Strengthen Coastal Communities in Zambales | L13: Unknown | M13: 2022 | N13: 2022 | O13: 2024 | P13: Asexual Propagation, Sexual Propagation | Q13: Larval Enhancement, Coral Gardening | R13: Not applicable | S13: Not applicable | T13: In-situ | U13: Unknown | V13: Coral trees; tree nursery | W13: Reduce population declines and ecosystem degradation, Promote coral reef conservation stewardship | X13: M4, M6 | Y13: Enhance fish stock; community education/engagement | Z13: Mead Foundation | AA13: Development | AB13: International | AC13: NGO | AD13: NGO | AE13: Unknown | AF13: Unknown | AG13: Unknown | AH13: Mead Foundation; UP MSI | AI13: NGO | AJ13: NGO | AK13: MLGU; DFAT | AL13: MERF; University of Southern Cross; ACIAR | AM13: Unknown | AN13: Survey | AO13: Questionnaire | AP13: Survey | AQ13: Unknown | AR13: Karen Chan; Mead Foundation | AS13: karen@mead-foundation.org; 09175111210
A14: 0230 | B14: =CONCATENATE(C14, "-", J14, "-", M14, "-", A14) -> 2023-PH060412000-Unknown-0230 | C14: =IF(OR(D14="Published", D14="Unpublished"), 2023, IF(D14="New", 2025, "")) -> 2023 | D14: Published | E14: Modified | F14: No | G14: VI | H14: Aklan | I14: Malay | J14: PH060412000 | K14: APEC PPSTI-5 | L14: Unknown | M14: Unknown | N14: Unknown | O14: Unknown | P14: Asexual Propagation | Q14: Coral Gardening | R14: Not applicable | S14: Not applicable | T14: In-situ | U14: CNU | V14: CNU | W14: Unknown | X14: UNK | Y14: Unknown | Z14: DOST-PCAARRD | AA14: Development | AB14: Local | AC14: Government - NGA | AD14: DOST | AE14: Unknown | AF14: Unknown | AG14: Unknown | AH14: Sangkalikasan Producers Cooperative, DOST | AI14: CSO | AJ14: CSO | AK14: Philippine Coast Guard; DOST | AL14: Sangkalikasan Producers Cooperative | AM14: Unknown | AN14: Grey literature | AO14: News/Press Release | AP14: Carlos, M. B., Surara, C. A., & Mananghaya, R. A. (2016, February 12). Restoring the country's coral reefs through Filippinovation. DOST-PCAARRD. https://www.pcaarrd.dost.gov.ph/index.php/quick-information-dispatch-qid-articles/restoring-the-country-s-coral-reefs-through-filipinnovation | AQ14: https://www.pcaarrd.dost.gov.ph/index.php/quick-information-dispatch-qid-articles/restoring-the-country-s-coral-reefs-through-filipinnovation | AR14: Unknown | AS14: Unknown
A15: 0374 | B15: =CONCATENATE(C15, "-", J15, "-", M15, "-", A15) -> 2023-PH112319000-2007-0374 | C15: =IF(OR(D15="Published", D15="Unpublished"), 2023, IF(D15="New", 2025, "")) -> 2023 | D15: Published | E15: Modified | F15: No | G15: XI | H15: Davao del Norte | I15: City of Tagum | J15: PH112319000 | K15: Artificial Coral Reef Project | L15: Site inside 22-ha MPA in Brgy Liboganon | M15: 2007 | N15: 2007 | O15: 2016 | P15: Substrate Enhancement | Q15: Artificial Reef | R15: Engineered/Advanced | S15: Reef ball | T15: Not applicable | U15: Not applicable | V15: Reef ball | W15: "Reestablish a self-sustaining, functioning reef ecosystem" | X15: M2 | Y15: Improve marine life | Z15: CLGU | AA15: Development | AB15: Local | AC15: Government - LGU | AD15: CLGU | AE15: Unknown | AF15: 3.00 ha | AG15: 200 reef balls | AH15: CLGU | AI15: Government - LGU | AJ15: CLGU | AK15: DENR | AL15: Unknown | AM15: Unknown | AN15: Grey literature | AO15: News/Press Release | AP15: Mayuga, J. (2017, March 26). Tagum City cites artificial reef project, supports "MPA networking" initiative. Business Mirror. https://businessmirror.com.ph/2017/03/26/tagum-city-cites-artificial-reef-project-supports-mpa-networking-initiative/ | AQ15: https://businessmirror.com.ph/2017/03/26/tagum-city-cites-artificial-reef-project-supports-mpa-networking-initiative/; https://mobile.facebook.com/DistinctivelyDavao/posts/tagum-city-cites-artificial-reef-project-supports-mpa-networking-initiativetagum/283751215413471/?_rdc=1&_rdr | AR15: Unknown | AS15: Unknown
A16: 0404 | B16: =CONCATENATE(C16, "-", J16, "-", M16, "-", A16) -> 2023-PH166724000-2018-0404 | C16: =IF(OR(D16="Published", D16="Unpublished"), 2023, IF(D16="New", 2025, "")) -> 2023 | D16: Published | E16: Modified | F16: No | G16: XIII | H16: Surigao del Norte | I16: City of Surigao | J16: PH166724000 | K16: Artificial Coral Reefs | L16: Site in Brgy Sugbay and Brgy Manjagao | M16: 2018 | N16: Unknown | O16: Unknown | P16: Substrate Enhancement | Q16: Artificial Reef | R16: Concrete | S16: Unspecified concrete structure | T16: Not applicable | U16: Not applicable | V16: Concrete | W16: "Reestablish a self-sustaining, functioning reef ecosystem" | X16: M2 | Y16: Shelter and breeding ground for fish | Z16: Unknown | AA16: Development | AB16: Unknown | AC16: Unknown | AD16: Unknown | AE16: Unknown | AF16: Unknown | AG16: Unknown | AH16: CLGU | AI16: Government - LGU | AJ16: CLGU | AK16: Unknown | AL16: Unknown | AM16: Unknown | AN16: Grey literature | AO16: News/Press Release | AP16: Bombo Butuan Newsdesk (2018, March 19). Artificial coral reefs, gimontar sa Surigao City. Bombo Radyo. https://butuan.bomboradyo.com/artificial-coral-reefs-gimontar-sa-surigao-city/ | AQ16: https://butuan.bomboradyo.com/artificial-coral-reefs-gimontar-sa-surigao-city/ | AR16: Unknown | AS16: Unknown
A17: 0391 | B17: =CONCATENATE(C17, "-", J17, "-", M17, "-", A17) -> 2023-PH128004000-2009-0391 | C17: =IF(OR(D17="Published", D17="Unpublished"), 2023, IF(D17="New", 2025, "")) -> 2023 | D17: Published | E17: Modified | F17: Yes | G17: XII | H17: Sarangani | I17: Maasim | J17: PH128004000 | K17: Artificial Reef Deployment Project | L17: Unknown | M17: 2009 | N17: 2009 | O17: 2015 | P17: Substrate Enhancement | Q17: Artificial Reef | R17: Concrete | S17: Concrete domes | T17: Not applicable | U17: Not applicable | V17: Domes | W17: "Reestablish a self-sustaining, functioning reef ecosystem", Reduce population declines and ecosystem degradation, Promote coral reef conservation stewardship | X17: M2, M4, M6 | Y17: Restore marine and coastal life; restore fishery resources; breeding ground; corporate social responsibility | Z17: Conrado and Ladislawa Alcantara Foundation; Holcim Cement | AA17: Development | AB17: Local | AC17: NGO | AD17: NGO | AE17: Unknown | AF17: Unknown | AG17: 4,300 units | AH17: Conrado and Ladislawa Alcantara Foundation | AI17: NGO | AJ17: NGO | AK17: MLGU | AL17: Sarangani Energy Corporation | AM17: Unknown | AN17: Grey literature | AO17: News/Press Release | AP17: The Philippine Star (2015, November 23). Sarangani's Kamanga Marine Eco-tourism Park and Sanctuary cited as one of Philippine's best. PhilStar Global. https://www.philstar.com/other-sections/the-good-news/2015/11/23/1524749/saranganis-kamanga-marine-eco-tourism-park-and-sanctuary-cited-one-philippines-best | AQ17: https://www.philstar.com/other-sections/the-good-news/2015/11/23/1524749/saranganis-kamanga-marine-eco-tourism-park-and-sanctuary-cited-one-philippines-best; https://www.sunstar.com.ph/more-articles/artificial-reef-to-be-deployed-in-sarangani-bay | AR17: Unknown | AS17: Unknown | AT17: Project_end is based on the year the article was published (as it was mentioned that restoration started in 2009).
A18: 0393 | B18: =CONCATENATE(C18, "-", J18, "-", M18, "-", A18) -> 2023-PH128006000-2015-0393 | C18: =IF(OR(D18="Published", D18="Unpublished"), 2023, IF(D18="New", 2025, "")) -> 2023 | D18: Published | E18: Modified | F18: No | G18: XII | H18: Sarangani | I18: Malapatan | J18: PH128006000 | K18: Artificial Reef Deployment Project | L18: Unknown | M18: 2015 | N18: Unknown | O18: Unknown | P18: Substrate Enhancement | Q18: Artificial Reef | R18: Concrete | S18: Concrete domes | T18: Not applicable | U18: Not applicable | V18: Domes | W18: Unknown | X18: UNK | Y18: Unknown | Z18: Conrado and Ladislawa Alcantara Foundation | AA18: Development | AB18: Local | AC18: NGO | AD18: NGO | AE18: Unknown | AF18: Unknown | AG18: 300 units | AH18: Conrado and Ladislawa Alcantara Foundation | AI18: NGO | AJ18: NGO | AK18: Unknown | AL18: Unknown | AM18: Unknown | AN18: Grey literature | AO18: Blog/Website | AP18: Artificial Reef Dome. (n.d.). Our work: Environment protection and conservation projects. Conrado & Ladislawa Alcantara Foundation. https://clafi.org/our_work_categories/environment-protection-and-conservation-projects/ | AQ18: https://clafi.org/our_work_categories/environment-protection-and-conservation-projects/ | AR18: Unknown | AS18: Unknown
A19: 0003 | B19: =CONCATENATE(C19, "-", J19, "-", M19, "-", A19) -> 2023-PH012812000-1986-0003 | C19: =IF(OR(D19="Published", D19="Unpublished"), 2023, IF(D19="New", 2025, "")) -> 2023 | D19: Published | E19: Modified | F19: Yes | G19: I | H19: Ilocos Norte | I19: City of Laoag | J19: PH012812000 | K19: Artificial Reef Development Program | L19: Site in Calayab | M19: 1986 | N19: 1985 | O19: 1987 | P19: Substrate Enhancement | Q19: Artificial Reef | R19: Tires | S19: Tires | T19: Not applicable | U19: Not applicable | V19: Tires | W19: "Reestablish a self-sustaining, functioning reef ecosystem", Reduce population declines and ecosystem degradation, "Provide alternative, sustainable livelihood opportunities" | X19: M2, M4, M5 | Y19: Support the government's food productivity, environmental protection and enhancement efforts; Support sustenance fishery; enhance and restore habitats; costal fishery management | Z19: BFAR | AA19: Development | AB19: Local | AC19: Government - NGA | AD19: BFAR | AE19: Unknown | AF19: Unknown | AG19: 10 TM | AH19: BFAR | AI19: Government - NGA | AJ19: BFAR | AK19: Ministry of Human Settlements; Government organizations | AL19: NGOs | AM19: People's organizations; Fisher's associations | AN19: Peer-reviewed | AO19: Conference Proceeding | AP19: Balgos, M. C. (1995). Evaluation of artificial reef development in the Philippines. In J. L. Munro & M. C. Balgos (Eds.), Artificial reefs in the Philippines (ICLARM Conference Proceedings No. 49, pp. 6–22). International Center for Living Aquatic Resources Management (ICLARM). | AQ19: https://core.ac.uk/download/pdf/6515223.pdf; https://www.ircwash.org/sites/default/files/802-PH90-8920.pdf | AR19: Miriam Balgos | AS19: Unknown
A20: 0005 | B20: =CONCATENATE(C20, "-", J20, "-", M20, "-", A20) -> 2023-PH012817000-1986-0005 | C20: =IF(OR(D20="Published", D20="Unpublished"), 2023, IF(D20="New", 2025, "")) -> 2023 | D20: Published | E20: Modified | F20: Yes | G20: I | H20: Ilocos Norte | I20: Pasuquin | J20: PH012817000 | K20: Artificial Reef Development Program | L20: Site in Puyupuyan | M20: 1986 | N20: 1985 | O20: 1987 | P20: Substrate Enhancement | Q20: Artificial Reef | R20: Tires | S20: Tires | T20: Not applicable | U20: Not applicable | V20: Tires | W20: "Reestablish a self-sustaining, functioning reef ecosystem", Reduce population declines and ecosystem degradation, "Provide alternative, sustainable livelihood opportunities" | X20: M2, M4, M5 | Y20: Support the government's food productivity, environmental protection and enhancement efforts; Support sustenance fishery; enhance and restore habitats; costal fishery management | Z20: BFAR | AA20: Development | AB20: Local | AC20: Government - NGA | AD20: BFAR | AE20: Unknown | AF20: Unknown | AG20: 10 TM | AH20: BFAR | AI20: Government - NGA | AJ20: BFAR | AK20: Ministry of Human Settlements; Government organizations | AL20: NGOs | AM20: People's organizations; Fisher's associations | AN20: Peer-reviewed | AO20: Conference Proceeding | AP20: Balgos, M. C. (1995). Evaluation of artificial reef development in the Philippines. In J. L. Munro & M. C. Balgos (Eds.), Artificial reefs in the Philippines (ICLARM Conference Proceedings No. 49, pp. 6–22). International Center for Living Aquatic Resources Management (ICLARM). | AQ20: https://core.ac.uk/download/pdf/6515223.pdf; https://www.ircwash.org/sites/default/files/802-PH90-8920.pdf | AR20: Miriam Balgos | AS20: Unknown
A21: 0008 | B21: =CONCATENATE(C21, "-", J21, "-", M21, "-", A21) -> 2023-PH012905000-1986-0008 | C21: =IF(OR(D21="Published", D21="Unpublished"), 2023, IF(D21="New", 2025, "")) -> 2023 | D21: Published | E21: Modified | F21: Yes | G21: I | H21: Ilocos Sur | I21: Cabugao | J21: PH012905000 | K21: Artificial Reef Development Program | L21: Site in Pung-os | M21: 1986 | N21: 1985 | O21: 1987 | P21: Substrate Enhancement | Q21: Artificial Reef | R21: Tires | S21: Tires | T21: Not applicable | U21: Not applicable | V21: Tires | W21: "Reestablish a self-sustaining, functioning reef ecosystem", Reduce population declines and ecosystem degradation, "Provide alternative, sustainable livelihood opportunities" | X21: M2, M4, M5 | Y21: Support the government's food productivity, environmental protection and enhancement efforts; Support sustenance fishery; enhance and restore habitats; costal fishery management | Z21: BFAR | AA21: Development | AB21: Local | AC21: Government - NGA | AD21: BFAR | AE21: Unknown | AF21: Unknown | AG21: 10 TM | AH21: BFAR | AI21: Government - NGA | AJ21: BFAR | AK21: Ministry of Human Settlements; Government organizations | AL21: NGOs | AM21: People's organizations; Fisher's associations | AN21: Peer-reviewed | AO21: Conference Proceeding | AP21: Balgos, M. C. (1995). Evaluation of artificial reef development in the Philippines. In J. L. Munro & M. C. Balgos (Eds.), Artificial reefs in the Philippines (ICLARM Conference Proceedings No. 49, pp. 6–22). International Center for Living Aquatic Resources Management (ICLARM). | AQ21: https://core.ac.uk/download/pdf/6515223.pdf; https://www.ircwash.org/sites/default/files/802-PH90-8920.pdf | AR21: Miriam Balgos | AS21: Unknown
A22: 0009 | B22: =CONCATENATE(C22, "-", J22, "-", M22, "-", A22) -> 2023-PH012905000-1986-0009 | C22: =IF(OR(D22="Published", D22="Unpublished"), 2023, IF(D22="New", 2025, "")) -> 2023 | D22: Published | E22: Modified | F22: Yes | G22: I | H22: Ilocos Sur | I22: Cabugao | J22: PH012905000 | K22: Artificial Reef Development Program | L22: Site in Namruangan | M22: 1986 | N22: 1985 | O22: 1987 | P22: Substrate Enhancement | Q22: Artificial Reef | R22: Tires | S22: Tires | T22: Not applicable | U22: Not applicable | V22: Tires | W22: "Reestablish a self-sustaining, functioning reef ecosystem", Reduce population declines and ecosystem degradation, "Provide alternative, sustainable livelihood opportunities" | X22: M2, M4, M5 | Y22: Support the government's food productivity, environmental protection and enhancement efforts; Support sustenance fishery; enhance and restore habitats; costal fishery management | Z22: BFAR | AA22: Development | AB22: Local | AC22: Government - NGA | AD22: BFAR | AE22: Unknown | AF22: Unknown | AG22: 10 TM | AH22: BFAR | AI22: Government - NGA | AJ22: BFAR | AK22: Ministry of Human Settlements; Government organizations | AL22: NGOs | AM22: People's organizations; Fisher's associations | AN22: Peer-reviewed | AO22: Conference Proceeding | AP22: Balgos, M. C. (1995). Evaluation of artificial reef development in the Philippines. In J. L. Munro & M. C. Balgos (Eds.), Artificial reefs in the Philippines (ICLARM Conference Proceedings No. 49, pp. 6–22). International Center for Living Aquatic Resources Management (ICLARM). | AQ22: https://core.ac.uk/download/pdf/6515223.pdf; https://www.ircwash.org/sites/default/files/802-PH90-8920.pdf | AR22: Miriam Balgos | AS22: Unknown
A23: 0011 | B23: =CONCATENATE(C23, "-", J23, "-", M23, "-", A23) -> 2023-PH012906000-1986-0011 | C23: =IF(OR(D23="Published", D23="Unpublished"), 2023, IF(D23="New", 2025, "")) -> 2023 | D23: Published | E23: Modified | F23: Yes | G23: I | H23: Ilocos Sur | I23: City of Candon | J23: PH012906000 | K23: Artificial Reef Development Program | L23: Site in Calongbuyan | M23: 1986 | N23: 1985 | O23: 1987 | P23: Substrate Enhancement | Q23: Artificial Reef | R23: Tires | S23: Tires | T23: Not applicable | U23: Not applicable | V23: Tires | W23: "Reestablish a self-sustaining, functioning reef ecosystem", Reduce population declines and ecosystem degradation, "Provide alternative, sustainable livelihood opportunities" | X23: M2, M4, M5 | Y23: Support the government's food productivity, environmental protection and enhancement efforts; Support sustenance fishery; enhance and restore habitats; costal fishery management | Z23: BFAR | AA23: Development | AB23: Local | AC23: Government - NGA | AD23: BFAR | AE23: Unknown | AF23: Unknown | AG23: 8 TM | AH23: BFAR | AI23: Government - NGA | AJ23: BFAR | AK23: Ministry of Human Settlements; Government organizations | AL23: NGOs | AM23: People's organizations; Fisher's associations | AN23: Peer-reviewed | AO23: Conference Proceeding | AP23: Balgos, M. C. (1995). Evaluation of artificial reef development in the Philippines. In J. L. Munro & M. C. Balgos (Eds.), Artificial reefs in the Philippines (ICLARM Conference Proceedings No. 49, pp. 6–22). International Center for Living Aquatic Resources Management (ICLARM). | AQ23: https://core.ac.uk/download/pdf/6515223.pdf; https://www.ircwash.org/sites/default/files/802-PH90-8920.pdf | AR23: Miriam Balgos | AS23: Unknown
A24: 0013 | B24: =CONCATENATE(C24, "-", J24, "-", M24, "-", A24) -> 2023-PH012914000-1986-0013 | C24: =IF(OR(D24="Published", D24="Unpublished"), 2023, IF(D24="New", 2025, "")) -> 2023 | D24: Published | E24: Modified | F24: Yes | G24: I | H24: Ilocos Sur | I24: Narvacan | J24: PH012914000 | K24: Artificial Reef Development Program | L24: Site in Pantoc | M24: 1986 | N24: 1985 | O24: 1987 | P24: Substrate Enhancement | Q24: Artificial Reef | R24: Tires | S24: Tires | T24: Not applicable | U24: Not applicable | V24: Tires | W24: "Reestablish a self-sustaining, functioning reef ecosystem", Reduce population declines and ecosystem degradation, "Provide alternative, sustainable livelihood opportunities" | X24: M2, M4, M5 | Y24: Support the government's food productivity, environmental protection and enhancement efforts; Support sustenance fishery; enhance and restore habitats; costal fishery management | Z24: BFAR | AA24: Development | AB24: Local | AC24: Government - NGA | AD24: BFAR | AE24: Unknown | AF24: Unknown | AG24: 8 TM | AH24: BFAR | AI24: Government - NGA | AJ24: BFAR | AK24: Ministry of Human Settlements; Government organizations | AL24: NGOs | AM24: People's organizations; Fisher's associations | AN24: Peer-reviewed | AO24: Conference Proceeding | AP24: Balgos, M. C. (1995). Evaluation of artificial reef development in the Philippines. In J. L. Munro & M. C. Balgos (Eds.), Artificial reefs in the Philippines (ICLARM Conference Proceedings No. 49, pp. 6–22). International Center for Living Aquatic Resources Management (ICLARM). | AQ24: https://core.ac.uk/download/pdf/6515223.pdf; https://www.ircwash.org/sites/default/files/802-PH90-8920.pdf | AR24: Miriam Balgos | AS24: Unknown
A25: 0014 | B25: =CONCATENATE(C25, "-", J25, "-", M25, "-", A25) -> 2023-PH012924000-1986-0014 | C25: =IF(OR(D25="Published", D25="Unpublished"), 2023, IF(D25="New", 2025, "")) -> 2023 | D25: Published | E25: Modified | F25: Yes | G25: I | H25: Ilocos Sur | I25: Santa Cruz | J25: PH012924000 | K25: Artificial Reef Development Program | L25: Site in Pilar | M25: 1986 | N25: 1985 | O25: 1987 | P25: Substrate Enhancement | Q25: Artificial Reef | R25: Tires | S25: Tires | T25: Not applicable | U25: Not applicable | V25: Tires | W25: "Reestablish a self-sustaining, functioning reef ecosystem", Reduce population declines and ecosystem degradation, "Provide alternative, sustainable livelihood opportunities" | X25: M2, M4, M5 | Y25: Support the government's food productivity, environmental protection and enhancement efforts; Support sustenance fishery; enhance and restore habitats; costal fishery management | Z25: BFAR | AA25: Development | AB25: Local | AC25: Government - NGA | AD25: BFAR | AE25: Unknown | AF25: Unknown | AG25: 8 TM | AH25: BFAR | AI25: Government - NGA | AJ25: BFAR | AK25: Ministry of Human Settlements; Government organizations | AL25: NGOs | AM25: People's organizations; Fisher's associations | AN25: Peer-reviewed | AO25: Conference Proceeding | AP25: Balgos, M. C. (1995). Evaluation of artificial reef development in the Philippines. In J. L. Munro & M. C. Balgos (Eds.), Artificial reefs in the Philippines (ICLARM Conference Proceedings No. 49, pp. 6–22). International Center for Living Aquatic Resources Management (ICLARM). | AQ25: https://core.ac.uk/download/pdf/6515223.pdf; https://www.ircwash.org/sites/default/files/802-PH90-8920.pdf | AR25: Miriam Balgos | AS25: Unknown
A26: 0016 | B26: =CONCATENATE(C26, "-", J26, "-", M26, "-", A26) -> 2023-PH012930000-1986-0016 | C26: =IF(OR(D26="Published", D26="Unpublished"), 2023, IF(D26="New", 2025, "")) -> 2023 | D26: Published | E26: Modified | F26: Yes | G26: I | H26: Ilocos Sur | I26: Sinait | J26: PH012930000 | K26: Artificial Reef Development Program | L26: Site in Katipunan | M26: 1986 | N26: 1985 | O26: 1987 | P26: Substrate Enhancement | Q26: Artificial Reef | R26: Tires | S26: Tires | T26: Not applicable | U26: Not applicable | V26: Tires | W26: "Reestablish a self-sustaining, functioning reef ecosystem", Reduce population declines and ecosystem degradation, "Provide alternative, sustainable livelihood opportunities" | X26: M2, M4, M5 | Y26: Support the government's food productivity, environmental protection and enhancement efforts; Support sustenance fishery; enhance and restore habitats; costal fishery management | Z26: BFAR | AA26: Development | AB26: Local | AC26: Government - NGA | AD26: BFAR | AE26: Unknown | AF26: Unknown | AG26: 10 TM | AH26: BFAR | AI26: Government - NGA | AJ26: BFAR | AK26: Ministry of Human Settlements; Government organizations | AL26: NGOs | AM26: People's organizations; Fisher's associations | AN26: Peer-reviewed | AO26: Conference Proceeding | AP26: Balgos, M. C. (1995). Evaluation of artificial reef development in the Philippines. In J. L. Munro & M. C. Balgos (Eds.), Artificial reefs in the Philippines (ICLARM Conference Proceedings No. 49, pp. 6–22). International Center for Living Aquatic Resources Management (ICLARM). | AQ26: https://core.ac.uk/download/pdf/6515223.pdf; https://www.ircwash.org/sites/default/files/802-PH90-8920.pdf | AR26: Miriam Balgos | AS26: Unknown
A27: 0017 | B27: =CONCATENATE(C27, "-", J27, "-", M27, "-", A27) -> 2023-PH012933000-1986-0017 | C27: =IF(OR(D27="Published", D27="Unpublished"), 2023, IF(D27="New", 2025, "")) -> 2023 | D27: Published | E27: Modified | F27: Yes | G27: I | H27: Ilocos Sur | I27: Tagudin | J27: PH012933000 | K27: Artificial Reef Development Program | L27: Site in Becques | M27: 1986 | N27: 1985 | O27: 1987 | P27: Substrate Enhancement | Q27: Artificial Reef | R27: Tires | S27: Tires | T27: Not applicable | U27: Not applicable | V27: Tires | W27: "Reestablish a self-sustaining, functioning reef ecosystem", Reduce population declines and ecosystem degradation, "Provide alternative, sustainable livelihood opportunities" | X27: M2, M4, M5 | Y27: Support the government's food productivity, environmental protection and enhancement efforts; Support sustenance fishery; enhance and restore habitats; costal fishery management | Z27: BFAR | AA27: Development | AB27: Local | AC27: Government - NGA | AD27: BFAR | AE27: Unknown | AF27: Unknown | AG27: 7 TM | AH27: BFAR | AI27: Government - NGA | AJ27: BFAR | AK27: Ministry of Human Settlements; Government organizations | AL27: NGOs | AM27: People's organizations; Fisher's associations | AN27: Peer-reviewed | AO27: Conference Proceeding | AP27: Balgos, M. C. (1995). Evaluation of artificial reef development in the Philippines. In J. L. Munro & M. C. Balgos (Eds.), Artificial reefs in the Philippines (ICLARM Conference Proceedings No. 49, pp. 6–22). International Center for Living Aquatic Resources Management (ICLARM). | AQ27: https://core.ac.uk/download/pdf/6515223.pdf; https://www.ircwash.org/sites/default/files/802-PH90-8920.pdf | AR27: Miriam Balgos | AS27: Unknown
A28: 0018 | B28: =CONCATENATE(C28, "-", J28, "-", M28, "-", A28) -> 2023-PH012934000-1986-0018 | C28: =IF(OR(D28="Published", D28="Unpublished"), 2023, IF(D28="New", 2025, "")) -> 2023 | D28: Published | E28: Modified | F28: Yes | G28: I | H28: Ilocos Sur | I28: City of Vigan | J28: PH012934000 | K28: Artificial Reef Development Program | L28: Site in San Pedro | M28: 1986 | N28: 1985 | O28: 1987 | P28: Substrate Enhancement | Q28: Artificial Reef | R28: Tires | S28: Tires | T28: Not applicable | U28: Not applicable | V28: Tires | W28: "Reestablish a self-sustaining, functioning reef ecosystem", Reduce population declines and ecosystem degradation, "Provide alternative, sustainable livelihood opportunities" | X28: M2, M4, M5 | Y28: Support the government's food productivity, environmental protection and enhancement efforts; Support sustenance fishery; enhance and restore habitats; costal fishery management | Z28: BFAR | AA28: Development | AB28: Local | AC28: Government - NGA | AD28: BFAR | AE28: Unknown | AF28: Unknown | AG28: 9 TM | AH28: BFAR | AI28: Government - NGA | AJ28: BFAR | AK28: Ministry of Human Settlements; Government organizations | AL28: NGOs | AM28: People's organizations; Fisher's associations | AN28: Peer-reviewed | AO28: Conference Proceeding | AP28: Balgos, M. C. (1995). Evaluation of artificial reef development in the Philippines. In J. L. Munro & M. C. Balgos (Eds.), Artificial reefs in the Philippines (ICLARM Conference Proceedings No. 49, pp. 6–22). International Center for Living Aquatic Resources Management (ICLARM). | AQ28: https://core.ac.uk/download/pdf/6515223.pdf; https://www.ircwash.org/sites/default/files/802-PH90-8920.pdf | AR28: Miriam Balgos | AS28: Unknown
A29: 0020 | B29: =CONCATENATE(C29, "-", J29, "-", M29, "-", A29) -> 2023-PH013302000-1986-0020 | C29: =IF(OR(D29="Published", D29="Unpublished"), 2023, IF(D29="New", 2025, "")) -> 2023 | D29: Published | E29: Modified | F29: Yes | G29: I | H29: La Union | I29: Aringay | J29: PH013302000 | K29: Artificial Reef Development Program | L29: Site in Dulao | M29: 1986 | N29: 1985 | O29: 1987 | P29: Substrate Enhancement | Q29: Artificial Reef | R29: Tires | S29: Tires | T29: Not applicable | U29: Not applicable | V29: Tires | W29: "Reestablish a self-sustaining, functioning reef ecosystem", Reduce population declines and ecosystem degradation, "Provide alternative, sustainable livelihood opportunities" | X29: M2, M4, M5 | Y29: Support the government's food productivity, environmental protection and enhancement efforts; Support sustenance fishery; enhance and restore habitats; costal fishery management | Z29: BFAR | AA29: Development | AB29: Local | AC29: Government - NGA | AD29: BFAR | AE29: Unknown | AF29: Unknown | AG29: 10 TM | AH29: BFAR | AI29: Government - NGA | AJ29: BFAR | AK29: Ministry of Human Settlements; Government organizations | AL29: NGOs | AM29: People's organizations; Fisher's associations | AN29: Peer-reviewed | AO29: Conference Proceeding | AP29: Balgos, M. C. (1995). Evaluation of artificial reef development in the Philippines. In J. L. Munro & M. C. Balgos (Eds.), Artificial reefs in the Philippines (ICLARM Conference Proceedings No. 49, pp. 6–22). International Center for Living Aquatic Resources Management (ICLARM). | AQ29: https://core.ac.uk/download/pdf/6515223.pdf; https://www.ircwash.org/sites/default/files/802-PH90-8920.pdf | AR29: Miriam Balgos | AS29: Unknown
A30: 0024 | B30: =CONCATENATE(C30, "-", J30, "-", M30, "-", A30) -> 2023-PH013306000-1986-0024 | C30: =IF(OR(D30="Published", D30="Unpublished"), 2023, IF(D30="New", 2025, "")) -> 2023 | D30: Published | E30: Modified | F30: Yes | G30: I | H30: La Union | I30: Bangar | J30: PH013306000 | K30: Artificial Reef Development Program | L30: Site in Mindoro | M30: 1986 | N30: 1985 | O30: 1987 | P30: Substrate Enhancement | Q30: Artificial Reef | R30: Unknown | S30: Unknown | T30: Not applicable | U30: Not applicable | V30: Unknown | W30: "Reestablish a self-sustaining, functioning reef ecosystem", Reduce population declines and ecosystem degradation, "Provide alternative, sustainable livelihood opportunities" | X30: M2, M4, M5 | Y30: Support the government's food productivity, environmental protection and enhancement efforts; Support sustenance fishery; enhance and restore habitats; costal fishery management | Z30: BFAR | AA30: Development | AB30: Local | AC30: Government - NGA | AD30: BFAR | AE30: Unknown | AF30: Unknown | AG30: Unknown | AH30: BFAR | AI30: Government - NGA | AJ30: BFAR | AK30: Ministry of Human Settlements; Government organizations | AL30: NGOs | AM30: People's organizations; Fisher's associations | AN30: Peer-reviewed | AO30: Conference Proceeding | AP30: Balgos, M. C. (1995). Evaluation of artificial reef development in the Philippines. In J. L. Munro & M. C. Balgos (Eds.), Artificial reefs in the Philippines (ICLARM Conference Proceedings No. 49, pp. 6–22). International Center for Living Aquatic Resources Management (ICLARM). | AQ30: https://core.ac.uk/download/pdf/6515223.pdf; https://www.ircwash.org/sites/default/files/802-PH90-8920.pdf | AR30: Miriam Balgos | AS30: Unknown
... A73: 0409 | B73: =CONCATENATE(C73, "-", J73, "-", M73, "-", A73) -> 2023-PH133900000-1985-0409 | C73: =IF(OR(D73="Published", D73="Unpublished"), 2023, IF(D73="New", 2025, "")) -> 2023 | D73: Published | E73: Modified | F73: Yes | G73: NCR | H73: Metro Manila | I73: City of Manila | J73: PH133900000 | K73: Artificial Reef Development Program | L73: Site in Manila Bay Fish Sanctuary (Port Area) fronting Navotas and Tondo area in Manila and Orion in Bataan | M73: 1985 | N73: 1985 | O73: 1987 | P73: Substrate Enhancement | Q73: Artificial Reef | R73: Tires | S73: Tires | T73: Not applicable | U73: Not applicable | V73: Tires | W73: "Reestablish a self-sustaining, functioning reef ecosystem", Reduce population declines and ecosystem degradation, "Provide alternative, sustainable livelihood opportunities" | X73: M2, M4, M5 | Y73: Support the government's food productivity, environmental protection and enhancement efforts; Support sustenance fishery; enhance and restore habitats; costal fishery management | Z73: BFAR | AA73: Development | AB73: Local | AC73: Government - NGA | AD73: BFAR | AE73: Unknown | AF73: Unknown | AG73: 8 TM | AH73: BFAR | AI73: Government - NGA | AJ73: BFAR | AK73: Ministry of Human Settlements; Government organizations | AL73: NGOs | AM73: People's organizations; Fisher's associations | AN73: Peer-reviewed | AO73: Conference Proceeding | AP73: Balgos, M. C. (1995). Evaluation of artificial reef development in the Philippines. In J. L. Munro & M. C. Balgos (Eds.), Artificial reefs in the Philippines (ICLARM Conference Proceedings No. 49, pp. 6–22). International Center for Living Aquatic Resources Management (ICLARM). | AQ73: https://core.ac.uk/download/pdf/6515223.pdf | AR73: Miriam Balgos | AS73: Unknown
A74: 0410 | B74: =CONCATENATE(C74, "-", J74, "-", M74, "-", A74) -> 2023-PH064501000-1986-0410 | C74: =IF(OR(D74="Published", D74="Unpublished"), 2023, IF(D74="New", 2025, "")) -> 2023 | D74: Published | E74: Modified | F74: Yes | G74: NIR | H74: Negros Occidental | I74: City of Bacolod | J74: PH064501000 | K74: Artificial Reef Development Program | L74: Site in Banago | M74: 1986 | N74: 1985 | O74: 1987 | P74: Substrate Enhancement | Q74: Artificial Reef | R74: Tires | S74: Tires | T74: Not applicable | U74: Not applicable | V74: Tires | W74: "Reestablish a self-sustaining, functioning reef ecosystem", Reduce population declines and ecosystem degradation, "Provide alternative, sustainable livelihood opportunities" | X74: M2, M4, M5 | Y74: Support the government's food productivity, environmental protection and enhancement efforts; Support sustenance fishery; enhance and restore habitats; costal fishery management | Z74: BFAR | AA74: Development | AB74: Local | AC74: Government - NGA | AD74: BFAR | AE74: Unknown | AF74: Unknown | AG74: 10 TM | AH74: BFAR | AI74: Government - NGA | AJ74: BFAR | AK74: Ministry of Human Settlements; Government organizations | AL74: NGOs | AM74: People's organizations; Fisher's associations | AN74: Peer-reviewed | AO74: Conference Proceeding | AP74: Balgos, M. C. (1995). Evaluation of artificial reef development in the Philippines. In J. L. Munro & M. C. Balgos (Eds.), Artificial reefs in the Philippines (ICLARM Conference Proceedings No. 49, pp. 6–22). International Center for Living Aquatic Resources Management (ICLARM). | AQ74: https://core.ac.uk/download/pdf/6515223.pdf | AR74: Miriam Balgos | AS74: Unknown | AT74: 10 modules were also deployed in Sangwa, Bangsua in Negros Occidental but this place does not match any current records
A75: 0428 | B75: =CONCATENATE(C75, "-", J75, "-", M75, "-", A75) -> 2023-PH074619000-1986-0428 | C75: =IF(OR(D75="Published", D75="Unpublished"), 2023, IF(D75="New", 2025, "")) -> 2023 | D75: Published | E75: Modified | F75: Yes | G75: NIR | H75: Negros Oriental | I75: Siaton | J75: PH074619000 | K75: Artificial Reef Development Program | L75: Site in San Jose | M75: 1986 | N75: 1985 | O75: 1987 | P75: Substrate Enhancement | Q75: Artificial Reef | R75: Tires | S75: Tires | T75: Not applicable | U75: Not applicable | V75: Tires | W75: "Reestablish a self-sustaining, functioning reef ecosystem", Reduce population declines and ecosystem degradation, "Provide alternative, sustainable livelihood opportunities" | X75: M2, M4, M5 | Y75: Support the government's food productivity, environmental protection and enhancement efforts; Support sustenance fishery; enhance and restore habitats; costal fishery management | Z75: BFAR | AA75: Development | AB75: Local | AC75: Government - NGA | AD75: BFAR | AE75: Unknown | AF75: Unknown | AG75: 45 units | AH75: BFAR | AI75: Government - NGA | AJ75: BFAR | AK75: Ministry of Human Settlements; Government organizations | AL75: NGOs | AM75: People's organizations; Fisher's associations | AN75: Peer-reviewed | AO75: Conference Proceeding | AP75: Balgos, M. C. (1995). Evaluation of artificial reef development in the Philippines. In J. L. Munro & M. C. Balgos (Eds.), Artificial reefs in the Philippines (ICLARM Conference Proceedings No. 49, pp. 6–22). International Center for Living Aquatic Resources Management (ICLARM). | AQ75: https://core.ac.uk/download/pdf/6515223.pdf | AR75: Miriam Balgos | AS75: Unknown
A76: 0431 | B76: =CONCATENATE(C76, "-", J76, "-", M76, "-", A76) -> 2023-PH074625000-1986-0431 | C76: =IF(OR(D76="Published", D76="Unpublished"), 2023, IF(D76="New", 2025, "")) -> 2023 | D76: Published | E76: Modified | F76: Yes | G76: NIR | H76: Negros Oriental | I76: Zamboanguita | J76: PH074625000 | K76: Artificial Reef Development Program | L76: Site in Poblacion | M76: 1986 | N76: 1985 | O76: 1987 | P76: Substrate Enhancement | Q76: Artificial Reef | R76: Tires | S76: Tires | T76: Not applicable | U76: Not applicable | V76: Tires | W76: "Reestablish a self-sustaining, functioning reef ecosystem", Reduce population declines and ecosystem degradation, "Provide alternative, sustainable livelihood opportunities" | X76: M2, M4, M5 | Y76: Support the government's food productivity, environmental protection and enhancement efforts; Support sustenance fishery; enhance and restore habitats; costal fishery management | Z76: BFAR | AA76: Development | AB76: Local | AC76: Government - NGA | AD76: BFAR | AE76: Unknown | AF76: Unknown | AG76: 42 units | AH76: BFAR | AI76: Government - NGA | AJ76: BFAR | AK76: Ministry of Human Settlements; Government organizations | AL76: NGOs | AM76: People's organizations; Fisher's associations | AN76: Peer-reviewed | AO76: Conference Proceeding | AP76: Balgos, M. C. (1995). Evaluation of artificial reef development in the Philippines. In J. L. Munro & M. C. Balgos (Eds.), Artificial reefs in the Philippines (ICLARM Conference Proceedings No. 49, pp. 6–22). International Center for Living Aquatic Resources Management (ICLARM). | AQ76: https://core.ac.uk/download/pdf/6515223.pdf | AR76: Miriam Balgos | AS76: Unknown
A77: 0448 | B77: =CONCATENATE(C77, "-", J77, "-", M77, "-", A77) -> 2023-PH153809000-1986-0448 | C77: =IF(OR(D77="Published", D77="Unpublished"), 2023, IF(D77="New", 2025, "")) -> 2023 | D77: Published | E77: Modified | F77: Yes | G77: BARMM | H77: Maguindanao del Norte | I77: Matanog | J77: PH153809000 | K77: Artificial Reef Development Program | L77: Site in Sugod Bay | M77: 1986 | N77: 1985 | O77: 1987 | P77: Substrate Enhancement | Q77: Artificial Reef | R77: Tires | S77: Tires | T77: Not applicable | U77: Not applicable | V77: Tires | W77: "Reestablish a self-sustaining, functioning reef ecosystem", Reduce population declines and ecosystem degradation, "Provide alternative, sustainable livelihood opportunities" | X77: M2, M4, M5 | Y77: Support the government's food productivity, environmental protection and enhancement efforts; Support sustenance fishery; enhance and restore habitats; costal fishery management | Z77: BFAR | AA77: Development | AB77: Local | AC77: Government - NGA | AD77: BFAR | AE77: Unknown | AF77: Unknown | AG77: Unknown | AH77: BFAR | AI77: Government - NGA | AJ77: BFAR | AK77: Ministry of Human Settlements; Government organizations | AL77: NGOs | AM77: People's organizations; Fisher's associations | AN77: Peer-reviewed | AO77: Conference Proceeding | AP77: Balgos, M. C. (1995). Evaluation of artificial reef development in the Philippines. In J. L. Munro & M. C. Balgos (Eds.), Artificial reefs in the Philippines (ICLARM Conference Proceedings No. 49, pp. 6–22). International Center for Living Aquatic Resources Management (ICLARM). | AQ77: https://core.ac.uk/download/pdf/6515223.pdf; https://www.ircwash.org/sites/default/files/802-PH90-8920.pdf | AR77: Miriam Balgos | AS77: Unknown
A78: 0398 | B78: =CONCATENATE(C78, "-", J78, "-", M78, "-", A78) -> 2023-PH160203000-1987-0398 | C78: =IF(OR(D78="Published", D78="Unpublished"), 2023, IF(D78="New", 2025, "")) -> 2023 | D78: Unpublished | E78: Modified | F78: Yes | G78: XIII | H78: Agusan del Norte | I78: City of Cabadbaran | J78: PH160203000 | K78: Artificial Reef Project | L78: Site in Calibunan MPA | M78: 1987 | N78: Unknown | O78: Unknown | P78: Substrate Enhancement | Q78: Artificial Reef | R78: Concrete | S78: Concrete triangle | T78: Not applicable | U78: Not applicable | V78: bamboo, tires, triangle shaped concrete modules | W78: "Reestablish a self-sustaining, functioning reef ecosystem", Reduce population declines and ecosystem degradation | X78: M2, M4 | Y78: Spawning ground for fish; to revive fish ppopulations | Z78: DA - Provincial Agriculture Office | AA78: Development | AB78: Local | AC78: Government - NGA | AD78: DA | AE78: Unknown | AF78: Unknown | AG78: Unknown | AH78: Calibunan Fisherfolks | AI78: PO | AJ78: PO | AK78: PAO; DA-BFAR; MLGU | AL78: Unknown | AM78: Unknown | AN78: Grey literature | AO78: News/Press Release | AP78: de Sequera, V. (2001, June 17). Butuan: The Waters Live Again. PhilStar Global. https://www.philstar.com/other-sections/starweek-magazine/2001/06/17/127209/butuan-waters-live-again | AQ78: https://www.philstar.com/other-sections/starweek-magazine/2001/06/17/127209/butuan-waters-live-again | AR78: Unknown | AS78: Unknown | AT78: The AR started with Bamboos, then transitioned to tires then to concrete
A79: 0378 | B79: =CONCATENATE(C79, "-", J79, "-", M79, "-", A79) -> 2023-PH112402000-2017-0378 | C79: =IF(OR(D79="Published", D79="Unpublished"), 2023, IF(D79="New", 2025, "")) -> 2023 | D79: Published | E79: Modified | F79: No | G79: XI | H79: Davao del Sur | I79: City of Davao | J79: PH112402000 | K79: Artificial Reefs Project | L79: Site inside MPA in Brgy Bago Aplaya | M79: 2017 | N79: Unknown | O79: Unknown | P79: Substrate Enhancement | Q79: Artificial Reef | R79: Concrete | S79: Concrete domes | T79: Not applicable | U79: Not applicable | V79: Concrete; Domes | W79: Promote coral reef conservation stewardship, "Reestablish a self-sustaining, functioning reef ecosystem" | X79: M2, M6 | Y79: Development of fisherfolk community; preservation of coastal resources | Z79: Davao City Water District | AA79: Development | AB79: Local | AC79: Government - LGU | AD79: CLGU | AE79: Unknown | AF79: Unknown | AG79: 5 units | AH79: Davao City Water District | AI79: Government - LGU | AJ79: CLGU | AK79: Philippine Navy; BFAR; CLGU | AL79: Unknown | AM79: Brgy Aplaya residents | AN79: Grey literature | AO79: News/Press Release | AP79: Ajero, W. (n.d.). DCWD installs artificial reefs in Bago Aplaya. Davao City Water District. https://www.davao-water.gov.ph/home/pages/post.php?link=_GPrHoZaGZDEFMzRxVnu | AQ79: https://www.davao-water.gov.ph/home/pages/post.php?link=_GPrHoZaGZDEFMzRxVnu; https://www.pressreader.com/philippines/sunstar-davao/20170803/281608125516436 | AR79: Unknown | AS79: Unknown
A80: 0379 | B80: =CONCATENATE(C80, "-", J80, "-", M80, "-", A80) -> 2025-PH112402000-2017-0379 | C80: =IF(OR(D80="Published", D80="Unpublished"), 2023, IF(D80="New", 2025, "")) -> 2025 | D80: New | E80: New | F80: No | G80: XI | H80: Davao del Sur | I80: City of Davao | J80: PH112402000 | K80: Artificial Reefs Project | L80: Site in an MPA in the Davao Gulf | M80: 2017 | N80: Unknown | O80: Unknown | P80: Substrate Enhancement | Q80: Artificial Reef | R80: Concrete | S80: Concrete domes | T80: Not applicable | U80: Not applicable | V80: Concrete; Domes | W80: "Provide alternative, sustainable livelihood opportunities" | X80: M5 | Y80: Fisheries livelihoods | Z80: Philippine Navy - Naval Forces Eastern Mindanao | AA80: Development | AB80: Local | AC80: Government - NGA | AD80: AFP | AE80: Unknown | AF80: Unknown | AG80: 14 units | AH80: Philippine Navy - Naval Forces Eastern Mindanao | AI80: Government - NGA | AJ80: AFP | AK80: BFAR; CLGU | AL80: Davao City Water District | AM80: Unknown | AN80: Grey literature | AO80: Social Media | AP80: UNTV News and Rescue. (2017, August 24). Naval Forces in Eastern Mindanao conducts coral reef restoration in Davao City [Video]. YouTube. https://www.youtube.com/watch?v=J2E9tUJsTVo | AQ80: https://www.youtube.com/watch?v=J2E9tUJsTVo; https://www.ircwash.org/sites/default/files/802-PH90-8920.pdf | AR80: Unknown | AS80: Unknown
A81: 0061 | B81: =CONCATENATE(C81, "-", J81, "-", M81, "-", A81) -> 2023-PH015514000-1991-0061 | C81: =IF(OR(D81="Published", D81="Unpublished"), 2023, IF(D81="New", 2025, "")) -> 2023 | D81: Published | E81: Modified | F81: Yes | G81: I | H81: Pangasinan | I81: Bolinao | J81: PH015514000 | K81: ASEAN Australia Economic Cooperation Program Living Coastal Resources Project | L81: Site at Silaqui Island (9°52'30" to 20°00' "E-Iongitude and 16°22'30" to 6°27'30" N-Iatitude) | M81: 1991 | N81: 1991 | O81: 1991 | P81: Substrate Enhancement | Q81: Artificial Reef | R81: Concrete | S81: Concrete tent-like | T81: Not applicable | U81: Not applicable | V81: Concrete tent-like block structure of AR modules | W81: Scientific Research | X81: M7 | Y81: Experimental | Z81: ASEAN Australia Economic Cooperation Program Living Coastal Resources Project | AA81: Research | AB81: International | AC81: Donor Agency | AD81: Donor Agency | AE81: Unknown | AF81: Unknown | AG81: 4 blocks | AH81: UP MSI | AI81: Academe | AJ81: Public Academic Institutions | AK81: Unknown | AL81: Unknown | AM81: Unknown | AN81: Peer-reviewed | AO81: Journal Article | AP81: Pamintuan, I., Alino, P., Gomez, E., & Rollon, R. (1994). Early Successional Patterns of Invertebrates in Artificial Reefs Established at Clear and Silty Areas in Bolinao, Pangasinan, Northern Philippines. Bulletin of Marine Science, 55(2-3), 867-877. Retrieved from https://www.researchgate.net/publication/233624454_Early_Successional_Patterns_of_Invertebrates_in_Artificial_Reefs_Established_at_Clear_and_Silty_Areas_in_Bolinao_Pangasinan_Northern_Philippines | AQ81: https://www.ingentaconnect.com/content/umrsmas/bullmar/1994/00000055/f0020002/art00047# | AR81: I. Pamintuan; R. Rollon; P. Alino | AS81: Unknown
A82: 0469 | B82: =CONCATENATE(C82, "-", J82, "-", M82, "-", A82) -> 2025-PH015514000-1991-0469 | C82: =IF(OR(D82="Published", D82="Unpublished"), 2023, IF(D82="New", 2025, "")) -> 2025 | D82: New | E82: New | F82: Yes | G82: I | H82: Pangasinan | I82: Bolinao | J82: PH015514000 | K82: ASEAN Australia Economic Cooperation Program Living Coastal Resources Project | L82: Site in Guiguiwanen Bay (9°52'30" to 20°00' "E-Iongitude and 16°22'30" to 6°27'30" N-Iatitude) | M82: 1991 | N82: 1991 | O82: 1991 | P82: Substrate Enhancement | Q82: Artificial Reef | R82: Concrete | S82: Concrete tent-like | T82: Not applicable | U82: Not applicable | V82: Concrete tent-like block structure of AR modules | W82: Scientific Research | X82: M7 | Y82: Experimental | Z82: ASEAN Australia Economic Cooperation Program Living Coastal Resources Project | AA82: Research | AB82: International | AC82: Donor Agency | AD82: Donor Agency | AE82: Unknown | AF82: Unknown | AG82: 4 blocks | AH82: UP MSI | AI82: Academe | AJ82: Public Academic Institutions | AK82: Unknown | AL82: Unknown | AM82: Unknown | AN82: Peer-reviewed | AO82: Journal Article | AP82: Pamintuan, I., Alino, P., Gomez, E., & Rollon, R. (1994). Early Successional Patterns of Invertebrates in Artificial Reefs Established at Clear and Silty Areas in Bolinao, Pangasinan, Northern Philippines. Bulletin of Marine Science, 55(2-3), 867-877. Retrieved from https://www.researchgate.net/publication/233624454_Early_Successional_Patterns_of_Invertebrates_in_Artificial_Reefs_Established_at_Clear_and_Silty_Areas_in_Bolinao_Pangasinan_Northern_Philippines | AQ82: https://www.ingentaconnect.com/content/umrsmas/bullmar/1994/00000055/f0020002/art00047# | AR82: I. Pamintuan; R. Rollon; P. Alino | AS82: Unknown
A83: 0105 | B83: =CONCATENATE(C83, "-", J83, "-", M83, "-", A83) -> 2023-PH037113000-2012-0105 | C83: =IF(OR(D83="Published", D83="Unpublished"), 2023, IF(D83="New", 2025, "")) -> 2023 | D83: Published | E83: Unchanged | F83: No | G83: III | H83: Zambales | I83: Santa Cruz | J83: PH037113000 | K83: Bioconservation Project under DENR ICRM | L83: Unknown | M83: 2012 | N83: Unknown | O83: Unknown | P83: Substrate Enhancement | Q83: Artificial Reef | R83: Unknown | S83: Unknown | T83: Not applicable | U83: Not applicable | V83: Unknown | W83: "Reestablish a self-sustaining, functioning reef ecosystem" | X83: M2 | Y83: Restore degraded reef | Z83: MLGU | AA83: Development | AB83: Local | AC83: Government - LGU | AD83: MLGU | AE83: Unknown | AF83: Unknown | AG83: Unknown | AH83: MLGU | AI83: Government - LGU | AJ83: MLGU | AK83: DENR 3 | AL83: Unknown | AM83: Unknown | AN83: Survey | AO83: Questionnaire | AP83: Survey | AQ83: Unknown | AR83: Linos Mejos | AS83: 9503417670
A84: 0319 | B84: =CONCATENATE(C84, "-", J84, "-", M84, "-", A84) -> 2023-PH084802000-2013-0319 | C84: =IF(OR(D84="Published", D84="Unpublished"), 2023, IF(D84="New", 2025, "")) -> 2023 | D84: Published | E84: Modified | F84: No | G84: VIII | H84: Northern Samar | I84: Biri | J84: PH084802000 | K84: Biri Buds | L84: Unknown | M84: 2013 | N84: Unknown | O84: Unknown | P84: Substrate Enhancement | Q84: Artificial Reef | R84: Concrete, Engineered/Advanced | S84: Concrete domes, Reefbuds | T84: Not applicable | U84: Not applicable | V84: Domes; Reefbuds | W84: Promote coral reef conservation stewardship, Scientific Research | X84: M6, M7 | Y84: Ocean awareness, education and research | Z84: Unknown | AA84: Unknown | AB84: Unknown | AC84: Unknown | AD84: Unknown | AE84: Unknown | AF84: Unknown | AG84: Unknown | AH84: Biri Initiative | AI84: Private | AJ84: Private | AK84: Unknown | AL84: Holcim Cement; Aquamundo Sports | AM84: Unknown | AN84: Grey literature | AO84: Blog/Website | AP84: Ewen, R., & Parker, D. (2017, October). Biri Initiative, a story on coral restoration. Seven Seas Media. https://sevenseasmedia.org/biri-initiative-story-on-coral-restoration/ | AQ84: https://sevenseasmedia.org/biri-initiative-story-on-coral-restoration/; https://www.thescubanews.com/2014/08/06/reefbud-technology-downsized-to-broaden-appeal/ | AR84: Unknown | AS84: Unknown
A85: 0060 | B85: =CONCATENATE(C85, "-", J85, "-", M85, "-", A85) -> 2023-PH015514000-2004-0060 | C85: =IF(OR(D85="Published", D85="Unpublished"), 2023, IF(D85="New", 2025, "")) -> 2023 | D85: Published | E85: Modified | F85: No | G85: I | H85: Pangasinan | I85: Bolinao | J85: PH015514000 | K85: Bolinao Coral Reef Targeted Research | L85: Unknown | M85: 2004 | N85: 2004 | O85: 2009 | P85: Asexual Propagation | Q85: Coral Gardening | R85: Not applicable | S85: Not applicable | T85: In-situ | U85: CNU | V85: CNU; coral planting | W85: Unknown | X85: UNK | Y85: Unknown | Z85: Unknown | AA85: Unknown | AB85: Unknown | AC85: Unknown | AD85: Unknown | AE85: Unknown | AF85: Unknown | AG85: Unknown | AH85: Unknown | AI85: Unknown | AJ85: Unknown | AK85: Unknown | AL85: Unknown | AM85: Unknown | AN85: Grey literature | AO85: Other Reports | AP85: Mickelfield, A. (n.d.) An Evaluation of Coral Reef Restoration Methods & Artificial Reefs. Retrieved from https://www.marineconservationphilippines.org/wp-content/uploads/2018/02/an-evaluation-of-coral-reef-restoration-methods.pdf | AQ85: https://www.marineconservationphilippines.org/wp-content/uploads/2018/02/an-evaluation-of-coral-reef-restoration-methods.pdf | AR85: Marine Conservation Philippines | AS85: Unknown
A86: 0227 | B86: =CONCATENATE(C86, "-", J86, "-", M86, "-", A86) -> 2023-PH060412000-2010-0227 | C86: =IF(OR(D86="Published", D86="Unpublished"), 2023, IF(D86="New", 2025, "")) -> 2023 | D86: Published | E86: Modified | F86: No | G86: VI | H86: Aklan | I86: Malay | J86: PH060412000 | K86: Boracay Beach Management Program | L86: Site in Crocodile Island | M86: 2010 | N86: Unknown | O86: Unknown | P86: Asexual Propagation | Q86: Coral Gardening | R86: Not applicable | S86: Not applicable | T86: In-situ | U86: CNU | V86: CNU; coral planting | W86: Unknown | X86: UNK | Y86: Unknown | Z86: Petron Foundation; San Miguel Corp. | AA86: Development | AB86: Local | AC86: Private | AD86: Private | AE86: Unknown | AF86: Unknown | AG86: Unknown | AH86: Boracay Foundation | AI86: NGO | AJ86: NGO | AK86: MLGU | AL86: Petron Foundation; San Miguel Corp. | AM86: Unknown | AN86: Grey literature | AO86: News/Press Release | AP86: Artificial reef dome deployment in Boracay. (2012, January 26). Gadgets Magazine. https://gadgetsmagazine.com.ph/technology/artificial-reef-dome-deployment-in-boracay | AQ86: https://gadgetsmagazine.com.ph/technology/artificial-reef-dome-deployment-in-boracay | AR86: Unknown | AS86: Unknown | AT86: Link does not open
A87: 0228 | B87: =CONCATENATE(C87, "-", J87, "-", M87, "-", A87) -> 2023-PH060412000-2011-0228 | C87: =IF(OR(D87="Published", D87="Unpublished"), 2023, IF(D87="New", 2025, "")) -> 2023 | D87: Published | E87: Modified | F87: No | G87: VI | H87: Aklan | I87: Malay | J87: PH060412000 | K87: Boracay Beach Management Program | L87: Sites in Balinghai snorkeling area and Boracay shoreline | M87: 2011 | N87: Unknown | O87: Unknown | P87: Substrate Enhancement | Q87: Artificial Reef | R87: Unknown | S87: Unknown | T87: Not applicable | U87: Not applicable | V87: Unknown | W87: Unknown | X87: UNK | Y87: Unknown | Z87: Petron Foundation | AA87: Development | AB87: Local | AC87: Private | AD87: Private | AE87: Unknown | AF87: Unknown | AG87: Unknown | AH87: Boracay Foundation | AI87: NGO | AJ87: NGO | AK87: MLGU | AL87: Unknown | AM87: Unknown | AN87: Grey literature | AO87: News/Press Release | AP87: Artificial reef dome deployment in Boracay. (2012, January 26). Gadgets Magazine. https://gadgetsmagazine.com.ph/technology/artificial-reef-dome-deployment-in-boracay | AQ87: https://gadgetsmagazine.com.ph/technology/artificial-reef-dome-deployment-in-boracay | AR87: Unknown | AS87: Unknown | AT87: Link does not open
A88: 0223 | B88: =CONCATENATE(C88, "-", J88, "-", M88, "-", A88) -> 2023-PH060406000-2022-0223 | C88: =IF(OR(D88="Published", D88="Unpublished"), 2023, IF(D88="New", 2025, "")) -> 2023 | D88: Published | E88: Unchanged | F88: No | G88: VI | H88: Aklan | I88: Ibajay | J88: PH060406000 | K88: Bugtong Bato MPA Artificial Coral Reef Project | L88: Unknown | M88: 2022 | N88: 2022 | O88: 2025 | P88: Substrate Enhancement | Q88: Artificial Reef | R88: Unknown | S88: Unknown | T88: Not applicable | U88: Not applicable | V88: Unknown | W88: "Reestablish a self-sustaining, functioning reef ecosystem", "Provide alternative, sustainable livelihood opportunities" | X88: M2, M5 | Y88: Rehabilitate MPA; tourism | Z88: MLGU | AA88: Development | AB88: Local | AC88: Government - LGU | AD88: MLGU | AE88: Unknown | AF88: Unknown | AG88: Unknown | AH88: MLGU | AI88: Government - LGU | AJ88: MLGU | AK88: Unknown | AL88: Unknown | AM88: Unknown | AN88: Survey | AO88: Questionnaire | AP88: Survey | AQ88: Unknown | AR88: SB Chair on Environment | AS88: Nefnef22@gmail.com; 2892024
A89: 0435 | B89: =CONCATENATE(C89, "-", J89, "-", M89, "-", A89) -> 2025-PH074625000-2016-0435 | C89: =IF(OR(D89="Published", D89="Unpublished"), 2023, IF(D89="New", 2025, "")) -> 2025 | D89: New | E89: New | F89: Yes | G89: NIR | H89: Negros Oriental | I89: Zamboanguita | J89: PH074625000 | K89: Build-A-Reef | L89: Site in Brgy Poblacion | M89: 2016 | N89: 2016 | O89: Unknown | P89: Substrate Enhancement | Q89: Artificial Reef | R89: Concrete | S89: Concrete block | T89: Not applicable | U89: Not applicable | V89: Hollow blocks | W89: "Reestablish a self-sustaining, functioning reef ecosystem" | X89: M2 | Y89: Natural refuge and habitat | Z89: Philippine Coast Guard | AA89: Development | AB89: Local | AC89: Government - NGA | AD89: PCG | AE89: Unknown | AF89: Unknown | AG89: 587 blocks | AH89: Philippine Coast Guard South District Command; PCG Auxiliary 1306th Squadron | AI89: Government - NGA | AJ89: PCG | AK89: Municipal DRR Office | AL89: Philippine Coast Guard Auxiliary | AM89: Unknown | AN89: Grey literature | AO89: News/Press Release | AP89: Partlow, M. J. (2018, September 26). "Build-a-Reef" brings back sea life in NegOr coastal town. Philippine News Agency. https://www.pna.gov.ph/articles/1049175 | AQ89: https://www.pna.gov.ph/articles/1049175 | AR89: Unknown | AS89: Unknown
A90: 0335 | B90: =CONCATENATE(C90, "-", J90, "-", M90, "-", A90) -> 2023-PH097322000-2021-0335 | C90: =IF(OR(D90="Published", D90="Unpublished"), 2023, IF(D90="New", 2025, "")) -> 2023 | D90: Published | E90: Modified | F90: No | G90: IX | H90: Zamboanga del Sur | I90: City of Pagadian | J90: PH097322000 | K90: Build-A-Reef Program | L90: Unknown | M90: 2021 | N90: Unknown | O90: Unknown | P90: Substrate Enhancement | Q90: Artificial Reef | R90: Unknown | S90: Unknown | T90: Not applicable | U90: Not applicable | V90: Unknown | W90: Unknown | X90: UNK | Y90: Unknown | Z90: Unknown | AA90: Unknown | AB90: Unknown | AC90: Unknown | AD90: Unknown | AE90: Unknown | AF90: Unknown | AG90: Unknown | AH90: Philippine Coast Guard | AI90: Government - NGA | AJ90: PCG | AK90: Unknown | AL90: Abdkt Freedive Team Strong Scuba; JCI Greater Pagadian | AM90: Unknown | AN90: Grey literature | AO90: Social Media | AP90: PCGA 312th Auxiliary Squadron (2021, February 15). Build a Reef program of 312th Squadron, in partnership with CGS Zamboanga del Sur, JCI Greater Pagadian, BFAR Zamboanga del [Status Update]. Facebook. https://web.facebook.com/people/PCGA-312th-Auxiliary-Squadron/100064379604303/?_rdc=1&_rdr [Video removed] | AQ90: https://web.facebook.com/people/PCGA-312th-Auxiliary-Squadron/100064379604303/?_rdc=1&_rdr | AR90: Unknown | AS90: Unknown
A91: 0377 | B91: =CONCATENATE(C91, "-", J91, "-", M91, "-", A91) -> 2023-PH112402000-2017-0377 | C91: =IF(OR(D91="Published", D91="Unpublished"), 2023, IF(D91="New", 2025, "")) -> 2023 | D91: Published | E91: Modified | F91: No | G91: XI | H91: Davao del Sur | I91: City of Davao | J91: PH112402000 | K91: Build-a-Reef Project | L91: Site inside MPAs in Brgy Vicente Hizon, Lanang and Brgy Centro | M91: 2017 | N91: Unknown | O91: Unknown | P91: Substrate Enhancement | Q91: Artificial Reef | R91: Concrete | S91: Concrete domes | T91: Not applicable | U91: Not applicable | V91: Concrete; Domes | W91: "Reestablish a self-sustaining, functioning reef ecosystem", Reduce population declines and ecosystem degradation | X91: M2, M4 | Y91: Habitat for fish species; fish production | Z91: Phoenix Philippines Foundation | AA91: Development | AB91: Local | AC91: Private | AD91: Private | AE91: Unknown | AF91: 0.000077 ha | AG91: 30 units | AH91: Phoenix Philippines Foundation | AI91: Private | AJ91: Private | AK91: Philippine Coast Guard | AL91: Philippine Coast Guard Auxiliary | AM91: Unknown | AN91: Grey literature | AO91: Blog/Website | AP91: Phoenix helps save marine life through artificial reefs (2017, October 13). Phoenix Petroleum. https://www.phoenixfuels.ph/phoenix-helps-save-marine-life-through-artificial-reefs/ | AQ91: https://www.phoenixfuels.ph/phoenix-helps-save-marine-life-through-artificial-reefs/ | AR91: Unknown | AS91: Unknown
A92: 0251 | B92: =CONCATENATE(C92, "-", J92, "-", M92, "-", A92) -> 2023-PH063014000-2015-0251 | C92: =IF(OR(D92="Published", D92="Unpublished"), 2023, IF(D92="New", 2025, "")) -> 2023 | D92: Published | E92: Modified | F92: No | G92: VI | H92: Iloilo | I92: Carles | J92: PH063014000 | K92: Building Back Better | L92: Unknown | M92: 2015 | N92: Unknown | O92: Unknown | P92: Substrate Enhancement | Q92: Artificial Reef | R92: Concrete | S92: Concrete jackstone | T92: Not applicable | U92: Not applicable | V92: Jackstone | W92: Reduce population declines and ecosystem degradation | X92: M4 | Y92: fish stock enhancement; fishing ground | Z92: Christian Aid | AA92: Development | AB92: International | AC92: NGO | AD92: NGO | AE92: Unknown | AF92: Unknown | AG92: 100 units | AH92: Iloilo CODE of NGOs | AI92: NGO | AJ92: NGO | AK92: Unknown | AL92: Unknown | AM92: Bayas Maliog-liog Small Fisherfolks Association | AN92: Grey literature | AO92: News/Press Release | AP92: Lozada, D. (2016, September 4). "For the next generation": Iloilo's fishermen take lead in coastal management. Rappler. https://www.rappler.com/environment/disasters/145137-iloilo-fishermen-lead-coastal-management/ | AQ92: https://www.rappler.com/moveph/145137-iloilo-fishermen-lead-coastal-management/ | AR92: Unknown | AS92: lgucarlesiloilo@gmail.com
A93: 0171 | B93: =CONCATENATE(C93, "-", J93, "-", M93, "-", A93) -> 2023-PH174005000-1989-0171 | C93: =IF(OR(D93="Published", D93="Unpublished"), 2023, IF(D93="New", 2025, "")) -> 2023 | D93: Published | E93: Modified | F93: Yes | G93: IV-B | H93: Marinduque | I93: Santa Cruz | J93: PH174005000 | K93: Calancan Bay Rehabilitation Program | L93: Site in Calancay Bay | M93: 1989 | N93: 1989 | O93: 1994 | P93: Substrate Enhancement | Q93: Artificial Reef | R93: Hybrid | S93: Tires, Bamboo, Unspecified concrete structure | T93: Not applicable | U93: Not applicable | V93: tire modules, concrete modules bamboo modules | W93: Mitigate anticipated coral loss prior to a known disturbance, Promote coral reef conservation stewardship | X93: M3, M6 | Y93: Reduce the impact of mine tailings dumped in Calancalan Bay by a copper mining company; Sustained conservation and development of Calancan Bay and surrounding communities and processes and the improvement of overall environmental quality | Z93: Mining company responsible for the mine tailing dumping | AA93: Development | AB93: Local | AC93: Private | AD93: Private | AE93: Unknown | AF93: Unknown | AG93: 848 TM; 1.134 concrete modules; 18 BM | AH93: DENR | AI93: Government - NGA | AJ93: DENR | AK93: Unknown | AL93: Unknown | AM93: Unknown | AN93: Peer-reviewed | AO93: Conference Proceeding | AP93: Balgos, M. C. (1995). Evaluation of artificial reef development in the Philippines. In J. L. Munro & M. C. Balgos (Eds.), Artificial reefs in the Philippines (ICLARM Conference Proceedings No. 49, pp. 6–22). International Center for Living Aquatic Resources Management (ICLARM). | AQ93: https://core.ac.uk/download/pdf/6515223.pdf | AR93: Miriam Balgos | AS93: Unknown
A94: 0275 | B94: =CONCATENATE(C94, "-", J94, "-", M94, "-", A94) -> 2025-PH072207000-1985-0275 | C94: =IF(OR(D94="Published", D94="Unpublished"), 2023, IF(D94="New", 2025, "")) -> 2025 | D94: New | E94: New | F94: Yes | G94: VII | H94: Cebu | I94: Badian | J94: PH072207000 | K94: Central Visayas Regional Projects - 1 | L94: Site in Brgy Bugas | M94: 1985 | N94: 1985 | O94: 1988 | P94: Substrate Enhancement | Q94: Artificial Reef | R94: Natural | S94: Bamboo | T94: Not applicable | U94: Not applicable | V94: Pyramidal bamboo modules | W94: Promote coral reef conservation stewardship | X94: M6 | Y94: Coastal resource management | Z94: World Bank | AA94: Development | AB94: International | AC94: Donor Agency | AD94: Donor Agency | AE94: Unknown | AF94: Unknown | AG94: Unknown | AH94: Central Visayas Regional Projects I - Regional Project Office (RPO) | AI94: Government - NGA | AJ94: Central Visayas Regional Projects I - Regional Project Office (RPO) | AK94: NEDA | AL94: Unknown | AM94: Unknown | AN94: Grey literature | AO94: Other Reports | AP94: LMP, FISH Project, WWF-Philippines and CI-Philippines (2009). Directory of CRM Learning Destinations in the Philippines, 2nd Edition. Cebu City Philippines. http://oneocean.org/download/db_files/directory_of_crm_destinations2Ed.pdf | AQ94: http://oneocean.org/download/db_files/directory_of_crm_destinations2Ed.pdf | AR94: Unknown | AS94: Unknown
A95: 0438 | B95: =CONCATENATE(C95, "-", J95, "-", M95, "-", A95) -> 2025-PH076104000-1988-0438 | C95: =IF(OR(D95="Published", D95="Unpublished"), 2023, IF(D95="New", 2025, "")) -> 2025 | D95: New | E95: New | F95: Yes | G95: NIR | H95: Siquijor | I95: Maria | J95: PH076104000 | K95: Central Visayas Regional Projects - 1 | L95: Site in Candaping B MPA | M95: 1988 | N95: 1984 | O95: 1992 | P95: Substrate Enhancement | Q95: Artificial Reef | R95: Concrete | S95: Unspecified concrete structure | T95: Not applicable | U95: Not applicable | V95: Concrete | W95: Promote coral reef conservation stewardship | X95: M6 | Y95: Coastal resource management | Z95: World Bank | AA95: Development | AB95: International | AC95: Donor Agency | AD95: Donor Agency | AE95: Unknown | AF95: Unknown | AG95: Unknown | AH95: Central Visayas Regional Projects - I Regional Project Office (RPO) | AI95: Government - NGA | AJ95: Central Visayas Regional Projects I - Regional Project Office (RPO) | AK95: NEDA | AL95: Unknown | AM95: Unknown | AN95: Grey literature | AO95: Other Reports | AP95: LMP, FISH Project, WWF-Philippines and CI-Philippines (2009). Directory of CRM Learning Destinations in the Philippines, 2nd Edition. Cebu City Philippines. http://oneocean.org/download/db_files/directory_of_crm_destinations2Ed.pdf | AQ95: http://oneocean.org/download/db_files/directory_of_crm_destinations2Ed.pdf | AR95: Unknown | AS95: Unknown
A96: 0461 | B96: =CONCATENATE(C96, "-", J96, "-", M96, "-", A96) -> 2025-PH072207000-1985-0461 | C96: =IF(OR(D96="Published", D96="Unpublished"), 2023, IF(D96="New", 2025, "")) -> 2025 | D96: New | E96: New | F96: Yes | G96: VII | H96: Cebu | I96: Badian | J96: PH072207000 | K96: Central Visayas Regional Projects - 1 | L96: Site in Brgy Manduyong | M96: 1985 | N96: 1985 | O96: 1988 | P96: Substrate Enhancement | Q96: Artificial Reef | R96: Natural | S96: Bamboo | T96: Not applicable | U96: Not applicable | V96: Pyramidal bamboo modules | W96: Promote coral reef conservation stewardship | X96: M6 | Y96: Coastal resource management | Z96: World Bank | AA96: Development | AB96: International | AC96: Donor Agency | AD96: Donor Agency | AE96: Unknown | AF96: Unknown | AG96: Unknown | AH96: Central Visayas Regional Projects I - Regional Project Office (RPO) | AI96: Government - NGA | AJ96: Central Visayas Regional Projects I - Regional Project Office (RPO) | AK96: NEDA | AL96: Unknown | AM96: Unknown | AN96: Grey literature | AO96: Other Reports | AP96: LMP, FISH Project, WWF-Philippines and CI-Philippines (2009). Directory of CRM Learning Destinations in the Philippines, 2nd Edition. Cebu City Philippines. http://oneocean.org/download/db_files/directory_of_crm_destinations2Ed.pdf | AQ96: http://oneocean.org/download/db_files/directory_of_crm_destinations2Ed.pdf | AR96: Unknown | AS96: Unknown
A97: 0462 | B97: =CONCATENATE(C97, "-", J97, "-", M97, "-", A97) -> 2025-PH072207000-1985-0462 | C97: =IF(OR(D97="Published", D97="Unpublished"), 2023, IF(D97="New", 2025, "")) -> 2025 | D97: New | E97: New | F97: Yes | G97: VII | H97: Cebu | I97: Badian | J97: PH072207000 | K97: Central Visayas Regional Projects - 1 | L97: Site in Brgy Malhiao | M97: 1985 | N97: 1985 | O97: 1988 | P97: Substrate Enhancement | Q97: Artificial Reef | R97: Natural | S97: Bamboo | T97: Not applicable | U97: Not applicable | V97: Pyramidal bamboo modules | W97: Promote coral reef conservation stewardship | X97: M6 | Y97: Coastal resource management | Z97: World Bank | AA97: Development | AB97: International | AC97: Donor Agency | AD97: Donor Agency | AE97: Unknown | AF97: Unknown | AG97: Unknown | AH97: Central Visayas Regional Projects I - Regional Project Office (RPO) | AI97: Government - NGA | AJ97: Central Visayas Regional Projects I - Regional Project Office (RPO) | AK97: NEDA | AL97: Unknown | AM97: Unknown | AN97: Grey literature | AO97: Other Reports | AP97: LMP, FISH Project, WWF-Philippines and CI-Philippines (2009). Directory of CRM Learning Destinations in the Philippines, 2nd Edition. Cebu City Philippines. http://oneocean.org/download/db_files/directory_of_crm_destinations2Ed.pdf | AQ97: http://oneocean.org/download/db_files/directory_of_crm_destinations2Ed.pdf | AR97: Unknown | AS97: Unknown
A98: 0463 | B98: =CONCATENATE(C98, "-", J98, "-", M98, "-", A98) -> 2025-PH072207000-1985-0463 | C98: =IF(OR(D98="Published", D98="Unpublished"), 2023, IF(D98="New", 2025, "")) -> 2025 | D98: New | E98: New | F98: Yes | G98: VII | H98: Cebu | I98: Badian | J98: PH072207000 | K98: Central Visayas Regional Projects - 1 | L98: Site in Brgy Zaragosa | M98: 1985 | N98: 1985 | O98: 1988 | P98: Substrate Enhancement | Q98: Artificial Reef | R98: Natural | S98: Bamboo | T98: Not applicable | U98: Not applicable | V98: Pyramidal bamboo modules | W98: Promote coral reef conservation stewardship | X98: M6 | Y98: Coastal resource management | Z98: World Bank | AA98: Development | AB98: International | AC98: Donor Agency | AD98: Donor Agency | AE98: Unknown | AF98: Unknown | AG98: Unknown | AH98: Central Visayas Regional Projects I - Regional Project Office (RPO) | AI98: Government - NGA | AJ98: Central Visayas Regional Projects I - Regional Project Office (RPO) | AK98: NEDA | AL98: Unknown | AM98: Unknown | AN98: Grey literature | AO98: Other Reports | AP98: LMP, FISH Project, WWF-Philippines and CI-Philippines (2009). Directory of CRM Learning Destinations in the Philippines, 2nd Edition. Cebu City Philippines. http://oneocean.org/download/db_files/directory_of_crm_destinations2Ed.pdf | AQ98: http://oneocean.org/download/db_files/directory_of_crm_destinations2Ed.pdf | AR98: Unknown | AS98: Unknown
A99: 0464 | B99: =CONCATENATE(C99, "-", J99, "-", M99, "-", A99) -> 2025-PH072207000-1985-0464 | C99: =IF(OR(D99="Published", D99="Unpublished"), 2023, IF(D99="New", 2025, "")) -> 2025 | D99: New | E99: New | F99: Yes | G99: VII | H99: Cebu | I99: Badian | J99: PH072207000 | K99: Central Visayas Regional Projects - 1 | L99: Site in Brgy Lambug | M99: 1985 | N99: 1985 | O99: 1988 | P99: Substrate Enhancement | Q99: Artificial Reef | R99: Natural | S99: Bamboo | T99: Not applicable | U99: Not applicable | V99: Pyramidal bamboo modules | W99: Promote coral reef conservation stewardship | X99: M6 | Y99: Coastal resource management | Z99: World Bank | AA99: Development | AB99: International | AC99: Donor Agency | AD99: Donor Agency | AE99: Unknown | AF99: Unknown | AG99: Unknown | AH99: Central Visayas Regional Projects I - Regional Project Office (RPO) | AI99: Government - NGA | AJ99: Central Visayas Regional Projects I - Regional Project Office (RPO) | AK99: NEDA | AL99: Unknown | AM99: Unknown | AN99: Grey literature | AO99: Other Reports | AP99: LMP, FISH Project, WWF-Philippines and CI-Philippines (2009). Directory of CRM Learning Destinations in the Philippines, 2nd Edition. Cebu City Philippines. http://oneocean.org/download/db_files/directory_of_crm_destinations2Ed.pdf | AQ99: http://oneocean.org/download/db_files/directory_of_crm_destinations2Ed.pdf | AR99: Unknown | AS99: Unknown
A100: 0465 | B100: =CONCATENATE(C100, "-", J100, "-", M100, "-", A100) -> 2025-PH072207000-1985-0465 | C100: =IF(OR(D100="Published", D100="Unpublished"), 2023, IF(D100="New", 2025, "")) -> 2025 | D100: New | E100: New | F100: Yes | G100: VII | H100: Cebu | I100: Badian | J100: PH072207000 | K100: Central Visayas Regional Projects - 1 | L100: Site in Brgy Malabago | M100: 1985 | N100: 1985 | O100: 1988 | P100: Substrate Enhancement | Q100: Artificial Reef | R100: Natural | S100: Bamboo | T100: Not applicable | U100: Not applicable | V100: Pyramidal bamboo modules | W100: Promote coral reef conservation stewardship | X100: M6 | Y100: Coastal resource management | Z100: World Bank | AA100: Development | AB100: International | AC100: Donor Agency | AD100: Donor Agency | AE100: Unknown | AF100: Unknown | AG100: Unknown | AH100: Central Visayas Regional Projects I - Regional Project Office (RPO) | AI100: Government - NGA | AJ100: Central Visayas Regional Projects I - Regional Project Office (RPO) | AK100: NEDA | AL100: Unknown | AM100: Unknown | AN100: Grey literature | AO100: Other Reports | AP100: LMP, FISH Project, WWF-Philippines and CI-Philippines (2009). Directory of CRM Learning Destinations in the Philippines, 2nd Edition. Cebu City Philippines. http://oneocean.org/download/db_files/directory_of_crm_destinations2Ed.pdf | AQ100: http://oneocean.org/download/db_files/directory_of_crm_destinations2Ed.pdf | AR100: Unknown | AS100: Unknown
A101: 0466 | B101: =CONCATENATE(C101, "-", J101, "-", M101, "-", A101) -> 2025-PH072207000-1985-0466 | C101: =IF(OR(D101="Published", D101="Unpublished"), 2023, IF(D101="New", 2025, "")) -> 2025 | D101: New | E101: New | F101: Yes | G101: VII | H101: Cebu | I101: Badian | J101: PH072207000 | K101: Central Visayas Regional Projects - 1 | L101: Site in Brgy Bato | M101: 1985 | N101: 1985 | O101: 1988 | P101: Substrate Enhancement | Q101: Artificial Reef | R101: Natural | S101: Bamboo | T101: Not applicable | U101: Not applicable | V101: Pyramidal bamboo modules | W101: Promote coral reef conservation stewardship | X101: M6 | Y101: Coastal resource management | Z101: World Bank | AA101: Development | AB101: International | AC101: Donor Agency | AD101: Donor Agency | AE101: Unknown | AF101: Unknown | AG101: Unknown | AH101: Central Visayas Regional Projects I - Regional Project Office (RPO) | AI101: Government - NGA | AJ101: Central Visayas Regional Projects I - Regional Project Office (RPO) | AK101: NEDA | AL101: Unknown | AM101: Unknown | AN101: Grey literature | AO101: Other Reports | AP101: LMP, FISH Project, WWF-Philippines and CI-Philippines (2009). Directory of CRM Learning Destinations in the Philippines, 2nd Edition. Cebu City Philippines. http://oneocean.org/download/db_files/directory_of_crm_destinations2Ed.pdf | AQ101: http://oneocean.org/download/db_files/directory_of_crm_destinations2Ed.pdf | AR101: Unknown | AS101: Unknown
A102: 0467 | B102: =CONCATENATE(C102, "-", J102, "-", M102, "-", A102) -> 2025-PH072207000-1985-0467 | C102: =IF(OR(D102="Published", D102="Unpublished"), 2023, IF(D102="New", 2025, "")) -> 2025 | D102: New | E102: New | F102: Yes | G102: VII | H102: Cebu | I102: Badian | J102: PH072207000 | K102: Central Visayas Regional Projects - 1 | L102: Site in Brgy Hinablan | M102: 1985 | N102: 1985 | O102: 1988 | P102: Substrate Enhancement | Q102: Artificial Reef | R102: Natural | S102: Bamboo | T102: Not applicable | U102: Not applicable | V102: Pyramidal bamboo modules | W102: Promote coral reef conservation stewardship | X102: M6 | Y102: Coastal resource management | Z102: World Bank | AA102: Development | AB102: International | AC102: Donor Agency | AD102: Donor Agency | AE102: Unknown | AF102: Unknown | AG102: Unknown | AH102: Central Visayas Regional Projects I - Regional Project Office (RPO) | AI102: Government - NGA | AJ102: Central Visayas Regional Projects I - Regional Project Office (RPO) | AK102: NEDA | AL102: Unknown | AM102: Unknown | AN102: Grey literature | AO102: Other Reports | AP102: LMP, FISH Project, WWF-Philippines and CI-Philippines (2009). Directory of CRM Learning Destinations in the Philippines, 2nd Edition. Cebu City Philippines. http://oneocean.org/download/db_files/directory_of_crm_destinations2Ed.pdf | AQ102: http://oneocean.org/download/db_files/directory_of_crm_destinations2Ed.pdf | AR102: Unknown | AS102: Unknown
A103: 0468 | B103: =CONCATENATE(C103, "-", J103, "-", M103, "-", A103) -> 2025-PH074609000-1988-0468 | C103: 2025 | D103: New | E103: New | F103: Yes | G103: NIR | H103: Negros Oriental | I103: Dauin | J103: PH074609000 | K103: Central Visayas Regional Projects - 1 | L103: Unknown | M103: 1988 | N103: 1985 | O103: 1988 | P103: Substrate Enhancement | Q103: Artificial Reef | R103: Unknown | S103: Unknown | T103: Not applicable | U103: Not applicable | V103: Unknown | W103: Promote coral reef conservation stewardship | X103: M6 | Y103: Coastal resource management | Z103: Unknown | AA103: Development | AB103: Unknown | AC103: Unknown | AD103: Unknown | AE103: Unknown | AF103: Unknown | AG103: Unknown | AH103: Unknown | AI103: Unknown | AJ103: Unknown | AK103: Unknown | AL103: Unknown | AM103: Unknown | AN103: Grey literature | AO103: Other Reports | AP103: LMP, FISH Project, WWF-Philippines and CI-Philippines (2009). Directory of CRM Learning Destinations in the Philippines, 2nd Edition. Cebu City Philippines. http://oneocean.org/download/db_files/directory_of_crm_destinations2Ed.pdf | AQ103: http://oneocean.org/download/db_files/directory_of_crm_destinations2Ed.pdf | AR103: Unknown | AS103: Unknown
A104: 0231 | B104: =CONCATENATE(C104, "-", J104, "-", M104, "-", A104) -> 2023-PH060412000-2012-0231 | C104: =IF(OR(D104="Published", D104="Unpublished"), 2023, IF(D104="New", 2025, "")) -> 2023 | D104: Published | E104: Modified | F104: No | G104: VI | H104: Aklan | I104: Malay | J104: PH060412000 | K104: Code Blue | L104: Unknown | M104: 2012 | N104: Unknown | O104: Unknown | P104: Substrate Enhancement | Q104: Artificial Reef | R104: Engineered/Advanced | S104: Reefbuds | T104: Not applicable | U104: Not applicable | V104: Reefbuds | W104: Unknown | X104: UNK | Y104: Unknown | Z104: Loren Legarda Foundation | AA104: Development | AB104: Local | AC104: NGO | AD104: NGO | AE104: Unknown | AF104: Unknown | AG104: 5000 units | AH104: Sangkalikasan Producers Cooperative | AI104: CSO | AJ104: CSO | AK104: Unknown | AL104: Dr. Harald Kremnitz; Boracay Assoc. of SCUBA diving schools | AM104: Unknown | AN104: Grey literature | AO104: News/Press Release | AP104: Burgos, N. (2012, February 5). 5,000 "reefbuds" to repair Boracay's coral reef system. Philippine Daily Inquirer. https://newsinfo.inquirer.net/140121/5000-%E2%80%98reefbuds%E2%80%99-to-repair-boracay%E2%80%99s-coral-reef-system | AQ104: https://newsinfo.inquirer.net/140121/5000-%E2%80%98reefbuds%E2%80%99-to-repair-boracay%E2%80%99s-coral-reef-system; https://sites.google.com/a/islandecosystems.org/gics; | AR104: Unknown | AS104: Unknown
A105: 0243 | B105: =CONCATENATE(C105, "-", J105, "-", M105, "-", A105) -> 2023-PH060606000-1994-0243 | C105: =IF(OR(D105="Published", D105="Unpublished"), 2023, IF(D105="New", 2025, "")) -> 2023 | D105: Published | E105: Modified | F105: Yes | G105: VI | H105: Antique | I105: Culasi | J105: PH060606000 | K105: Community Fishery Resources Management | L105: Site in Malalison Island | M105: 1994 | N105: 1991 | O105: Unknown | P105: Substrate Enhancement | Q105: Artificial Reef | R105: Concrete | S105: Unspecified concrete structure | T105: Not applicable | U105: Not applicable | V105: Concretre modules (Beams and cylinders piled into reefs) | W105: Scientific Research, "Reestablish a self-sustaining, functioning reef ecosystem" | X105: M2, M7 | Y105: Experimental; Rehabilitation of fish and benthic communities | Z105: Unknown | AA105: Unknown | AB105: Unknown | AC105: Unknown | AD105: Unknown | AE105: Unknown | AF105: Unknown | AG105: 31 modules | AH105: Southeast Asian Fisheries Development Center (SEAFDEC) AQD | AI105: R&D Consortium | AJ105: R&D Consortium | AK105: Unknown | AL105: Unknown | AM105: Fisher's associations | AN105: Peer-reviewed | AO105: Conference Proceeding | AP105: Balgos, M. C. (1995). Evaluation of artificial reef development in the Philippines. In J. L. Munro & M. C. Balgos (Eds.), Artificial reefs in the Philippines (ICLARM Conference Proceedings No. 49, pp. 6–22). International Center for Living Aquatic Resources Management (ICLARM). | AQ105: https://core.ac.uk/download/pdf/6515223.pdf | AR105: Miriam Balgos | AS105: Unknown
A106: 0287 | B106: =CONCATENATE(C106, "-", J106, "-", M106, "-", A106) -> 2023-PH072226000-2010-0287 | C106: =IF(OR(D106="Published", D106="Unpublished"), 2023, IF(D106="New", 2025, "")) -> 2023 | D106: Published | E106: Modified | F106: No | G106: VII | H106: Cebu | I106: City of Lapu-Lapu | J106: PH072226000 | K106: Conservation of Ocean Resources and Aquatic Life (C.O.R.A.L.) | L106: Site in Suba Basbas | M106: 2010 | N106: Unknown | O106: Unknown | P106: Asexual Propagation | Q106: Coral Gardening | R106: Not applicable | S106: Not applicable | T106: In-situ | U106: CNU | V106: CNU | W106: Unknown | X106: UNK | Y106: Unknown | Z106: Conservation of Ocean Resources and Aquatic Life (C.O.R.A.L.) | AA106: Development | AB106: Local | AC106: NGO | AD106: NGO | AE106: Unknown | AF106: Unknown | AG106: Unknown | AH106: Conservation of Ocean Resources and Aquatic Life (C.O.R.A.L.) | AI106: NGO | AJ106: NGO | AK106: Unknown | AL106: Unknown | AM106: Unknown | AN106: Grey literature | AO106: Blog/Website | AP106: CORAL (n.d.). Conservation of Ocean's Resources & Aquatic Life. Who We Are. http://www.coralmovement.org/ | AQ106: http://www.coralmovement.org/ | AR106: Unknown | AS106: Unknown
A107: 0283 | B107: =CONCATENATE(C107, "-", J107, "-", M107, "-", A107) -> 2023-PH072226000-1997-0283 | C107: =IF(OR(D107="Published", D107="Unpublished"), 2023, IF(D107="New", 2025, "")) -> 2023 | D107: Published | E107: Modified | F107: Yes | G107: VII | H107: Cebu | I107: City of Lapu-Lapu | J107: PH072226000 | K107: Coral Farm Project | L107: Site in Caw-oy | M107: 1997 | N107: 1997 | O107: 2000 | P107: Asexual Propagation | Q107: Coral Gardening | R107: Not applicable | S107: Not applicable | T107: In-situ | U107: Bed-type CNU | V107: coral nursery units | W107: "Reestablish a self-sustaining, functioning reef ecosystem", "Provide alternative, sustainable livelihood opportunities" | X107: M2, M5 | Y107: Nursery for coral fragments, maintain biodiversity and generate income for fisherfolk by marketing the farm-grown coral fragments for rehabilitation and ecotourism | Z107: German Ministry of Environment facilitated by the Tropical Ecology Program of the German Technical Cooperation | AA107: Development | AB107: International | AC107: Donor Agency | AD107: Donor Agency | AE107: Unknown | AF107: 2.00 ha | AG107: 275 CNUs/22,000 COPs | AH107: University of San Carlos | AI107: Academe | AJ107: Private Academic Institutions | AK107: CHED - Center for Development Fund | AL107: Unknown | AM107: Caw-oy Fisherfolks | AN107: Peer-reviewed | AO107: Book | AP107: Heeger, T., & Sotto, F. (2000). Coral farming: A tool for reef rehabilitation and community ecotourism. ResearchGate; Tropical Ecology Program of the German Technical Cooperation (GTZ- TOB). | AQ107: https://www.researchgate.net/publication/350049376_Coral_farming_A_tool_for_reef_rehabilitation_and_community_ecotourism | AR107: Unknown | AS107: Unknown
A108: 0190 | B108: =CONCATENATE(C108, "-", J108, "-", M108, "-", A108) -> 2025-PH050516000-2013-0190 | C108: =IF(OR(D108="Published", D108="Unpublished"), 2023, IF(D108="New", 2025, "")) -> 2025 | D108: New | E108: New | F108: No | G108: V | H108: Albay | I108: Santo Domingo | J108: PH050516000 | K108: Coral Genesis Project | L108: Sites in Brgy San Vicente and Brgy Pandayan | M108: 2013 | N108: Unknown | O108: Unknown | P108: Substrate Enhancement | Q108: Artificial Reef, Mineral Accretion | R108: Concrete | S108: Unspecified concrete structure | T108: Not applicable | U108: Not applicable | V108: Concrete; micro solar panel implants | W108: "Reestablish a self-sustaining, functioning reef ecosystem", "Provide alternative, sustainable livelihood opportunities" | X108: M2, M5 | Y108: Coral reef propagation and restoration; tourist attraction | Z108: JCI Legazpi | AA108: Development | AB108: Local | AC108: CSO | AD108: CSO | AE108: Unknown | AF108: 65m long | AG108: Unknown | AH108: JCI Legazpi | AI108: CSO | AJ108: CSO | AK108: Philippine Navy; PCG | AL108: Bicol SCUBA Divers Foundation | AM108: Unknown | AN108: Grey literature | AO108: News/Press Release | AP108: Arguelles, M. (2013, August 7). Helping coral reefs with beads of faith. Philippine Daily Inquirer. https://newsinfo.inquirer.net/460845/helping-coral-reefs-with-beads-of-faith#ixzz5IKRlKWsE | AQ108: https://newsinfo.inquirer.net/460845/helping-coral-reefs-with-beads-of-faith#ixzz5IKRlKWsE | AR108: Unknown | AS108: Unknown
A109: 0403 | B109: =CONCATENATE(C109, "-", J109, "-", M109, "-", A109) -> 2023-PH166724000-2021-0403 | C109: =IF(OR(D109="Published", D109="Unpublished"), 2023, IF(D109="New", 2025, "")) -> 2023 | D109: Published | E109: Modified | F109: No | G109: XIII | H109: Surigao del Norte | I109: City of Surigao | J109: PH166724000 | K109: Coral Reef Farm Project | L109: Site in Brgy Ipil MPA and Brgy Mabua | M109: 2021 | N109: Unknown | O109: Unknown | P109: Substrate Enhancement | Q109: Artificial Reef, Rubble Stabilisation | R109: Concrete | S109: Concrete cubic | T109: Not applicable | U109: Not applicable | V109: Concrete cubic; mesh | W109: Accelerate reef recovery post-disturbance | X109: M1 | Y109: Hasten reef development | Z109: JCI Surigao Nickel | AA109: Development | AB109: Local | AC109: CSO | AD109: CSO | AE109: Unknown | AF109: Unknown | AG109: 1,700 units | AH109: JCI Surigao Nickel | AI109: CSO | AJ109: CSO | AK109: PCG District North Eastern Mindanao; CLGU; DENR; BFAR | AL109: Unknown | AM109: Unknown | AN109: Grey literature | AO109: News/Press Release | AP109: NewsLine Philippines (2021, July 2). Artificial reefs installed in protected waters of Surigao City. NewsLine Philippines: Building Information Highway for the Community. https://newsline.ph/top-stories/2021/07/02/artificial-reefs-installed-in-protected-waters-in-surigao-city/ | AQ109: https://web.facebook.com/jcisurigaonickel/posts/a-reef-for-life-a-dive-of-hopejci-surigao-nickel-in-partnership-with-other-jci-p/3308942349207324/?_rdc=1&_rdr; https://newsline.ph/artificial-reefs-installed-in-protected-waters-in-surigao-city/ | AR109: Unknown | AS109: Unknown
A110: 0175 | B110: =CONCATENATE(C110, "-", J110, "-", M110, "-", A110) -> 2025-PH175301000-2023-0175 | C110: =IF(OR(D110="Published", D110="Unpublished"), 2023, IF(D110="New", 2025, "")) -> 2025 | D110: New | E110: New | F110: No | G110: IV-B | H110: Palawan | I110: Aborlan | J110: PH175301000 | K110: Coral Reef Gardening Project 2023 | L110: Site in Brgy Tigman | M110: 2023 | N110: 2023 | O110: Unknown | P110: Asexual Propagation, Substrate Enhancement | Q110: Artificial Reef, Coral Gardening | R110: Concrete | S110: Concrete domes | T110: In-situ | U110: CNU | V110: CNU; Coral domes and quadrats; transplantation | W110: Unknown | X110: UNK | Y110: Unknown | Z110: Dr. Benjamin Gonzales | AA110: Development | AB110: Local | AC110: Private | AD110: Private | AE110: Unknown | AF110: Unknown | AG110: Unknown | AH110: Dr. Benjamin Gonzales | AI110: Individual/Student Project | AJ110: Individual/Student Project | AK110: MLGU | AL110: B Gonzales Environmental Research and Management Consultancy | AM110: Unknown | AN110: Grey literature | AO110: Social Media | AP110: Aborlan Tourism Office. (2024, August 10). On August 6, 2024, a team led by Dr. Benjamin Gonzales together with BGERMC in collaboration with MENRO and MAO [Status update]. Facebook. https://www.facebook.com/profile.php?id=61560256107542 | AQ110: https://www.facebook.com/profile.php?id=61560256107542 | AR110: Unknown | AS110: Unknown
A111: 0043 | B111: =CONCATENATE(C111, "-", J111, "-", M111, "-", A111) -> 2023-PH015503000-2001-0043 | C111: =IF(OR(D111="Published", D111="Unpublished"), 2023, IF(D111="New", 2025, "")) -> 2023 | D111: Published | E111: Modified | F111: Yes | G111: I | H111: Pangasinan | I111: City of Alaminos | J111: PH015503000 | K111: Coral Reef Habitat and Productivity Enhancement through Coral Transplantation and Giant Clam Restocking | L111: Unknown | M111: 2001 | N111: 2001 | O111: 2005 | P111: Asexual Propagation, Substrate Enhancement | Q111: Direct Transplantation, Artificial Reef | R111: Natural | S111: Giant Clam Restock | T111: Not applicable | U111: Not applicable | V111: Transplantation of corals (tying to marble chips) and reseeding of giant clams | W111: "Reestablish a self-sustaining, functioning reef ecosystem", Scientific Research | X111: M2, M7 | Y111: Improve biodiversity and productivity of stressed coral reef habitats in 10 selected demonstration sites | Z111: Pew Marine Conservation Fellowship | AA111: Research | AB111: International | AC111: Donor Agency | AD111: Donor Agency | AE111: Unknown | AF111: Unknown | AG111: Unknown | AH111: UP MSI | AI111: Academe | AJ111: Public Academic Institutions | AK111: Unknown | AL111: Unknown | AM111: Unknown | AN111: Peer-reviewed | AO111: Journal Article | AP111: Gomez, E., Cabaitan, P., & Vicentuan, K. (2006). Coral culture and transplantation and restocking of giant clams in the Philippines. In J.H. Primavera, E.T. Quinitio, & M. R. R. Eguia (Eds.). Proceedings of the Regional Technical Consultation on Stock Enhancement for Threatened Species of International Concern, Iloilo City, Philippines, 13-15 July 2005 (pp. 39-48). Tigbaua, Iloilo, Philippines: Aquaculture Department, Southeast Asian Fisheries Development Center. Retrieved from https://aquadocs.org/bitstream/handle/1834/40478/GomezED2006.pdf?sequence=1&isAllowed=y | AQ111: https://aquadocs.org/bitstream/handle/1834/40478/GomezED2006.pdf?sequence=1&isAllowed=y | AR111: Dr. Patrick Cabaitan | AS111: Unknown
A112: 0049 | B112: =CONCATENATE(C112, "-", J112, "-", M112, "-", A112) -> 2023-PH015505000-2001-0049 | C112: =IF(OR(D112="Published", D112="Unpublished"), 2023, IF(D112="New", 2025, "")) -> 2023 | D112: Published | E112: Modified | F112: Yes | G112: I | H112: Pangasinan | I112: Anda | J112: PH015505000 | K112: Coral Reef Habitat and Productivity Enhancement through Coral Transplantation and Giant Clam Restocking | L112: Site in Caniogan MPA | M112: 2001 | N112: 2001 | O112: 2005 | P112: Asexual Propagation, Substrate Enhancement | Q112: Direct transplantation, Artificial Reef | R112: Natural | S112: Giant Clam Restock | T112: Not applicable | U112: Not applicable | V112: Transplantation of corals and reseeding of giant clams | W112: "Reestablish a self-sustaining, functioning reef ecosystem", Scientific Research | X112: M2, M7 | Y112: Improve biodiversity and productivity of stressed coral reef habitats in 10 selected demonstration sites | Z112: Pew Marine Conservation Fellowship | AA112: Research | AB112: International | AC112: Donor Agency | AD112: Donor Agency | AE112: Unknown | AF112: Unknown | AG112: Unknown | AH112: UP MSI | AI112: Academe | AJ112: Public Academic Institutions | AK112: Unknown | AL112: Unknown | AM112: Unknown | AN112: Peer-reviewed | AO112: Journal Article | AP112: Gomez, E., Cabaitan, P., & Vicentuan, K. (2006). Coral culture and transplantation and restocking of giant clams in the Philippines. In J.H. Primavera, E.T. Quinitio, & M. R. R. Eguia (Eds.). Proceedings of the Regional Technical Consultation on Stock Enhancement for Threatened Species of International Concern, Iloilo City, Philippines, 13-15 July 2005 (pp. 39-48). Tigbaua, Iloilo, Philippines: Aquaculture Department, Southeast Asian Fisheries Development Center. Retrieved from https://aquadocs.org/bitstream/handle/1834/40478/GomezED2006.pdf?sequence=1&isAllowed=y | AQ112: https://aquadocs.org/bitstream/handle/1834/40478/GomezED2006.pdf?sequence=1&isAllowed=y; https://gefcoral.org/Portals/25/%20Appendix%20C%20-%20Cabaitan,Gomez,Ali%C3%B1o%202008%20JEMBE.pdf | AR112: Dr. Patrick Cabaitan | AS112: Unknown
A113: 0103 | B113: =CONCATENATE(C113, "-", J113, "-", M113, "-", A113) -> 2023-PH037106000-2001-0103 | C113: =IF(OR(D113="Published", D113="Unpublished"), 2023, IF(D113="New", 2025, "")) -> 2023 | D113: Published | E113: Modified | F113: Yes | G113: III | H113: Zambales | I113: Masinloc | J113: PH037106000 | K113: Coral Reef Habitat and Productivity Enhancement through Coral Transplantation and Giant Clam Restocking | L113: Unknown | M113: 2001 | N113: 2001 | O113: 2005 | P113: Asexual Propagation, Substrate Enhancement | Q113: Direct transplantation, Artificial Reef | R113: Natural | S113: Giant Clam Restock | T113: Not applicable | U113: Not applicable | V113: Transplantation of corals and reseeding of giant clams | W113: "Reestablish a self-sustaining, functioning reef ecosystem", Scientific Research | X113: M2, M7 | Y113: Improve biodiversity and productivity of stressed coral reef habitats in 10 selected demonstration sites | Z113: Pew Marine Conservation Fellowship | AA113: Research | AB113: International | AC113: Donor Agency | AD113: Donor Agency | AE113: Unknown | AF113: Unknown | AG113: Unknown | AH113: UP MSI | AI113: Academe | AJ113: Public Academic Institutions | AK113: Unknown | AL113: Unknown | AM113: Unknown | AN113: Peer-reviewed | AO113: Journal Article | AP113: Gomez, E., Cabaitan, P., & Vicentuan, K. (2006). Coral culture and transplantation and restocking of giant clams in the Philippines. In J.H. Primavera, E.T. Quinitio, & M. R. R. Eguia (Eds.). Proceedings of the Regional Technical Consultation on Stock Enhancement for Threatened Species of International Concern, Iloilo City, Philippines, 13-15 July 2005 (pp. 39-48). Tigbaua, Iloilo, Philippines: Aquaculture Department, Southeast Asian Fisheries Development Center. Retrieved from https://aquadocs.org/bitstream/handle/1834/40478/GomezED2006.pdf?sequence=1&isAllowed=y | AQ113: https://aquadocs.org/bitstream/handle/1834/40478/GomezED2006.pdf?sequence=1&isAllowed=y | AR113: Dr. Patrick Cabaitan | AS113: Unknown
A114: 0141 | B114: =CONCATENATE(C114, "-", J114, "-", M114, "-", A114) -> 2023-PH045602000-2001-0141 | C114: =IF(OR(D114="Published", D114="Unpublished"), 2023, IF(D114="New", 2025, "")) -> 2023 | D114: Published | E114: Modified | F114: Yes | G114: IV-A | H114: Quezon | I114: Alabat | J114: PH045602000 | K114: Coral Reef Habitat and Productivity Enhancement through Coral Transplantation and Giant Clam Restocking | L114: Unknown | M114: 2001 | N114: 2001 | O114: 2005 | P114: Asexual Propagation, Substrate Enhancement | Q114: Direct transplantation, Artificial Reef | R114: Natural | S114: Giant Clam Restock | T114: Not applicable | U114: Not applicable | V114: Transplantation of corals and reseeding of giant clams | W114: "Reestablish a self-sustaining, functioning reef ecosystem", Scientific Research | X114: M2, M7 | Y114: Improve biodiversity and productivity of stressed coral reef habitats in 10 selected demonstration sites | Z114: Pew Marine Conservation Fellowship | AA114: Research | AB114: International | AC114: Donor Agency | AD114: Donor Agency | AE114: Unknown | AF114: Unknown | AG114: Unknown | AH114: UP MSI | AI114: Academe | AJ114: Public Academic Institutions | AK114: Unknown | AL114: Unknown | AM114: Unknown | AN114: Peer-reviewed | AO114: Journal Article | AP114: Gomez, E., Cabaitan, P., & Vicentuan, K. (2006). Coral culture and transplantation and restocking of giant clams in the Philippines. In J.H. Primavera, E.T. Quinitio, & M. R. R. Eguia (Eds.). Proceedings of the Regional Technical Consultation on Stock Enhancement for Threatened Species of International Concern, Iloilo City, Philippines, 13-15 July 2005 (pp. 39-48). Tigbaua, Iloilo, Philippines: Aquaculture Department, Southeast Asian Fisheries Development Center. Retrieved from https://aquadocs.org/bitstream/handle/1834/40478/GomezED2006.pdf?sequence=1&isAllowed=y | AQ114: https://aquadocs.org/bitstream/handle/1834/40478/GomezED2006.pdf?sequence=1&isAllowed=y | AR114: Dr. Patrick Cabaitan | AS114: Unknown
A115: 0154 | B115: =CONCATENATE(C115, "-", J115, "-", M115, "-", A115) -> 2023-PH045620000-2001-0154 | C115: =IF(OR(D115="Published", D115="Unpublished"), 2023, IF(D115="New", 2025, "")) -> 2023 | D115: Published | E115: Modified | F115: Yes | G115: IV-A | H115: Quezon | I115: Infanta | J115: PH045620000 | K115: Coral Reef Habitat and Productivity Enhancement through Coral Transplantation and Giant Clam Restocking | L115: Unknown | M115: 2001 | N115: 2001 | O115: 2005 | P115: Asexual Propagation, Substrate Enhancement | Q115: Direct transplantation, Artificial Reef | R115: Natural | S115: Giant Clam Restock | T115: Not applicable | U115: Not applicable | V115: Transplantation of corals (attachment to introduced boulders) and reseeding of giant clams | W115: "Reestablish a self-sustaining, functioning reef ecosystem", Scientific Research | X115: M2, M7 | Y115: Improve biodiversity and productivity of stressed coral reef habitats in 10 selected demonstration sites | Z115: Pew Marine Conservation Fellowship | AA115: Research | AB115: International | AC115: Donor Agency | AD115: Donor Agency | AE115: Unknown | AF115: Unknown | AG115: Unknown | AH115: UP MSI | AI115: Academe | AJ115: Public Academic Institutions | AK115: Unknown | AL115: Unknown | AM115: Unknown | AN115: Peer-reviewed | AO115: Journal Article | AP115: Gomez, E., Cabaitan, P., & Vicentuan, K. (2006). Coral culture and transplantation and restocking of giant clams in the Philippines. In J.H. Primavera, E.T. Quinitio, & M. R. R. Eguia (Eds.). Proceedings of the Regional Technical Consultation on Stock Enhancement for Threatened Species of International Concern, Iloilo City, Philippines, 13-15 July 2005 (pp. 39-48). Tigbaua, Iloilo, Philippines: Aquaculture Department, Southeast Asian Fisheries Development Center. Retrieved from https://aquadocs.org/bitstream/handle/1834/40478/GomezED2006.pdf?sequence=1&isAllowed=y | AQ115: https://aquadocs.org/bitstream/handle/1834/40478/GomezED2006.pdf?sequence=1&isAllowed=y | AR115: Dr. Patrick Cabaitan | AS115: Unknown
A116: 0259 | B116: =CONCATENATE(C116, "-", J116, "-", M116, "-", A116) -> 2023-PH063045000-2001-0259 | C116: =IF(OR(D116="Published", D116="Unpublished"), 2023, IF(D116="New", 2025, "")) -> 2023 | D116: Published | E116: Modified | F116: Yes | G116: VI | H116: Iloilo | I116: Tigbauan | J116: PH063045000 | K116: Coral Reef Habitat and Productivity Enhancement through Coral Transplantation and Giant Clam Restocking | L116: Unknown | M116: 2001 | N116: 2001 | O116: 2005 | P116: Asexual Propagation, Substrate Enhancement | Q116: Direct transplantation, Artificial Reef | R116: Natural | S116: Giant Clam Restock | T116: Not applicable | U116: Not applicable | V116: Transplantation of corals and reseeding of giant clams | W116: "Reestablish a self-sustaining, functioning reef ecosystem", Scientific Research | X116: M2, M7 | Y116: Improve biodiversity and productivity of stressed coral reef habitats in 10 selected demonstration sites | Z116: Pew Marine Conservation Fellowship | AA116: Research | AB116: International | AC116: Donor Agency | AD116: Donor Agency | AE116: Unknown | AF116: Unknown | AG116: Unknown | AH116: UP MSI | AI116: Academe | AJ116: Public Academic Institutions | AK116: Unknown | AL116: Unknown | AM116: Unknown | AN116: Peer-reviewed | AO116: Journal Article | AP116: Gomez, E., Cabaitan, P., & Vicentuan, K. (2006). Coral culture and transplantation and restocking of giant clams in the Philippines. In J.H. Primavera, E.T. Quinitio, & M. R. R. Eguia (Eds.). Proceedings of the Regional Technical Consultation on Stock Enhancement for Threatened Species of International Concern, Iloilo City, Philippines, 13-15 July 2005 (pp. 39-48). Tigbaua, Iloilo, Philippines: Aquaculture Department, Southeast Asian Fisheries Development Center. Retrieved from https://aquadocs.org/bitstream/handle/1834/40478/GomezED2006.pdf?sequence=1&isAllowed=y | AQ116: https://aquadocs.org/bitstream/handle/1834/40478/GomezED2006.pdf?sequence=1&isAllowed=y | AR116: Dr. Patrick Cabaitan | AS116: Unknown
A117: 0262 | B117: =CONCATENATE(C117, "-", J117, "-", M117, "-", A117) -> 2023-PH071210000-2001-0262 | C117: =IF(OR(D117="Published", D117="Unpublished"), 2023, IF(D117="New", 2025, "")) -> 2023 | D117: Published | E117: Modified | F117: Yes | G117: VII | H117: Bohol | I117: Calape | J117: PH071210000 | K117: Coral Reef Habitat and Productivity Enhancement through Coral Transplantation and Giant Clam Restocking | L117: Unknown | M117: 2001 | N117: 2001 | O117: 2005 | P117: Asexual Propagation, Substrate Enhancement | Q117: Direct transplantation, Artificial Reef | R117: Natural | S117: Giant Clam Restock | T117: Not applicable | U117: Not applicable | V117: Transplantation of corals and reseeding of giant clams | W117: "Reestablish a self-sustaining, functioning reef ecosystem", Scientific Research | X117: M2, M7 | Y117: Improve biodiversity and productivity of stressed coral reef habitats in 10 selected demonstration sites | Z117: Pew Marine Conservation Fellowship | AA117: Research | AB117: International | AC117: Donor Agency | AD117: Donor Agency | AE117: Unknown | AF117: Unknown | AG117: Unknown | AH117: UP MSI | AI117: Academe | AJ117: Public Academic Institutions | AK117: Unknown | AL117: Unknown | AM117: Unknown | AN117: Peer-reviewed | AO117: Journal Article | AP117: Gomez, E., Cabaitan, P., & Vicentuan, K. (2006). Coral culture and transplantation and restocking of giant clams in the Philippines. In J.H. Primavera, E.T. Quinitio, & M. R. R. Eguia (Eds.). Proceedings of the Regional Technical Consultation on Stock Enhancement for Threatened Species of International Concern, Iloilo City, Philippines, 13-15 July 2005 (pp. 39-48). Tigbaua, Iloilo, Philippines: Aquaculture Department, Southeast Asian Fisheries Development Center. Retrieved from https://aquadocs.org/bitstream/handle/1834/40478/GomezED2006.pdf?sequence=1&isAllowed=y | AQ117: https://aquadocs.org/bitstream/handle/1834/40478/GomezED2006.pdf?sequence=1&isAllowed=y | AR117: Dr. Patrick Cabaitan | AS117: Unknown
A118: 0271 | B118: =CONCATENATE(C118, "-", J118, "-", M118, "-", A118) -> 2023-PH072202000-2001-0271 | C118: =IF(OR(D118="Published", D118="Unpublished"), 2023, IF(D118="New", 2025, "")) -> 2023 | D118: Published | E118: Modified | F118: Yes | G118: VII | H118: Cebu | I118: Alcoy | J118: PH072202000 | K118: Coral Reef Habitat and Productivity Enhancement through Coral Transplantation and Giant Clam Restocking | L118: Unknown | M118: 2001 | N118: 2001 | O118: 2005 | P118: Asexual Propagation, Substrate Enhancement | Q118: Direct transplantation, Artificial Reef | R118: Natural | S118: Giant Clam Restock | T118: Not applicable | U118: Not applicable | V118: Transplantation of corals and reseeding of giant clams | W118: "Reestablish a self-sustaining, functioning reef ecosystem", Scientific Research | X118: M2, M7 | Y118: Improve biodiversity and productivity of stressed coral reef habitats in 10 selected demonstration sites | Z118: Pew Marine Conservation Fellowship | AA118: Research | AB118: International | AC118: Donor Agency | AD118: Donor Agency | AE118: Unknown | AF118: Unknown | AG118: Unknown | AH118: UP MSI | AI118: Academe | AJ118: Public Academic Institutions | AK118: Unknown | AL118: Unknown | AM118: Unknown | AN118: Peer-reviewed | AO118: Journal Article | AP118: Gomez, E., Cabaitan, P., & Vicentuan, K. (2006). Coral culture and transplantation and restocking of giant clams in the Philippines. In J.H. Primavera, E.T. Quinitio, & M. R. R. Eguia (Eds.). Proceedings of the Regional Technical Consultation on Stock Enhancement for Threatened Species of International Concern, Iloilo City, Philippines, 13-15 July 2005 (pp. 39-48). Tigbaua, Iloilo, Philippines: Aquaculture Department, Southeast Asian Fisheries Development Center. Retrieved from https://aquadocs.org/bitstream/handle/1834/40478/GomezED2006.pdf?sequence=1&isAllowed=y | AQ118: https://aquadocs.org/bitstream/handle/1834/40478/GomezED2006.pdf?sequence=1&isAllowed=y | AR118: Dr. Patrick Cabaitan | AS118: Unknown
A119: 0289 | B119: =CONCATENATE(C119, "-", J119, "-", M119, "-", A119) -> 2023-PH072226000-2001-0289 | C119: =IF(OR(D119="Published", D119="Unpublished"), 2023, IF(D119="New", 2025, "")) -> 2023 | D119: Published | E119: Modified | F119: Yes | G119: VII | H119: Cebu | I119: City of Lapu-Lapu | J119: PH072226000 | K119: Coral Reef Habitat and Productivity Enhancement through Coral Transplantation and Giant Clam Restocking | L119: Unknown | M119: 2001 | N119: 2001 | O119: 2005 | P119: Asexual Propagation, Substrate Enhancement | Q119: Direct transplantation, Artificial Reef | R119: Natural | S119: Giant Clam Restock | T119: Not applicable | U119: Not applicable | V119: Transplantation of corals and reseeding of giant clams | W119: "Reestablish a self-sustaining, functioning reef ecosystem", Scientific Research | X119: M2, M7 | Y119: Improve biodiversity and productivity of stressed coral reef habitats in 10 selected demonstration sites | Z119: Pew Marine Conservation Fellowship | AA119: Research | AB119: International | AC119: Donor Agency | AD119: Donor Agency | AE119: Unknown | AF119: Unknown | AG119: Unknown | AH119: UP MSI | AI119: Academe | AJ119: Public Academic Institutions | AK119: Unknown | AL119: Unknown | AM119: Unknown | AN119: Peer-reviewed | AO119: Journal Article | AP119: Gomez, E., Cabaitan, P., & Vicentuan, K. (2006). Coral culture and transplantation and restocking of giant clams in the Philippines. In J.H. Primavera, E.T. Quinitio, & M. R. R. Eguia (Eds.). Proceedings of the Regional Technical Consultation on Stock Enhancement for Threatened Species of International Concern, Iloilo City, Philippines, 13-15 July 2005 (pp. 39-48). Tigbaua, Iloilo, Philippines: Aquaculture Department, Southeast Asian Fisheries Development Center. Retrieved from https://aquadocs.org/bitstream/handle/1834/40478/GomezED2006.pdf?sequence=1&isAllowed=y | AQ119: https://aquadocs.org/bitstream/handle/1834/40478/GomezED2006.pdf?sequence=1&isAllowed=y | AR119: Dr. Patrick Cabaitan | AS119: Unknown
A120: 0295 | B120: =CONCATENATE(C120, "-", J120, "-", M120, "-", A120) -> 2023-PH072242000-2001-0295 | C120: =IF(OR(D120="Published", D120="Unpublished"), 2023, IF(D120="New", 2025, "")) -> 2023 | D120: Published | E120: Modified | F120: Yes | G120: VII | H120: Cebu | I120: San Francisco | J120: PH072242000 | K120: Coral Reef Habitat and Productivity Enhancement through Coral Transplantation and Giant Clam Restocking | L120: Site in Camotes Island | M120: 2001 | N120: 2001 | O120: 2005 | P120: Asexual Propagation, Substrate Enhancement | Q120: Direct transplantation, Artificial Reef | R120: Natural | S120: Giant Clam Restock | T120: Not applicable | U120: Not applicable | V120: Transplantation of corals and reseeding of giant clams | W120: "Reestablish a self-sustaining, functioning reef ecosystem", Scientific Research | X120: M2, M7 | Y120: Improve biodiversity and productivity of stressed coral reef habitats in 10 selected demonstration sites | Z120: Pew Marine Conservation Fellowship | AA120: Research | AB120: International | AC120: Donor Agency | AD120: Donor Agency | AE120: Unknown | AF120: Unknown | AG120: Unknown | AH120: UP MSI | AI120: Academe | AJ120: Public Academic Institutions | AK120: Unknown | AL120: Unknown | AM120: Unknown | AN120: Peer-reviewed | AO120: Journal Article | AP120: Gomez, E., Cabaitan, P., & Vicentuan, K. (2006). Coral culture and transplantation and restocking of giant clams in the Philippines. In J.H. Primavera, E.T. Quinitio, & M. R. R. Eguia (Eds.). Proceedings of the Regional Technical Consultation on Stock Enhancement for Threatened Species of International Concern, Iloilo City, Philippines, 13-15 July 2005 (pp. 39-48). Tigbaua, Iloilo, Philippines: Aquaculture Department, Southeast Asian Fisheries Development Center. Retrieved from https://aquadocs.org/bitstream/handle/1834/40478/GomezED2006.pdf?sequence=1&isAllowed=y | AQ120: https://aquadocs.org/bitstream/handle/1834/40478/GomezED2006.pdf?sequence=1&isAllowed=y | AR120: Dr. Patrick Cabaitan | AS120: Unknown
A121: 0301 | B121: =CONCATENATE(C121, "-", J121, "-", M121, "-", A121) -> 2023-PH082612000-2001-0301 | C121: =IF(OR(D121="Published", D121="Unpublished"), 2023, IF(D121="New", 2025, "")) -> 2023 | D121: Published | E121: Modified | F121: Yes | G121: VIII | H121: Eastern Samar | I121: Lawaan | J121: PH082612000 | K121: Coral Reef Habitat and Productivity Enhancement through Coral Transplantation and Giant Clam Restocking | L121: Unknown | M121: 2001 | N121: 2001 | O121: 2005 | P121: Asexual Propagation, Substrate Enhancement | Q121: Direct transplantation, Artificial Reef | R121: Natural | S121: Giant Clam Restock | T121: Not applicable | U121: Not applicable | V121: Transplantation of corals and reseeding of giant clams | W121: "Reestablish a self-sustaining, functioning reef ecosystem", Scientific Research | X121: M2, M7 | Y121: Improve biodiversity and productivity of stressed coral reef habitats in 10 selected demonstration sites | Z121: Pew Marine Conservation Fellowship | AA121: Research | AB121: International | AC121: Donor Agency | AD121: Donor Agency | AE121: Unknown | AF121: Unknown | AG121: Unknown | AH121: UP MSI | AI121: Academe | AJ121: Public Academic Institutions | AK121: Unknown | AL121: Unknown | AM121: Unknown | AN121: Peer-reviewed | AO121: Journal Article | AP121: Gomez, E., Cabaitan, P., & Vicentuan, K. (2006). Coral culture and transplantation and restocking of giant clams in the Philippines. In J.H. Primavera, E.T. Quinitio, & M. R. R. Eguia (Eds.). Proceedings of the Regional Technical Consultation on Stock Enhancement for Threatened Species of International Concern, Iloilo City, Philippines, 13-15 July 2005 (pp. 39-48). Tigbaua, Iloilo, Philippines: Aquaculture Department, Southeast Asian Fisheries Development Center. Retrieved from https://aquadocs.org/bitstream/handle/1834/40478/GomezED2006.pdf?sequence=1&isAllowed=y | AQ121: https://aquadocs.org/bitstream/handle/1834/40478/GomezED2006.pdf?sequence=1&isAllowed=y | AR121: Dr. Patrick Cabaitan | AS121: Unknown
A122: 0351 | B122: =CONCATENATE(C122, "-", J122, "-", M122, "-", A122) -> 2023-PH104214000-2001-0351 | C122: =IF(OR(D122="Published", D122="Unpublished"), 2023, IF(D122="New", 2025, "")) -> 2023 | D122: Published | E122: Modified | F122: Yes | G122: X | H122: Misamis Occidental | I122: Sinacaban | J122: PH104214000 | K122: Coral Reef Habitat and Productivity Enhancement through Coral Transplantation and Giant Clam Restocking | L122: Unknown | M122: 2001 | N122: 2001 | O122: 2005 | P122: Asexual Propagation, Substrate Enhancement | Q122: Direct transplantation, Artificial Reef | R122: Natural | S122: Giant Clam Restock | T122: Not applicable | U122: Not applicable | V122: Transplantation of corals and reseeding of giant clams | W122: "Reestablish a self-sustaining, functioning reef ecosystem", Scientific Research | X122: M2, M7 | Y122: Improve biodiversity and productivity of stressed coral reef habitats in 10 selected demonstration sites | Z122: Pew Marine Conservation Fellowship | AA122: Research | AB122: International | AC122: Donor Agency | AD122: Donor Agency | AE122: Unknown | AF122: Unknown | AG122: Unknown | AH122: UP MSI | AI122: Academe | AJ122: Public Academic Institutions | AK122: Unknown | AL122: Unknown | AM122: Unknown | AN122: Peer-reviewed | AO122: Journal Article | AP122: Gomez, E., Cabaitan, P., & Vicentuan, K. (2006). Coral culture and transplantation and restocking of giant clams in the Philippines. In J.H. Primavera, E.T. Quinitio, & M. R. R. Eguia (Eds.). Proceedings of the Regional Technical Consultation on Stock Enhancement for Threatened Species of International Concern, Iloilo City, Philippines, 13-15 July 2005 (pp. 39-48). Tigbaua, Iloilo, Philippines: Aquaculture Department, Southeast Asian Fisheries Development Center. Retrieved from https://aquadocs.org/bitstream/handle/1834/40478/GomezED2006.pdf?sequence=1&isAllowed=y | AQ122: https://aquadocs.org/bitstream/handle/1834/40478/GomezED2006.pdf?sequence=1&isAllowed=y | AR122: Dr. Patrick Cabaitan | AS122: Unknown
... A125: 0424 | B125: =CONCATENATE(C125, "-", J125, "-", M125, "-", A125) -> 2023-PH074610000-2001-0424 | C125: =IF(OR(D125="Published", D125="Unpublished"), 2023, IF(D125="New", 2025, "")) -> 2023 | D125: Published | E125: Modified | F125: Yes | G125: NIR | H125: Negros Oriental | I125: City of Dumaguete | J125: PH074610000 | K125: Coral Reef Habitat and Productivity Enhancement through Coral Transplantation and Giant Clam Restocking | L125: Unknown | M125: 2001 | N125: 2001 | O125: 2005 | P125: Asexual Propagation, Substrate Enhancement | Q125: Direct transplantation, Artificial Reef | R125: Natural | S125: Giant Clam Restock | T125: Not applicable | U125: Not applicable | V125: Transplantation of corals and reseeding of giant clams | W125: Scientific Research, "Reestablish a self-sustaining, functioning reef ecosystem" | X125: M2, M7 | Y125: Improve biodiversity and productivity of stressed coral reef habitats in 10 selected demonstration sites | Z125: Pew Marine Conservation Fellowship | AA125: Research | AB125: International | AC125: Donor Agency | AD125: Donor Agency | AE125: Unknown | AF125: Unknown | AG125: Unknown | AH125: UP MSI | AI125: Academe | AJ125: Public Academic Institutions | AK125: Unknown | AL125: Unknown | AM125: Unknown | AN125: Peer-reviewed | AO125: Journal Article | AP125: Gomez, E., Cabaitan, P., & Vicentuan, K. (2006). Coral culture and transplantation and restocking of giant clams in the Philippines. In J.H. Primavera, E.T. Quinitio, & M. R. R. Eguia (Eds.). Proceedings of the Regional Technical Consultation on Stock Enhancement for Threatened Species of International Concern, Iloilo City, Philippines, 13-15 July 2005 (pp. 39-48). Tigbaua, Iloilo, Philippines: Aquaculture Department, Southeast Asian Fisheries Development Center. Retrieved from https://aquadocs.org/bitstream/handle/1834/40478/GomezED2006.pdf?sequence=1&isAllowed=y | AQ125: https://aquadocs.org/bitstream/handle/1834/40478/GomezED2006.pdf?sequence=1&isAllowed=y | AR125: Dr. Patrick Cabaitan | AS125: Unknown
A126: 0368 | B126: =CONCATENATE(C126, "-", J126, "-", M126, "-", A126) -> 2023-PH112317000-2019-0368 | C126: =IF(OR(D126="Published", D126="Unpublished"), 2023, IF(D126="New", 2025, "")) -> 2023 | D126: Published | E126: Modified | F126: No | G126: XI | H126: Davao del Norte | I126: Island Garden City of Samal | J126: PH112317000 | K126: Coral Reef Preservation and Restoration | L126: Site in Brgy Balet | M126: 2019 | N126: Unknown | O126: Unknown | P126: Substrate Enhancement | Q126: Artificial Reef | R126: Concrete | S126: Unspecified concrete structure | T126: Not applicable | U126: Not applicable | V126: Pyramidal domes | W126: "Reestablish a self-sustaining, functioning reef ecosystem" | X126: M2 | Y126: Restore and improve marine life | Z126: Philippine Navy | AA126: Development | AB126: Local | AC126: Government - NGA | AD126: AFP | AE126: Unknown | AF126: Unknown | AG126: Unknown | AH126: Philippine Navy Naval Forces Eastern Mindanao | AI126: Government - NGA | AJ126: AFP | AK126: CLGU; Civil Military Operations Unit - Eastern Mindanao; Naval Special Operations Unit 7 | AL126: Unknown | AM126: Unknown | AN126: Grey literature | AO126: Social Media | AP126: CMOU-Eastern Mindanao. (2019, August 25). 24 August 19 – The Naval Forces Eastern Mindanao (NFEM), Civil Military Operations Unit-Eastern Mindanao (CMOU-EM), Naval Operations Unit-7 [Status update] [Images attached]. Facebook. https://web.facebook.com/CMOUEM2018/posts/1349837585154833 | AQ126: https://web.facebook.com/CMOUEM2018/posts/24-august-19-the-naval-forces-eastern-mindanao-nfem-civil-military-operations-un/1349837585154833/?_rdc=1&_rdr | AR126: Unknown | AS126: Unknown
A127: 0381 | B127: =CONCATENATE(C127, "-", J127, "-", M127, "-", A127) -> 2023-PH112509000-2024-0381 | C127: =IF(OR(D127="Published", D127="Unpublished"), 2023, IF(D127="New", 2025, "")) -> 2023 | D127: Published | E127: Modified | F127: No | G127: XI | H127: Davao Oriental | I127: City of Mati | J127: PH112509000 | K127: Coral Reef Regeneration Project | L127: Site in Brgy Bobon, Pujada Bay | M127: 2024 | N127: 2024 | O127: Unknown | P127: Substrate Enhancement | Q127: Artificial Reef | R127: Concrete, Engineered/Advanced | S127: 3D-printed clay brick, Unspecified concrete structure | T127: Not applicable | U127: Not applicable | V127: Concrete; 3D printed clay bricks | W127: "Reestablish a self-sustaining, functioning reef ecosystem" | X127: M2 | Y127: Habitat for marine life | Z127: Rethinking, Rebuilding, and Regenerating Coral Reefs (rrreefs) | AA127: Development | AB127: International | AC127: Private | AD127: Private | AE127: Unknown | AF127: 0.01 ha | AG127: 500 concrete base units; 820 3D-printed clay brick modules | AH127: Davao Oriental State University - Regional Integrated Coastal Resource Management Center | AI127: Academe | AJ127: Public Academic Institutions | AK127: Unknown | AL127: RRREEFS; Holcim Cement | AM127: Unknown | AN127: Grey literature | AO127: News/Press Release | AP127: Relator, R. (2024, Mar. 12). Reef made of clay bricks put up in Mati City, Davao Oriental. GMA Regional TV. https://www.gmanetwork.com/regionaltv/features/100891/reef-made-of-clay-bricks-put-up-in-mati-city-davao-oriental/story/ | AQ127: https://www.gmanetwork.com/regionaltv/features/100891/reef-made-of-clay-bricks-put-up-in-mati-city-davao-oriental/story/; https://www.sunstar.com.ph/davao/feature/holcim-supports-startup-rrreefs-in-restoring-coastal-areas-in-mati; https://www.facebook.com/maticitylgu/posts/look-marine-life-is-slowly-settling-in-the-artificial-reef-laid-down-by-several-/824622969706980/ | AR127: Unknown | AS127: Unknown
A128: 0072 | B128: =CONCATENATE(C128, "-", J128, "-", M128, "-", A128) -> 2023-PH015514000-2005-0072 | C128: =IF(OR(D128="Published", D128="Unpublished"), 2023, IF(D128="New", 2025, "")) -> 2023 | D128: Published | E128: Modified | F128: No | G128: I | H128: Pangasinan | I128: Bolinao | J128: PH015514000 | K128: Coral Reef Targeted Research and Capacity Building for Management Program | L128: Site in Silaqui Island (N 16.4454167, E 119.92408333333334) | M128: 2005 | N128: 2005 | O128: Unknown | P128: Asexual Propagation | Q128: Coral Gardening | R128: Not applicable | S128: Not applicable | T128: In-situ | U128: CNU, Suspended nursery, Leg-fixed nursery | V128: CNU; suspended nursery and leg-fixed nursery (plastic mesh and PVC pipe frames) | W128: Scientific Research | X128: M7 | Y128: Research; Analyzed and compared survivorship, bleaching and growth rates of fragments between the different nurseries, species and genotypes | Z128: Global Environment Facility / World Bank | AA128: Research | AB128: International | AC128: Donor Agency | AD128: Donor Agency | AE128: Unknown | AF128: Unknown | AG128: 6,824 ramets | AH128: UP MSI | AI128: Academe | AJ128: Public Academic Institutions | AK128: Unknown | AL128: European Union INCO-DEV Project | AM128: Unknown | AN128: Peer-reviewed | AO128: Journal Article | AP128: Shaish, L., Levy, G., Gomez, E., & Rinkevich, B. (2008). Fixed and suspended coral nurseries in the Philippines: Establishing the first step in the "gardening concept" of reef restoration. Journal of Experimental Marine Biology and Ecology, 358(1), 86-97. https://doi.org/10.1016/j.jembe.2008.01.024 | AQ128: https://www.sciencedirect.com/science/article/abs/pii/S002209810800066X?via%3Dihub | AR128: Lee Shaish | AS128: lishaish@yahoo.com
A129: 0073 | B129: =CONCATENATE(C129, "-", J129, "-", M129, "-", A129) -> 2023-PH015514000-2005-0073 | C129: =IF(OR(D129="Published", D129="Unpublished"), 2023, IF(D129="New", 2025, "")) -> 2023 | D129: Published | E129: Modified | F129: No | G129: I | H129: Pangasinan | I129: Bolinao | J129: PH015514000 | K129: Coral Reef Targeted Research and Capacity Building for Management Program | L129: Site in Santiago Island (N 16.4454167, E 119.92408333333334) | M129: 2005 | N129: 2005 | O129: 2007 | P129: Asexual Propagation | Q129: Coral Gardening | R129: Not applicable | S129: Not applicable | T129: In-situ | U129: CNU | V129: CNU; transplantation | W129: Scientific Research | X129: M7 | Y129: Research; Study the use of Montipora digitata coral species in restoration | Z129: Global Environment Facility / World Bank | AA129: Research | AB129: International | AC129: Donor Agency | AD129: Donor Agency | AE129: Unknown | AF129: Unknown | AG129: 1,960 ramets | AH129: University of Haifa | AI129: Academe | AJ129: Foreign Academic Entity | AK129: UP MSI | AL129: European Union INCO-DEV Project | AM129: Unknown | AN129: Peer-reviewed | AO129: Journal Article | AP129: Shaish, L., Levy, G., Katzir, G., & Rinkevich, B. (2010). Employing a highly fragmented, weedy coral species in reef restoration. Ecological Engineering, 36(10), 1424-1432. https://doi.org/10.1016/j.ecoleng.2010.06.022 | AQ129: https://www.sciencedirect.com/science/article/abs/pii/S092585741000176X | AR129: Lee Shaish | AS129: lishaish@yahoo.com
A130: 0075 | B130: =CONCATENATE(C130, "-", J130, "-", M130, "-", A130) -> 2023-PH015514000-2007-0075 | C130: =IF(OR(D130="Published", D130="Unpublished"), 2023, IF(D130="New", 2025, "")) -> 2023 | D130: Published | E130: Modified | F130: No | G130: I | H130: Pangasinan | I130: Bolinao | J130: PH015514000 | K130: Coral Reef Targeted Research and Capacity Building for Management Program | L130: Site in Silaqui Island and in Binabalian Labas | M130: 2007 | N130: 2007 | O130: 2008 | P130: Asexual Propagation | Q130: Coral Gardening | R130: Not applicable | S130: Not applicable | T130: In-situ | U130: Rope nursery | V130: Mid-water rope nursery; "fixed to bottom" rope nursery | W130: Scientific Research | X130: M7 | Y130: Research; Tested the design and performance of novel prototypes of floating nursery instruments | Z130: Global Environment Facility / World Bank | AA130: Research | AB130: International | AC130: Donor Agency | AD130: Donor Agency | AE130: Unknown | AF130: Unknown | AG130: 1,200 coral fragments | AH130: University of Haifa | AI130: Academe | AJ130: Foreign Academic Entity | AK130: UP MSI | AL130: European Union INCO-DEV Project | AM130: Unknown | AN130: Peer-reviewed | AO130: Journal Article | AP130: Levy, G., Shaish, L., Haim, A., & Rinkevich, B. (2010). Mid-water rope nursery - testing design and performance of a novel reef restoration instrument. Ecological Engineering, 36(4), 560-569. https://doi.org/10.1016/j.ecoleng.2009.12.003 | AQ130: https://www.sciencedirect.com/science/article/abs/pii/S0925857409003498 | AR130: Gideon Levy | AS130: gidi.levi@gmail.com
A131: 0081 | B131: =CONCATENATE(C131, "-", J131, "-", M131, "-", A131) -> 2023-PH015514000-2006-0081 | C131: =IF(OR(D131="Published", D131="Unpublished"), 2023, IF(D131="New", 2025, "")) -> 2023 | D131: Published | E131: Modified | F131: No | G131: I | H131: Pangasinan | I131: Bolinao | J131: PH015514000 | K131: Coral Reef Targeted Research and Capacity Building for Management Program | L131: Site in Silaqui Island and Lucero | M131: 2006 | N131: 2006 | O131: 2007 | P131: Asexual Propagation | Q131: Direct Transplantation, Coral Gardening | R131: Not applicable | S131: Not applicable | T131: In-situ | U131: Not applicable | V131: Nubbin collection; coral nurseries; direct transplantation | W131: Scientific Research | X131: M7 | Y131: Research; Test gardening method vis a vis direct transplantation method | Z131: Global Environment Facility / World Bank | AA131: Research | AB131: International | AC131: Donor Agency | AD131: Donor Agency | AE131: Unknown | AF131: Unknown | AG131: 360 COPs | AH131: UP MSI | AI131: Academe | AJ131: Public Academic Institutions | AK131: Unknown | AL131: European Union INCO-DEV Project | AM131: Unknown | AN131: Peer-reviewed | AO131: Journal Article | AP131: Dela Cruz, D. W., Rinkevich, B., Gomez, E. & Yap, H. (2015). Assessing an abridged nursery phase for slow growing corals used in coral restoration. Ecological Engineering, 84, 408-415. https://doi.org/10.1016/j.ecoleng.2015.09.042 | AQ131: https://www.researchgate.net/publication/282149376_Assessing_an_abridged_nursery_phase_for_slow_growing_corals_used_in_coral_restoration | AR131: Dr. Dexter dela Cruz | AS131: Unknown
A132: 0074 | B132: =CONCATENATE(C132, "-", J132, "-", M132, "-", A132) -> 2023-PH015514000-2007-0074 | C132: =IF(OR(D132="Published", D132="Unpublished"), 2023, IF(D132="New", 2025, "")) -> 2023 | D132: Published | E132: Modified | F132: Yes | G132: I | H132: Pangasinan | I132: Bolinao | J132: PH015514000 | K132: Coral Reef Targeted Research and Capacity Building for Management Program | L132: Site at a fringing reef site in the Malilnep channel (N 16°25′, E 119°56′) | M132: 2007 | N132: 2007 | O132: 2007 | P132: Sexual Propagation | Q132: Larval Enhancement | R132: Not applicable | S132: Not applicable | T132: Not applicable | U132: Not applicable | V132: Larval settlement in fiber cement tiles; in-situ tile installation inside PVC mesh cages | W132: Scientific Research | X132: M7 | Y132: Research; Examine the effect of herbivore exclusion on the survival of 6-week old spat of Acropora tenuis | Z132: Global Environment Facility / World Bank | AA132: Research | AB132: International | AC132: Donor Agency | AD132: Donor Agency | AE132: Unknown | AF132: Unknown | AG132: 120 tiles each with 20 coral spats | AH132: UP MSI | AI132: Academe | AJ132: Public Academic Institutions | AK132: Unknown | AL132: European Union INCO-DEV Project; Singapore Ministry of Education Academic Research Fund Tier 1 FRC | AM132: Unknown | AN132: Peer-reviewed | AO132: Journal Article | AP132: Baria, M. V., Guest, J. R., Edwards, A., Alino, P., Heyward, A. & Gomez, E. (2010). Caging enhances post-settlement survival of juveniles of the scleractinian coral Acropora tenuis. Journal of Experimental Marine Biology and Ecology, 394, 149-153. DOI:10.1016/j.jembe.2010.08.003 | AQ132: https://www.researchgate.net/publication/223475676_Caging_enhances_post-settlement_survival_of_juveniles_of_the_scleractinian_coral_Acropora_tenuis | AR132: Dr. Maria Vanessa Baria Rodriguez | AS132: Unknown
A133: 0076 | B133: =CONCATENATE(C133, "-", J133, "-", M133, "-", A133) -> 2023-PH015514000-2006-0076 | C133: =IF(OR(D133="Published", D133="Unpublished"), 2023, IF(D133="New", 2025, "")) -> 2023 | D133: Published | E133: Modified | F133: No | G133: I | H133: Pangasinan | I133: Bolinao | J133: PH015514000 | K133: Coral Reef Targeted Research and Capacity Building for Management Program | L133: Site at Binlab and Malilnep Ac | M133: 2006 | N133: 2007 | O133: 2007 | P133: Asexual Propagation | Q133: Direct Transplantation | R133: Not applicable | S133: Not applicable | T133: Not applicable | U133: Not applicable | V133: Fragment collection; transplantation using epoxy clay | W133: Scientific Research | X133: M7 | Y133: Research; Growth and survival of Montipora digitata during transplantation; Restore a degraded lagoon environment; | Z133: Global Environment Facility / World Bank | AA133: Research | AB133: International | AC133: Donor Agency | AD133: Donor Agency | AE133: Unknown | AF133: Unknown | AG133: Unknown | AH133: UP MSI | AI133: Academe | AJ133: Public Academic Institutions | AK133: Unknown | AL133: Unknown | AM133: Unknown | AN133: Peer-reviewed | AO133: Journal Article | AP133: Gomez, E., Yap, H. T., Cabaitan, P., & Dizon, R. (2011). Successful Transplantation of a Fragmenting Coral, Montipora digitata, for Reef Rehabilitation. Coastal Management, 39(5), 556-574. https://doi.org/10.1080/08920753.2011.600240 | AQ133: https://www.tandfonline.com/doi/abs/10.1080/08920753.2011.600240?journalCode=ucmg20 | AR133: Dr. H.T. Yap | AS133: Unknown
A134: 0080 | B134: =CONCATENATE(C134, "-", J134, "-", M134, "-", A134) -> 2023-PH015514000-2008-0080 | C134: =IF(OR(D134="Published", D134="Unpublished"), 2023, IF(D134="New", 2025, "")) -> 2023 | D134: Published | E134: Modified | F134: Yes | G134: I | H134: Pangasinan | I134: Bolinao | J134: PH015514000 | K134: Coral Reef Targeted Research and Capacity Building for Management Program | L134: Site in Lucero MPA | M134: 2008 | N134: 2008 | O134: 2010 | P134: Asexual Propagation, Sexual Propagation | Q134: Larval Enhancement, Coral Gardening | R134: Not applicable | S134: Not applicable | T134: In-situ | U134: Coral plug-in | V134: Plastic wall plug "coral plug-in"; in-situ installation cement and PVC mesh | W134: Scientific Research | X134: M7 | Y134: Research; Develop a coral settlement substrate called "coral plug-in" to be used for rearing corals in nurseries and transplant directly to the reef | Z134: Global Environment Facility / World Bank | AA134: Research | AB134: International | AC134: Donor Agency | AD134: Donor Agency | AE134: Unknown | AF134: Unknown | AG134: 150 plug-ins | AH134: UP MSI | AI134: Academe | AJ134: Public Academic Institutions | AK134: Unknown | AL134: Unknown | AM134: Unknown | AN134: Peer-reviewed | AO134: Journal Article | AP134: Guest, J., R., Baria, M. V., Gomez, E., Heyward, A. J., Edwards, A. J. (2014). Closing the circle: is it feasible to rehabilitate reefs with sexually propagated corals?. Coral Reefs, 33, 45-55. https://doi.org/10.1007/s00338-013-1114-1 | AQ134: https://link.springer.com/article/10.1007/s00338-013-1114-1 | AR134: Dr. James Guest | AS134: jrguest@gmail.com
A135: 0226 | B135: =CONCATENATE(C135, "-", J135, "-", M135, "-", A135) -> 2023-PH060412000-2022-0226 | C135: =IF(OR(D135="Published", D135="Unpublished"), 2023, IF(D135="New", 2025, "")) -> 2023 | D135: Published | E135: Modified | F135: Yes | G135: VI | H135: Aklan | I135: Malay | J135: PH060412000 | K135: Coral REEFhabilitation Program | L135: Unknown | M135: 2022 | N135: Unknown | O135: Unknown | P135: Asexual Propagation | Q135: Coral Gardening | R135: Not applicable | S135: Not applicable | T135: In-situ | U135: Table/Frame Nursery | V135: Based on the image, COPs are placed on a coral nursery made up of PVC pipes as frames and green plastic mesh where COPs are placed | W135: "Reestablish a self-sustaining, functioning reef ecosystem" | X135: M2 | Y135: Preservation of the island's watershed and waters | Z135: Boracay Island Water Company | AA135: Development | AB135: Local | AC135: Private | AD135: Private | AE135: Unknown | AF135: Unknown | AG135: Unknown | AH135: Boracay Foundation | AI135: NGO | AJ135: NGO | AK135: MLGU | AL135: Boracay Island Water Company; Boracay Business Scuba Diving Schools | AM135: Unknown | AN135: Grey literature | AO135: News/Press Release | AP135: Boracay Island Water Company invests in marine life (2022, June 16). Manila Water. https://www.manilawater.com/corporate/boracay-water/agos/2022-06-16/boracay-island-water-company-invests-in-marine-life | AQ135: https://www.manilawater.com/corporate/boracay-water/agos/2022-06-16/boracay-island-water-company-invests-in-marine-life; https://journalnews.com.ph/boracay-island-water-company-invests-in-marine-life/ | AR135: Unknown | AS135: Unknown
A136: 0198 | B136: =CONCATENATE(C136, "-", J136, "-", M136, "-", A136) -> 2025-PH051712000-2021-0198 | C136: =IF(OR(D136="Published", D136="Unpublished"), 2023, IF(D136="New", 2025, "")) -> 2025 | D136: New | E136: New | F136: No | G136: V | H136: Camarines Sur | I136: Del Gallego | J136: PH051712000 | K136: Coral Rehabilitation Project | L136: Unknown | M136: 2021 | N136: Unknown | O136: Unknown | P136: Asexual Propagation | Q136: Direct Transplantation | R136: Not applicable | S136: Not applicable | T136: Not applicable | U136: Not applicable | V136: Unknown | W136: Unknown | X136: UNK | Y136: Unknown | Z136: MLGU | AA136: Development | AB136: Local | AC136: Government - LGU | AD136: MLGU | AE136: Unknown | AF136: Unknown | AG136: Unknown | AH136: MLGU | AI136: Government - LGU | AJ136: MLGU | AK136: BFAR 5 | AL136: Unknown | AM136: Unknown | AN136: Grey literature | AO136: Social Media | AP136: BFAR 5 Dive Team (2021, June 2). Experience Del Gallego. We are so grateful and thankful for the effort of people of Del Gallego who envolved and participated in the [Status Update] | AQ136: https://web.facebook.com/109393900941452/videos/836922833909809 | AR136: Unknown | AS136: Unknown
A137: 0420 | B137: =CONCATENATE(C137, "-", J137, "-", M137, "-", A137) -> 2023-PH074609000-2022-0420 | C137: =IF(OR(D137="Published", D137="Unpublished"), 2023, IF(D137="New", 2025, "")) -> 2023 | D137: Published | E137: Modified | F137: Yes | G137: NIR | H137: Negros Oriental | I137: Dauin | J137: PH074609000 | K137: Coral Rescue Project | L137: Site in Atlantis Dive Resort | M137: 2022 | N137: Unknown | O137: Unknown | P137: Asexual Propagation | Q137: Coral Gardening | R137: Not applicable | S137: Not applicable | T137: In-situ | U137: Coral Tree Nursery | V137: coral nursery trees | W137: "Reestablish a self-sustaining, functioning reef ecosystem", Promote coral reef conservation stewardship, "Provide alternative, sustainable livelihood opportunities" | X137: M2, M6, M5 | Y137: Conservation; raising awareness; sustainability; tourism where divers can attach coral fragments | Z137: Atlantis Dive Resorts | AA137: Development | AB137: Local | AC137: Private | AD137: Private | AE137: Unknown | AF137: Unknown | AG137: Unknown | AH137: Atlantis Dive Resorts | AI137: Private | AJ137: Private | AK137: Unknown | AL137: Coral Restoration Foundation; MEAD Foundation | AM137: Unknown | AN137: Grey literature | AO137: Blog/Website | AP137: ZuBlu (2022, February 22). Roni Ben-Aharon from Atlantis Dive Resorts and Liveaboards - An Ecoventure Liveaboard. https://www.zubludiving.com/articles/zublu-insights/roni-ben-aharon-from-atlantis-dive-resorts-and-liveaboards | AQ137: https://www.zubludiving.com/articles/zublu-insights/roni-ben-aharon-from-atlantis-dive-resorts-and-liveaboards | AR137: Unknown | AS137: Unknown
A138: 0267 | B138: =CONCATENATE(C138, "-", J138, "-", M138, "-", A138) -> 2025-PH071233000-Unknown-0267 | C138: =IF(OR(D138="Published", D138="Unpublished"), 2023, IF(D138="New", 2025, "")) -> 2025 | D138: New | E138: New | F138: No | G138: VII | H138: Bohol | I138: Panglao | J138: PH071233000 | K138: Coral Restoration Program in the Philippines | L138: Site in Brgy Danao | M138: Unknown | N138: Unknown | O138: Unknown | P138: Asexual Propagation | Q138: Coral Gardening | R138: Not applicable | S138: Not applicable | T138: In-situ | U138: Coral Tree Nursery | V138: Coral trees | W138: "Reestablish a self-sustaining, functioning reef ecosystem" | X138: M2 | Y138: Restore natural reef system | Z138: Unknown | AA138: Unknown | AB138: Unknown | AC138: Unknown | AD138: Unknown | AE138: Unknown | AF138: Unknown | AG138: Unknown | AH138: LoveLand Living Planet Aquarium | AI138: Private | AJ138: Private | AK138: Bureau of Fire Protection | AL138: Haka Dive Center; Mead Foundation | AM138: Unknown | AN138: Grey literature | AO138: Social Media | AP138: Haka Dive Center (2020, August 8). Coral Reef Restoration Program in the Philippines [Youtube]. https://www.youtube.com/watch?v=jkzZm4QyHDI | AQ138: https://www.youtube.com/watch?v=jkzZm4QyHDI | AR138: Unknown | AS138: Unknown
A139: 0183 | B139: =CONCATENATE(C139, "-", J139, "-", M139, "-", A139) -> 2025-PH175913000-2013-0183 | C139: =IF(OR(D139="Published", D139="Unpublished"), 2023, IF(D139="New", 2025, "")) -> 2025 | D139: New | E139: New | F139: Yes | G139: IV-B | H139: Romblon | I139: San Fernando | J139: PH175913000 | K139: Doydoy Artificial Reefs | L139: Sites found across all Brgys in the municipality | M139: 2013 | N139: Unknown | O139: Unknown | P139: Substrate Enhancement | Q139: Artificial Reef | R139: Natural | S139: Bamboo | T139: Not applicable | U139: Not applicable | V139: Bamboo (shaped as triangle) | W139: "Reestablish a self-sustaining, functioning reef ecosystem" | X139: M2 | Y139: Shelter and breeding ground for fish | Z139: MLGU | AA139: Development | AB139: Local | AC139: Government - LGU | AD139: MLGU | AE139: PHP 10,000.00 | AF139: Unknown | AG139: 100 units | AH139: ABS-CBN Foundation | AI139: NGO | AJ139: NGO | AK139: MLGU | AL139: Unknown | AM139: Unknown | AN139: Grey literature | AO139: News/Press Release | AP139: Manzo, D. (2013, January 22). ABS-CBN Foundation pinangasiwaan ang paglagay ng artificial reefs sa LGU San Fernando. Philippine Information Agency MIMAROPA. https://pia4b.wordpress.com/2013/01/22/abs-cbn-foundation-pinangasiwaan-ang-paglagay-ng-artificial-reefs-sa-lgu-san-fernando/ | AQ139: https://pia4b.wordpress.com/2013/01/22/abs-cbn-foundation-pinangasiwaan-ang-paglagay-ng-artificial-reefs-sa-lgu-san-fernando/ | AR139: Mayor Dindo Rios | AS139: Unknown
A140: 0363 | B140: =CONCATENATE(C140, "-", J140, "-", M140, "-", A140) -> 2023-PH104319000-Unknown-0363 | C140: =IF(OR(D140="Published", D140="Unpublished"), 2023, IF(D140="New", 2025, "")) -> 2023 | D140: Published | E140: Modified | F140: No | G140: X | H140: Misamis Oriental | I140: Medina | J140: PH104319000 | K140: Duka Bay Carbon Cycle Laboratory | L140: Site inside Duka Bay MPA | M140: Unknown | N140: Unknown | O140: Unknown | P140: Asexual Propagation, Substrate Enhancement | Q140: Artificial Reef, Direct Transplantation | R140: Unknown | S140: Unknown | T140: Not applicable | U140: Not applicable | V140: "Large coral clones" | W140: Scientific Research, Ecological engineering | X140: M7, M8 | Y140: Develop a transplantable coral technology | Z140: Duka Bay Resort Inc. | AA140: Research | AB140: Local | AC140: Private | AD140: Private | AE140: Unknown | AF140: Unknown | AG140: Unknown | AH140: Duka Bay Resort Inc. | AI140: Private | AJ140: Private | AK140: Unknown | AL140: Ernesto Pelaez; Eduardo Yap | AM140: Unknown | AN140: Grey literature | AO140: News/Press Release | AP140: Sustainable coral nurseries ensure future of Philippine coral reefs (2011, May 28). Eco-Business. https://www.eco-business.com/news/sustainable-coral-nurseries-ensure-future-of-philippine-coral-reefs/ | AQ140: https://www.eco-business.com/news/sustainable-coral-nurseries-ensure-future-of-philippine-coral-reefs/ | AR140: Ernesto Pelaez | AS140: 0917 794 2759
A141: 0026 | B141: =CONCATENATE(C141, "-", J141, "-", M141, "-", A141) -> 2023-PH013309000-2014-0026 | C141: =IF(OR(D141="Published", D141="Unpublished"), 2023, IF(D141="New", 2025, "")) -> 2023 | D141: Published | E141: Modified | F141: No | G141: I | H141: La Union | I141: Caba | J141: PH013309000 | K141: Ecosystems Improved for Sustainable Fisheries (ECOFISH) Project | L141: Unknown | M141: 2014 | N141: 2012 | O141: 2017 | P141: Substrate Enhancement | Q141: Artificial Reef | R141: Unknown | S141: Unknown | T141: Not applicable | U141: Not applicable | V141: Unknown | W141: Reduce population declines and ecosystem degradation | X141: M4 | Y141: Facilitate regeneration of fish populations | Z141: USAID | AA141: Development | AB141: International | AC141: Donor Agency | AD141: Donor Agency | AE141: Unknown | AF141: Unknown | AG141: Unknown | AH141: MLGU | AI141: Government - LGU | AJ141: MLGU | AK141: Unknown | AL141: Unknown | AM141: Unknown | AN141: Grey literature | AO141: Government Report | AP141: ECOFISH Project. (2015). Quarterly Progress Update, ECOFISH Document No. 01/2015. https://faspselib.denr.gov.ph/sites/default/files//Publication%20Files/ECOFISH%20Project%20Update.PDF.pdf | AQ141: https://faspselib.denr.gov.ph/sites/default/files//Publication%20Files/ECOFISH%20Project%20Update.PDF.pdf | AR141: Unknown | AS141: Unknown
A142: 0191 | B142: =CONCATENATE(C142, "-", J142, "-", M142, "-", A142) -> 2023-PH050517000-2016-0191 | C142: =IF(OR(D142="Published", D142="Unpublished"), 2023, IF(D142="New", 2025, "")) -> 2023 | D142: Published | E142: Modified | F142: No | G142: V | H142: Albay | I142: City of Tabaco | J142: PH050517000 | K142: Establishment of Coral Demonstration Site in San Miguel Island | L142: Site in San Miguel Island | M142: 2016 | N142: Unknown | O142: Unknown | P142: Asexual Propagation | Q142: Coral Gardening | R142: Not applicable | S142: Not applicable | T142: In-situ | U142: Bamboo raft | V142: Bamboo raft; hanging monoline | W142: Scientific Research | X142: M7 | Y142: Experimental; Viability of low technology and low cost methodologies in coral reef restoration | Z142: Bicol University - Tabaco Campus | AA142: Research | AB142: Local | AC142: Academe | AD142: Public Academic Institutions | AE142: Unknown | AF142: Unknown | AG142: Unknown | AH142: Bicol University - Tabaco Campus | AI142: Academe | AJ142: Public Academic Institutions | AK142: Unknown | AL142: Unknown | AM142: Unknown | AN142: Grey literature | AO142: Unpublished article | AP142: Mendoza, A. B., Nieves, P., & Kubota, S. (n.d.). Reef Coral Restoration Program in the Bicol Region, Philippines. https://kochi.repo.nii.ac.jp/?action=repository_action_common_download&item_id=8640&item_no=1&attribute_id=17&file_no=1 | AQ142: https://kochi.repo.nii.ac.jp/?action=repository_action_common_download&item_id=8640&item_no=1&attribute_id=17&file_no=1 | AR142: Unknown | AS142: Unknown
A143: 0077 | B143: =CONCATENATE(C143, "-", J143, "-", M143, "-", A143) -> 2023-PH015514000-2005-0077 | C143: =IF(OR(D143="Published", D143="Unpublished"), 2023, IF(D143="New", 2025, "")) -> 2023 | D143: Published | E143: Modified | F143: No | G143: I | H143: Pangasinan | I143: Bolinao | J143: PH015514000 | K143: European Union INCO-DEV Project | L143: Site in Silaqui Island (N 16.4459167, E 119.92394444444444) | M143: 2005 | N143: 2005 | O143: 2007 | P143: Asexual Propagation | Q143: Direct Transplantation | R143: Not applicable | S143: Not applicable | T143: Not applicable | U143: Not applicable | V143: Coral transplantation; Attachment to dead giant clam shells; frames made of PVC pipes and mesh, angle iron for anchor | W143: Scientific Research | X143: M7 | Y143: Research; Compare the self-attachment times of different coral species to natural calcium carbonate substrate | Z143: European Union INCO-DEV Project | AA143: Research | AB143: International | AC143: Donor Agency | AD143: Donor Agency | AE143: Unknown | AF143: Unknown | AG143: Unknown | AH143: National University of Singapore | AI143: Academe | AJ143: Foreign Academic Entity | AK143: UP MSI | AL143: GEF/WB Coral Reef Targeted Research | AM143: Unknown | AN143: Peer-reviewed | AO143: Journal Article | AP143: Guest, J. R., Dizon, R., Edwards, A. J., Franco, C., & Gomez, E. (2011). How Quickly do Fragments of Coral "Self-Attach" after Transplantation?. Restoration Ecology, 19(2), 234-242. https://doi.org/10.1111/j.1526-100X.2009.00562.x | AQ143: https://www.academia.edu/25026620/How_Quickly_do_Fragments_of_Coral_Self_Attach_after_Transplantation | AR143: Dr. James Guest | AS143: james.guest@nus.edu.sg
A144: 0169 | B144: =CONCATENATE(C144, "-", J144, "-", M144, "-", A144) -> 2023-PH174002000-2021-0169 | C144: =IF(OR(D144="Published", D144="Unpublished"), 2023, IF(D144="New", 2025, "")) -> 2023 | D144: Published | E144: Modified | F144: Yes | G144: IV-B | H144: Marinduque | I144: Buenavista | J144: PH174002000 | K144: Filipinnovation on Coral Reef Restoration | L144: Site in Poctoy | M144: 2021 | N144: Unknown | O144: Unknown | P144: Asexual Propagation | Q144: Coral Gardening | R144: Not applicable | S144: Not applicable | T144: In-situ | U144: Table/Frame Nursery | V144: CNU (steel bar table) that are designed to hold 500 COPs per batch several times a year | W144: "Reestablish a self-sustaining, functioning reef ecosystem", Mitigate anticipated coral loss prior to a known disturbance | X144: M2, M3 | Y144: Reverse reef degradation (from silitation and sedimentation along the coast) and improve productivity of marine resources | Z144: DOST-MIMAROPA | AA144: Development | AB144: Local | AC144: Government - NGA | AD144: DOST | AE144: Unknown | AF144: Unknown | AG144: 10 CNUs | AH144: DOST-MIMAROPA | AI144: Government - NGA | AJ144: DOST | AK144: PLGU; BFAR; DENR; Marinduque State College | AL144: Unknown | AM144: local fishermen groups | AN144: Grey literature | AO144: News/Press Release | AP144: Luci-Atienza, C. (2021, June 25). "Filipinnovation": MIMAROPA's first large-scale coral restoration project already started. Manila Bulletin. https://mb.com.ph/2021/06/24/filipinnovation-mimaropas-first-large-scale-coral-restoration-project-already-started/ | AQ144: https://mb.com.ph/2021/06/24/filipinnovation-mimaropas-first-large-scale-coral-restoration-project-already-started/ | AR144: Unknown | AS144: Unknown
...

Sheet Glossary
A1: Status | B1: Definition | D1: Change_type | E1: Definition | G1: EXISTING Restoration_project_title | I1: Year | J1: Definition | L1: Gen_method | M1: Definition | O1: Specific_method | P1: Definition | R1: AR_material_type | S1: Definition | U1: AR_design | V1: Definition | X1: Nursery_type_loc | Y1: Definition | AA1: Nursery_type_design | AB1: Definition | AD1: Motivations from Bostrom-Einarsson et al. (2020) | AE1: Code | AF1: Definition | AH1: Funder_loc | AI1: Definition | AK1: Fund_type | AL1: Definition | AN1: Funder_sector | AO1: Definition | AQ1: Proponent_sector | AR1: Definition | AT1: Proponent_Gov_Type | AU1: Definition | AW1: Proponent_Specific_Entity | AX1: Definition | AZ1: Literature_type | BA1: Definition | BC1: Source Type | BD1: Definition
A2: Published | B2: Present in the 2023 database and included in the Matorres et al. (2024) paper | D2: Modified | E2: Changes were made to retained columns when comparing the current version to Matorres et al. (2024) | G2: Abig Pangasinan | I2: Unknown | J2: Explicit year when the project was either established, started, or ended was not mentioned | L2: Asexual Propagation | M2: Growing corals from fragments of existing corals. | O2: Direct transplantation | P2: Method involving transplanting coral fragments or colonies directly onto the substrate | R2: Concrete | S2: Structures made from concrete, including various shapes like domes, blocks, pyramids, and other molded forms. | U2: Not applicable | V2: Project is not an artificial reef project | X2: Not applicable | Y2: Project is not a coral gardening project | AA2: Not applicable | AB2: Project is not a coral gardening project | AD2: Accelerate reef recovery post-disturbance | AE2: M1 | AF2: Natural reef recovery is a lengthy processranging from 5 years to decades, and transplanting coral colonies on reef saffected by recruitment limitation may kick-start the recovery process | AH2: Local | AI2: Funder is based in the Philippines | AK2: Commercial | AL2: Restoration activities that are commercial in purpose | AN2: Academe | AO2: Funder is a university or HEI | AQ2: Academe | AR2: Project was implented by an academic institution, university, or HEI | AT2: Unknown | AU2: Project implementor was not indicated | AW2: Unknown | AZ2: Peer-reviewed | BA2: Published studies that have been reviewed by experts in the field before publication. This include journal articles and books. Conference proceedings may also be included in this category, following the treatment in Boström-Einarsson et al. (2020). | BC2: Book
A3: Unpublished | B3: Present in the 2023 dataset but not included in the Matorres et al. (2024) paper | D3: Unchanged | E3: No changes were made to retained columns when comparing the current version to Matorres et al. (2024) | G3: Acantasia Project | I3: 1970 | L3: Sexual Propagation | M3: Growing corals from larvae produced by coral spawning | O3: Coral gardening | P3: Method involving transplanting coral fragments or colonies after growing them in nurseries | R3: Tires | S3: Artificial reefs made primarily from rubber tires, either bundled, stacked, or combined with other materials. | U3: Bamboo | V3: Artificial Reef is made up mostly of bamboo materials for its frame | X3: Ex-situ | Y3: Coral nurseries are found on land, in controlled conditions | AA3: Table/Frame Nursery | AB3: Flat table in which the frames are either made out of steel, PVC, or bamboo that is placed on the seafloor | AD3: Reestablish a self-sustaining, functioning reef ecosystem | AE3: M2 | AF3: Objective here is not to restore a known coral community but rather rehabilitate coral reefecosystem processes to secure critical ecosystem services | AH3: International | AI3: Funder is based abroad or outside the Philippines | AK3: Development | AL3: Catch-all for projects whose stated objectives are related to rehabilitation, restoration, protection, provision of shelter and breeding ground, tourism, education, addressing illegal fishing and declining fish catch, tourism, coastal resource management, CSR, disaster rehab, livelihood, technology demonstration | AN3: CSO | AO3: Funder is a civil society group or clubs | AQ3: CSO | AR3: Project was implented by a civil socity group or club | AT3: Not applicable | AU3: Project was not established by the government | AW3: DENR | AX3: Department of Environment and Natural Resources, including PENRO and CENRO | AZ3: Grey literature | BA3: Documents that are not published in peer-reviewed journals. This includes reports, media articles, theses, unpublished manuscripts, NGO publications, and social media posts. | BC3: Conference Abstract
A4: New | B4: Added as a new entry in the 2025 database | D4: Deleted | E4: Project was included in Matorres et al. (2024) but was removed from the current database due to reasons such as: (1) missing valid reference, (2) split into multiple distinct projects, (3) identified as a duplicate, or (4) other relevant reasons | G4: ACIAR Coral Reef Restoration Project | I4: 1971 | L4: Substrate Enhancement | M4: Improving the seabed to support coral settlement | O4: Micro-fragmentation | P4: Method involving transplanting very small coral fragments to promote rapid tissue growth and fusion | R4: Natural | S4: Reefs made from biodegradable or naturally occurring materials such as bamboo, dead coral, sand, or giant clams. | U4: Bamboo pyramidal | X4: In-situ | Y4: Coral nurseries are found in the sea, in natural conditions | AA4: Coral Tree Nursery | AB4: Coral fragments are suspended from horizontal bars attaches to a vertical trunk; materials are either made from PVC, bamboo, or steel | AD4: Mitigate anticipated coral loss prior to a known disturbance | AE4: M3 | AF4: Mitigation strategy, whereby coral colonies are relocated from a soon-to-be impacted site to a safer site | AH4: Unknown | AI4: Funder was not indicated | AK4: Research | AL4: Restoration project stated objectives are for experiment, study, testing and those funded by research fellowships. Majority of these were implemented the academe. | AN4: Private | AO4: Funder is among the following: resorts, companies, corporations, foundations, social enterprises | AQ4: Private | AR4: Project was implemented by among the following: resorts, companies, corporations, social enterprises | AT4: NGA | AU4: Project was implemented by a national government authority, including BFAR, DENR, DOST, PCG, Phillippine Army | AW4: DOST | AX4: Department of Science and Technology | AZ4: Survey | BA4: Projects indentified via survey questionnaire or personal communication. | BC4: Conference Proceeding | BD4: Can either be grey or peer-reviewed literature. A rule of thumb is if the paper was cited by journal articles, then it is peer-reviewed. otherwise, it is grey literature.
D5: New | E5: Project was added as a new entry in the 2025 database, with no previous version to compare | G5: Adopt a Coral | I5: 1972 | L5: Unknown | M5: Restoration method was not indicated | O5: Larval enhancement | P5: Method involving the use of sexually produced coral larvae, grown in-situ or ex-situ before release or transplantation | R5: Metal/Wreck | S5: Structures made from metal components like steel frames or rebars, or large sunken objects such as ships or planes. | U5: Tires | X5: Unknown | Y5: The location of the coral nursery was not indicated. | AD5: Reduce population declines and ecosystem degradation | AE5: M4 | AF5: Conserve endangered coral species, and safeguard critical ecosystem services on threatened coral reefs by increasing coral cover, diversity, and overall structural complexity. This objective also includes creating artificial “sacrificial sites to movetourism pressures away from pristine, natural reef areas” | AK5: Unknown | AL5: Restoration objective was not stated nor funding agency | AN5: Government - NGA | AO5: Funder is a national government agency in the Philippines. | AQ5: Government - NGA | AR5: Project was implemented by a national government agency in the Philippines. | AT5: LGU | AU5: Project was implemented by a local government unit, including PLGU, MLGU, CLGU | AW5: MAFAR | AX5: Ministry of Agriculture, Fisheries, and Agrarian Reform | BC5: Journal Article | BD5: Articles published in an academic journal indexed in recognised scholarly databases (e.g., Scopus, Web of Science), and typically peer-reviewed.
G6: Agutayan Artificial Reef Project and Giant Clam Seeding | I6: 1973 | O6: Artificial reef | P6: Method involving the installation of artificial structures to provide habitat and promote coral settlement | R6: Engineered/Advanced | S6: Specially designed reef units using innovative materials or technology, such as Reef Balls, Reefbuds, or 3D-printed modules. | U6: Unspecified concrete structure | V6: The type of concrete artificial reef structure was not explicitly mentioned in the source material | AA6: Unknown | AB6: Project is a coral gardening project use of coral nurseries was not indicated | AD6: Provide alternative, sustainable livelihood opportunities | AE6: M5 | AF6: Coral transplantation efforts may provide alternative livelihood opportunities, such as enhancing fisheries habitat, tourism, and coral farming | AN6: Government - LGU | AO6: Funder is a local government unit in the Philippines. | AQ6: Government - LGU | AR6: Project was implemented by a local government unit in the Philippines. | AT6: RGA | AU6: Project was implemented by a regional government authority, which is specific to the region of BARMM | AW6: BFAR | AX6: Bureau of Fisheries and Aquatic Resources | BC6: Personal communication | BD6: Projects that were collated via phone call, email, or face-to-face.
G7: An Integrated Approach to Marine Resource Conservation and Sustainable Fisheries Management to Strengthen Coastal Communities in Zambales | I7: 1974 | O7: Mineral accretion | P7: Method involving the application of low-voltage electrical current to artificial substrates | R7: Recycled/Waste | S7: Reefs built using repurposed materials like glass bottles, PVC pipes, or other non-natural, non-metal waste items. | U7: Concrete cube | V7: Artificial reef wherein the individul units are concrete cubes with a hollow square face on each side | AA7: Bamboo raft | AD7: Promote coral reef conservation stewardship | AE7: M6 | AF7: Involvement in coral transplantation will foster conservation stewardship through increased education and research opportunities | AN7: Government - RGA | AO7: Funder is a regional government unit in the Philippines, which is most of the time just MAFAR). | AQ7: Government - RGA | AR7: Project was implemented by a regional government unit in the Philippines, which is most of the time just MAFAR). | AT7: Academe | AU7: Retained as is for the classification | AW7: AFP | AX7: Armed Forces of the Philippines | BC7: Questionnaire | BD7: Responses from the survey questionnaire that was circulated from August to December 2022.
G8: APEC PPSTI-5 | I8: 1975 | O8: Substrate stabilisation | P8: Method involving the use of mesh nets to stabilise loose or unstable substrate | R8: Hybrid | S8: Structures combining two or more material types (e.g., tires and bamboo) where no single material is dominant. | U8: Concrete cubic | AA8: CNU | AB8: In-situ nursery where coral fragments/COPs are being tended to grow; can be made out of steel bar for its frame | AD8: Scientific Research | AE8: M7 | AF8: Restoration conducted to advance scientific understanding of coral reef ecology, restoration techniques, or related processes through systematic study and data collection | AN8: NGO | AO8: Funder is a non-profit, non-governmental organization | AQ8: NGO | AR8: Project was implemented by non-profit, non-governmental organization | AT8: CSO | AU8: Retained as is for the classification | AW8: PCG | AX8: Philippine Coast Guard | BC8: Social Media | BD8: Projects that were collected from social media platforms such as Facebook or Youtube.
G9: Artificial Coral Reef Project | I9: 1976 | O9: Algae Removal | P9: Method involving the removal of algae to reduce competition for corals | R9: Not applicable | S9: Project does not use artificial reefs. | U9: Concrete domes | V9: Artificial reef structure that is dome-shaped with hollow portions | AA9: Suspended nursery | AD9: Ecological engineering | AE9: M8 | AF9: Restoration designed to modify and enhance the physical or biological environment to improve habitat conditions and support coral reef recovery using innovative technology | AN9: Donor Agency | AO9: Funder is among the following: funding agencies, fellowships, and are usually foreign institution | AQ9: Donor Agency | AR9: Project was implemented by foreign funding agency | AT9: Donor Agency | AW9: CLGU | AX9: City Local Government Unit | BC9: Blog/Website | BD9: Entries published on online platforms, typically authored by individuals, organisations, or project teams. This includes project descriptions or updates shared through blog sites, non-governmental institutional websites, or other web-based formats that are not disseminated through formal media outlets.
G10: Artificial Coral Reefs | I10: 1977 | R10: Unknown | S10: Project used artificial reefs but the type of material was not indicated in the source material. | U10: Reefbuds | V10: Artificial reef technology composed of environment-friendly natuyral organic and inorganic materials, such as shredded coconut husk, rice stalks, volcanic rock, activated carbon, sand, and cement. They form hollow pyramid/dome structures | AA10: Leg-fixed nursery | AD10: Unknown | AE10: UNK | AF10: Project objective was not indicated | AN10: Individual | AO10: Funder is an individual person | AQ10: Individual/Student Project | AR10: Project was implemented by a lone individual or as part of a student project | AT10: NGO | AW10: MLGU | AX10: Municipal Local Government Unit | BC10: News/Press Release | BD10: Official announcements or updates from organisations or government agencies, written in a formal and factual style. These may be published on websites such as the Philippine News Agency (pna.gov.ph), ABS-CBN News (news.abs-cbn.com), or Philippine Daily Inquirer (inquirer.net). Some LGUs and NGOs may also publish press releases on their own sites or platforms like Blogspot.
G11: Artificial Reef Deployment Project | I11: 1978 | O11: Unknown | P11: Restoration method was not indicated | U11: Concrete jackstone | V11: Concrete structure characterized by six protruding legs | AA11: Iron bar dome CNU | AN11: Unknown | AO11: Funder is not indicated | AQ11: PO | AR11: People's Organization, meaning these are community-based organizations representing sectors, usually marginal | AT11: Private | AW11: PLGU | AX11: Provincial Local Government Unit | BC11: Government Report | BD11: Official publications produced by government agencies in the Philippines, these may include briefer reports, technical reports, annual reports or the like
G12: Artificial Reef Development Program | I12: 1979 | U12: Concrete pyramid | V12: Concrete structure that is shaped into a pyramid, including those that were molded into a pyramid before installment, or formed from slabs into a pyramid underwater | AA12: Bed-type CNU | AB12: The Coral nursery unit is fixed to the seabed as a concrete square strructure in which the coral fragments are planted within it | AQ12: R&D Consortium | AR12: "Southeast Asian Fisheries Development Center", which is a 'consortium' of member countries of the ASEAN working collectively on specific research and development activities | AT12: Individual | AW12: Public Academic Institutions | AX12: Includes SUCs, LUCs, and Public Research Institutes | BC12: Unpublished article | BD12: A research article prepared for submission to a journal but not yet published or accepted. The format is usually in a journal article style. This can include thesis, journal article, or abstract.
G13: Artificial Reef Project | I13: 1980 | U13: Concrete roundtable | AA13: Integrated coral silviculture | AQ13: Unknown | AR13: Project implementor was not indicated | AT13: PO | AW13: Private Academic Institutions | AX13: Includes Private HEIs | BC13: Other Reports | BD13: This are print articles that are produced by non-governmental institutions.
G14: Artificial Reefs Project | I14: 1981 | U14: Concrete sculpture | V14: A concrete structure that is shaped to resemble humans, animals, or the like | AA14: Coral plug-in | AT14: R&D Consortium | AW14: Foreign Academic Entity
G15: ASEAN Australia Economic Cooperation Program Living Coastal Resources Project | I15: 1982 | U15: Concrete slabs | AA15: Angle-bar nursery | AW15: DOE | AX15: Department of Energy, including National Power Corporation
G16: Bioconservation Project under DENR ICRM | I16: 1983 | U16: Concrete statue | AA16: Rope nursery | AW16: DA | AX16: Department of Agriculture
G17: Biri Buds | I17: 1984 | U17: Concrete tent-like | AA17: Coral tree | AW17: DSWD | AX17: Department or Social Welfare and Development
G18: Bolinao Coral Reef Targeted Research | I18: 1985 | U18: Concrete triangle | AA18: Nursery trays | AW18: OWAA | AX18: Overseas Workers Welfare Administration
G19: Boracay Beach Management Program | I19: 1986 | U19: Concrete tripod | V19: A concrete structure with three legs or supports | AW19: CHED | AX19: Commission on Higher Education
G20: Bugtong Bato MPA Artificial Coral Reef Project | I20: 1987 | U20: 3D-printed clay brick | AW20: PNP | AX20: Philippine National Police
G21: Build-A-Reef | I21: 1988 | U21: PVC pipe
G22: Build-A-Reef Program | I22: 1989 | U22: Glass bottles
G23: Build-a-Reef Project | I23: 1990 | U23: Sand
G24: Building Back Better | I24: 1991 | U24: Dead coral | AW24: CSO | AX24: Retained as is for the classification
G25: Calancan Bay Rehabilitation Program | I25: 1992 | U25: Eco-MER | AW25: Donor Agency | AX25: Retained as is for the classification
G26: Central Visayas Regional Projects - 1 | I26: 1993 | U26: EcoReefs (ceramic-based) | V26: It is made of ceramic stoneware that is ideal for the settlement of corals and other invertebrates
G27: Code Blue | I27: 1994 | U27: Steel pipe | AW27: NGO | AX27: Retained as is for the classification
G28: Community Fishery Resources Management | I28: 1995 | U28: Wreck structure (plane, boat) | AW28: Private | AX28: Retained as is for the classification
G29: Conservation of Ocean Resources and Aquatic Life (C.O.R.A.L.) | I29: 1996 | U29: Beams and cylinders | AW29: Individual/Student Project | AX29: Retained as is for the classification
G30: Coral Farm Project | I30: 1997 | U30: Hollow block | AW30: Central Visayas Regional Projects I - Regional Project Office (RPO)
G31: Coral Genesis Project | I31: 1998 | U31: Rebars | AW31: Philippine Fisheries Devt. Authority
G32: Coral Reef Farm Project | I32: 1999 | U32: Reef ball | V32: They are typically dome-shaped with holes and rough surfaces; constructed from special, ph-baalnce microsilica concrete | AW32: PO
G33: Coral Reef Gardening Project 2023 | I33: 2000 | U33: Cement with silica | AW33: R&D Consortium | AX33: Retained as is for the classification
G34: Coral Reef Habitat and Productivity Enhancement through Coral Transplantation and Giant Clam Restocking | I34: 2001 | U34: Rubber
G35: Coral Reef Preservation and Restoration | I35: 2002 | U35: Small airplane
G36: Coral Reef Regeneration Project | I36: 2003 | U36: Junk material | V36: Artificial reef is made wholly from waste items such as steel cabinets, wreck structures (planes, boats) etc without modifications
G37: Coral Reef Targeted Research and Capacity Building for Management Program | I37: 2004 | U37: Steel frame
G38: Coral REEFhabilitation Program | I38: 2005 | U38: Unknown
G39: Coral Rehabilitation Project | I39: 2006 | U39: Steel cabinet
G40: Coral Rescue Project | I40: 2007 | U40: Steel frame
G41: Coral Restoration Program in the Philippines | I41: 2008 | U41: Steel pipe
G42: Doydoy Artificial Reefs | I42: 2009 | U42: Terracotta tiles
G43: Duka Bay Carbon Cycle Laboratory | I43: 2010 | U43: Tires
G44: Ecosystems Improved for Sustainable Fisheries (ECOFISH) Project | I44: 2011 | U44: Tree nursery
G45: Establishment of Coral Demonstration Site in San Miguel Island | I45: 2012 | U45: Wreck structure (plane, boat)
G46: European Union INCO-DEV Project | I46: 2013 | U46: Cement with silica
G47: Filipinnovation on Coral Reef Restoration | I47: 2014 | U47: Hollow block
G48: FishCORAL | I48: 2015 | U48: Quadrats
... G53: Habitat Enhancement Project: Bagonbanua Marine Reserve and Fish Sanctuary | I53: 2020 | U53: Terracota tiles
G54: House for Nemo: An Artificial Coral Reef Deployment Project | I54: 2021 | U54: Pyramid | V54: Concrete structure that is shaped like a pyramid as one unit
G55: Installation of Artificial Reef (AR) to Harness Potential of Balaoan, La Union Underwater Tourism and Improved Coral Reef Productivity | I55: 2022 | U55: Concrete block | V55: Concrete structure that is shaped like a cube, which can either be hollow or solid. It is usually used as inidividual units that are stacked to form bigger structures such as pyramids
G56: Integrated Management for Sustainable Environmental Approach to Coastal and Underwater Resources Program (IMSEACURE) | I56: 2023 | U56: Steel sculpture | V56: AR is a sculpture but made out of steel frames
G57: KALAHI-CIDSS | I57: 2024 | U57: Reef House | V57: AR used particularly for the SCREMP project in Central Visayas. The structure of the AR is unknown
G58: Kaligkasan sa Karagatan | I58: 2025 | U58: Giant Clam Restock
G59: La Union #KalikasanNaman Campaign | I59: 2026 | U59: Dome table
G60: Lingayen Fish Sanctuary | I60: 2027 | U60: Concrete cylinder
G61: National Coral Reef Management Conservation Program | I61: 2028 | U61: 3D-printed clay brick
G62: National Coral Reef Rehabilitation Roll-Out Program | I62: 2029
G63: Operation Blue Pipe | I63: 2030
G64: Operation Green Reef | I64: 2031
G65: Operation Pamamalakaya | I65: 2032
G66: Operation Peace for Fish | I66: 2033
G67: Oplan CORAL Park Project | I67: 2034
G68: Our Earth, Our Responsibility Campaign | I68: 2035
G69: Philippine Coral Reef Resources Assessment and Conservation Program (PhilCORE) | I69: 2036
G70: PLC Artificial Reef Program | I70: 2037
G71: PNP KaligKasan Program | I71: 2038
G72: Port Barrera Rehabilitation Project | I72: 2039
G73: Project 1. Culture Technologies for Coral Propagules from Eggs and Larvae | I73: 2040
... G83: reefbuds: A coral Augmentation Project | I83: 2050
G84: REEForestation using Recycled Waste Materials
G85: Regional Coral Restoration and Appropriate Technologies for Larger-Scale Coral & Fish Habitat Restoration in the Philippines and Australia (FIS 2019/23)
G86: S.O.S. Save our Seas: Supporting Ocean Biodiversity
G87: Sagip Bakawan Project
G88: Samar-Sea Ticao Pass Fisheries Development Corporation
G89: Sarangani Bay Artificial Reef Dome Project
G90: Sarangani Coastal Resources Development and Management Project
G91: Sea of Life
G92: Shangri-La Care for Nature Project
G93: Shore It Up
G94: Sixto Memorial Artificial Reef and Fish Sanctuary
G95: Small Islands Agricultural Support Services Program (SMISLE)
... G106: Unknown

Sheet Municipality
A1: Region | B1: Province | C1: Municipality | D1: Municipality_code
A2: BARMM | B2: Basilan | C2: City of Lamitan | D2: PH150702000
A3: BARMM | B3: Basilan | C3: Lantawan | D3: PH150703000
A4: BARMM | B4: Basilan | C4: Maluso | D4: PH150704000
A5: BARMM | B5: Basilan | C5: Sumisip | D5: PH150705000
A6: BARMM | B6: Basilan | C6: Tipo-Tipo | D6: PH150706000
A7: BARMM | B7: Basilan | C7: Tuburan | D7: PH150707000
A8: BARMM | B8: Basilan | C8: Akbar | D8: PH150708000
A9: BARMM | B9: Basilan | C9: Al-Barka | D9: PH150709000
A10: BARMM | B10: Basilan | C10: Hadji Mohammad Ajul | D10: PH150710000
A11: BARMM | B11: Basilan | C11: Ungkaya Pukan | D11: PH150711000
A12: BARMM | B12: Basilan | C12: Hadji Muhtamad | D12: PH150712000
... A120: BARMM | B120: Maguindanao del Sur | C120: Talayan | D120: PH153816000
A121: BARMM | B121: Special Geographic Area | C121: Kapalawan
A122: BARMM | B122: Special Geographic Area | C122: Old Kaabakan
A123: BARMM | B123: Special Geographic Area | C123: Kadayangan
A124: BARMM | B124: Special Geographic Area | C124: Nabalawag
A125: BARMM | B125: Special Geographic Area | C125: Pahamuddin
A126: BARMM | B126: Special Geographic Area | C126: Malidegao
A127: BARMM | B127: Special Geographic Area | C127: Ligawasan
A128: BARMM | B128: Special Geographic Area | C128: Tugunan
A129: I | B129: Ilocos Norte | C129: Adams | D129: PH012801000
A130: I | B130: Ilocos Norte | C130: Bacarra | D130: PH012802000
A131: I | B131: Ilocos Norte | C131: Badoc | D131: PH012803000
A132: I | B132: Ilocos Norte | C132: Bangui | D132: PH012804000
A133: I | B133: Ilocos Norte | C133: City of Batac | D133: PH012805000
A134: I | B134: Ilocos Norte | C134: Burgos | D134: PH012806000
A135: I | B135: Ilocos Norte | C135: Carasi | D135: PH012807000
A136: I | B136: Ilocos Norte | C136: Currimao | D136: PH012808000
A137: I | B137: Ilocos Norte | C137: Dingras | D137: PH012809000
A138: I | B138: Ilocos Norte | C138: Dumalneg | D138: PH012810000
A139: I | B139: Ilocos Norte | C139: Banna | D139: PH012811000
A140: I | B140: Ilocos Norte | C140: City of Laoag | D140: PH012812000
... A1644: CAR | B1644: Apayao | C1644: Santa Marcela | D1644: PH148107000

Sheet Interventions
A1: General Restoration Method | B1: Specific Restoration Method | C1: Artificial Reef Design
A2: Asexual Propagation | B2: Direct Transplantation | C2: Not applicable
A3: Asexual Propagation | B3: Coral Gardening | C3: Not applicable
A4: Asexual Propagation | B4: Microfragmentation | C4: Not applicable
A5: Sexual Propagation | B5: Larval Enhancement | C5: Not applicable
A6: Substrate Enhancement | B6: Artificial Reef | C6: Concrete
A7: Substrate Enhancement | B7: Artificial Reef | C7: Tires
A8: Substrate Enhancement | B8: Artificial Reef | C8: Natural
A9: Substrate Enhancement | B9: Artificial Reef | C9: Metal/Wreck
A10: Substrate Enhancement | B10: Artificial Reef | C10: Engineered/Advanced
A11: Substrate Enhancement | B11: Artificial Reef | C11: Recycled/Waste
A12: Substrate Enhancement | B12: Artificial Reef | C12: Hybrid
... A63: Unknown | B63: Unknown | C63: Unknown

Sheet InterventionsDD1
A1: {='CRR 2025'!P2:P1000} -> Substrate Enhancement | B1: =IFERROR(__xludf.DUMMYFUNCTION("byrow(A1:A1000, lambda(A, transpose(UNIQUE(filter(Interventions!B2:B1000,Interventions!A2:A1000=A)))))"),"Artificial Reef") -> Artificial Reef | C1: =IFERROR(__xludf.DUMMYFUNCTION("""COMPUTED_VALUE"""),"Mineral Accretion") -> Mineral Accretion | D1: =IFERROR(__xludf.DUMMYFUNCTION("""COMPUTED_VALUE"""),"Rubble Stabilisation") -> Rubble Stabilisation | E1: =IFERROR(__xludf.DUMMYFUNCTION("""COMPUTED_VALUE"""),"Algal Removal") -> Algal Removal
A2: Asexual Propagation | B2: =IFERROR(__xludf.DUMMYFUNCTION("""COMPUTED_VALUE"""),"Direct Transplantation") -> Direct Transplantation | C2: =IFERROR(__xludf.DUMMYFUNCTION("""COMPUTED_VALUE"""),"Coral Gardening") -> Coral Gardening | D2: =IFERROR(__xludf.DUMMYFUNCTION("""COMPUTED_VALUE"""),"Microfragmentation") -> Microfragmentation
A3: Sexual Propagation | B3: =IFERROR(__xludf.DUMMYFUNCTION("""COMPUTED_VALUE"""),"Larval Enhancement") -> Larval Enhancement
A4: Sexual Propagation | B4: =IFERROR(__xludf.DUMMYFUNCTION("""COMPUTED_VALUE"""),"Larval Enhancement") -> Larval Enhancement
A5: Sexual Propagation | B5: =IFERROR(__xludf.DUMMYFUNCTION("""COMPUTED_VALUE"""),"Larval Enhancement") -> Larval Enhancement
A6: Sexual Propagation | B6: =IFERROR(__xludf.DUMMYFUNCTION("""COMPUTED_VALUE"""),"Larval Enhancement") -> Larval Enhancement
A7: Sexual Propagation | B7: =IFERROR(__xludf.DUMMYFUNCTION("""COMPUTED_VALUE"""),"Larval Enhancement") -> Larval Enhancement
A8: Sexual Propagation | B8: =IFERROR(__xludf.DUMMYFUNCTION("""COMPUTED_VALUE"""),"Larval Enhancement") -> Larval Enhancement
A9: Sexual Propagation | B9: =IFERROR(__xludf.DUMMYFUNCTION("""COMPUTED_VALUE"""),"Larval Enhancement") -> Larval Enhancement
A10: Asexual Propagation, Substrate Enhancement | B10: =IFERROR(__xludf.DUMMYFUNCTION("""COMPUTED_VALUE"""),"Direct Transplantation") -> Direct Transplantation | C10: =IFERROR(__xludf.DUMMYFUNCTION("""COMPUTED_VALUE"""),"Coral Gardening") -> Coral Gardening | D10: =IFERROR(__xludf.DUMMYFUNCTION("""COMPUTED_VALUE"""),"Microfragmentation") -> Microfragmentation | E10: =IFERROR(__xludf.DUMMYFUNCTION("""COMPUTED_VALUE"""),"Artificial Reef") -> Artificial Reef | F10: =IFERROR(__xludf.DUMMYFUNCTION("""COMPUTED_VALUE"""),"Mineral Accretion") -> Mineral Accretion | G10: =IFERROR(__xludf.DUMMYFUNCTION("""COMPUTED_VALUE"""),"Rubble Stabilisation") -> Rubble Stabilisation | H10: =IFERROR(__xludf.DUMMYFUNCTION("""COMPUTED_VALUE"""),"Algal Removal") -> Algal Removal
A11: Substrate Enhancement | B11: =IFERROR(__xludf.DUMMYFUNCTION("""COMPUTED_VALUE"""),"Artificial Reef") -> Artificial Reef | C11: =IFERROR(__xludf.DUMMYFUNCTION("""COMPUTED_VALUE"""),"Mineral Accretion") -> Mineral Accretion | D11: =IFERROR(__xludf.DUMMYFUNCTION("""COMPUTED_VALUE"""),"Rubble Stabilisation") -> Rubble Stabilisation | E11: =IFERROR(__xludf.DUMMYFUNCTION("""COMPUTED_VALUE"""),"Algal Removal") -> Algal Removal
A12: Asexual Propagation, Sexual Propagation | B12: =IFERROR(__xludf.DUMMYFUNCTION("""COMPUTED_VALUE"""),"Direct Transplantation") -> Direct Transplantation | C12: =IFERROR(__xludf.DUMMYFUNCTION("""COMPUTED_VALUE"""),"Coral Gardening") -> Coral Gardening | D12: =IFERROR(__xludf.DUMMYFUNCTION("""COMPUTED_VALUE"""),"Microfragmentation") -> Microfragmentation | E12: =IFERROR(__xludf.DUMMYFUNCTION("""COMPUTED_VALUE"""),"Larval Enhancement") -> Larval Enhancement
A13: Asexual Propagation | B13: =IFERROR(__xludf.DUMMYFUNCTION("""COMPUTED_VALUE"""),"Direct Transplantation") -> Direct Transplantation | C13: =IFERROR(__xludf.DUMMYFUNCTION("""COMPUTED_VALUE"""),"Coral Gardening") -> Coral Gardening | D13: =IFERROR(__xludf.DUMMYFUNCTION("""COMPUTED_VALUE"""),"Microfragmentation") -> Microfragmentation
A14: Substrate Enhancement | B14: =IFERROR(__xludf.DUMMYFUNCTION("""COMPUTED_VALUE"""),"Artificial Reef") -> Artificial Reef | C14: =IFERROR(__xludf.DUMMYFUNCTION("""COMPUTED_VALUE"""),"Mineral Accretion") -> Mineral Accretion | D14: =IFERROR(__xludf.DUMMYFUNCTION("""COMPUTED_VALUE"""),"Rubble Stabilisation") -> Rubble Stabilisation | E14: =IFERROR(__xludf.DUMMYFUNCTION("""COMPUTED_VALUE"""),"Algal Removal") -> Algal Removal
A15: Substrate Enhancement | B15: =IFERROR(__xludf.DUMMYFUNCTION("""COMPUTED_VALUE"""),"Artificial Reef") -> Artificial Reef | C15: =IFERROR(__xludf.DUMMYFUNCTION("""COMPUTED_VALUE"""),"Mineral Accretion") -> Mineral Accretion | D15: =IFERROR(__xludf.DUMMYFUNCTION("""COMPUTED_VALUE"""),"Rubble Stabilisation") -> Rubble Stabilisation | E15: =IFERROR(__xludf.DUMMYFUNCTION("""COMPUTED_VALUE"""),"Algal Removal") -> Algal Removal
A16: Substrate Enhancement | B16: =IFERROR(__xludf.DUMMYFUNCTION("""COMPUTED_VALUE"""),"Artificial Reef") -> Artificial Reef | C16: =IFERROR(__xludf.DUMMYFUNCTION("""COMPUTED_VALUE"""),"Mineral Accretion") -> Mineral Accretion | D16: =IFERROR(__xludf.DUMMYFUNCTION("""COMPUTED_VALUE"""),"Rubble Stabilisation") -> Rubble Stabilisation | E16: =IFERROR(__xludf.DUMMYFUNCTION("""COMPUTED_VALUE"""),"Algal Removal") -> Algal Removal
A17: Substrate Enhancement | B17: =IFERROR(__xludf.DUMMYFUNCTION("""COMPUTED_VALUE"""),"Artificial Reef") -> Artificial Reef | C17: =IFERROR(__xludf.DUMMYFUNCTION("""COMPUTED_VALUE"""),"Mineral Accretion") -> Mineral Accretion | D17: =IFERROR(__xludf.DUMMYFUNCTION("""COMPUTED_VALUE"""),"Rubble Stabilisation") -> Rubble Stabilisation | E17: =IFERROR(__xludf.DUMMYFUNCTION("""COMPUTED_VALUE"""),"Algal Removal") -> Algal Removal
A18: Substrate Enhancement | B18: =IFERROR(__xludf.DUMMYFUNCTION("""COMPUTED_VALUE"""),"Artificial Reef") -> Artificial Reef | C18: =IFERROR(__xludf.DUMMYFUNCTION("""COMPUTED_VALUE"""),"Mineral Accretion") -> Mineral Accretion | D18: =IFERROR(__xludf.DUMMYFUNCTION("""COMPUTED_VALUE"""),"Rubble Stabilisation") -> Rubble Stabilisation | E18: =IFERROR(__xludf.DUMMYFUNCTION("""COMPUTED_VALUE"""),"Algal Removal") -> Algal Removal
A19: Substrate Enhancement | B19: =IFERROR(__xludf.DUMMYFUNCTION("""COMPUTED_VALUE"""),"Artificial Reef") -> Artificial Reef | C19: =IFERROR(__xludf.DUMMYFUNCTION("""COMPUTED_VALUE"""),"Mineral Accretion") -> Mineral Accretion | D19: =IFERROR(__xludf.DUMMYFUNCTION("""COMPUTED_VALUE"""),"Rubble Stabilisation") -> Rubble Stabilisation | E19: =IFERROR(__xludf.DUMMYFUNCTION("""COMPUTED_VALUE"""),"Algal Removal") -> Algal Removal
A20: Substrate Enhancement | B20: =IFERROR(__xludf.DUMMYFUNCTION("""COMPUTED_VALUE"""),"Artificial Reef") -> Artificial Reef | C20: =IFERROR(__xludf.DUMMYFUNCTION("""COMPUTED_VALUE"""),"Mineral Accretion") -> Mineral Accretion | D20: =IFERROR(__xludf.DUMMYFUNCTION("""COMPUTED_VALUE"""),"Rubble Stabilisation") -> Rubble Stabilisation | E20: =IFERROR(__xludf.DUMMYFUNCTION("""COMPUTED_VALUE"""),"Algal Removal") -> Algal Removal
A21: Substrate Enhancement | B21: =IFERROR(__xludf.DUMMYFUNCTION("""COMPUTED_VALUE"""),"Artificial Reef") -> Artificial Reef | C21: =IFERROR(__xludf.DUMMYFUNCTION("""COMPUTED_VALUE"""),"Mineral Accretion") -> Mineral Accretion | D21: =IFERROR(__xludf.DUMMYFUNCTION("""COMPUTED_VALUE"""),"Rubble Stabilisation") -> Rubble Stabilisation | E21: =IFERROR(__xludf.DUMMYFUNCTION("""COMPUTED_VALUE"""),"Algal Removal") -> Algal Removal
A22: Substrate Enhancement | B22: =IFERROR(__xludf.DUMMYFUNCTION("""COMPUTED_VALUE"""),"Artificial Reef") -> Artificial Reef | C22: =IFERROR(__xludf.DUMMYFUNCTION("""COMPUTED_VALUE"""),"Mineral Accretion") -> Mineral Accretion | D22: =IFERROR(__xludf.DUMMYFUNCTION("""COMPUTED_VALUE"""),"Rubble Stabilisation") -> Rubble Stabilisation | E22: =IFERROR(__xludf.DUMMYFUNCTION("""COMPUTED_VALUE"""),"Algal Removal") -> Algal Removal
A23: Substrate Enhancement | B23: =IFERROR(__xludf.DUMMYFUNCTION("""COMPUTED_VALUE"""),"Artificial Reef") -> Artificial Reef | C23: =IFERROR(__xludf.DUMMYFUNCTION("""COMPUTED_VALUE"""),"Mineral Accretion") -> Mineral Accretion | D23: =IFERROR(__xludf.DUMMYFUNCTION("""COMPUTED_VALUE"""),"Rubble Stabilisation") -> Rubble Stabilisation | E23: =IFERROR(__xludf.DUMMYFUNCTION("""COMPUTED_VALUE"""),"Algal Removal") -> Algal Removal
A24: Substrate Enhancement | B24: =IFERROR(__xludf.DUMMYFUNCTION("""COMPUTED_VALUE"""),"Artificial Reef") -> Artificial Reef | C24: =IFERROR(__xludf.DUMMYFUNCTION("""COMPUTED_VALUE"""),"Mineral Accretion") -> Mineral Accretion | D24: =IFERROR(__xludf.DUMMYFUNCTION("""COMPUTED_VALUE"""),"Rubble Stabilisation") -> Rubble Stabilisation | E24: =IFERROR(__xludf.DUMMYFUNCTION("""COMPUTED_VALUE"""),"Algal Removal") -> Algal Removal
A25: Substrate Enhancement | B25: =IFERROR(__xludf.DUMMYFUNCTION("""COMPUTED_VALUE"""),"Artificial Reef") -> Artificial Reef | C25: =IFERROR(__xludf.DUMMYFUNCTION("""COMPUTED_VALUE"""),"Mineral Accretion") -> Mineral Accretion | D25: =IFERROR(__xludf.DUMMYFUNCTION("""COMPUTED_VALUE"""),"Rubble Stabilisation") -> Rubble Stabilisation | E25: =IFERROR(__xludf.DUMMYFUNCTION("""COMPUTED_VALUE"""),"Algal Removal") -> Algal Removal
... A83: Substrate Enhancement | B83: =IFERROR(__xludf.DUMMYFUNCTION("""COMPUTED_VALUE"""),"Artificial Reef") -> Artificial Reef | C83: =IFERROR(__xludf.DUMMYFUNCTION("""COMPUTED_VALUE"""),"Mineral Accretion") -> Mineral Accretion | D83: =IFERROR(__xludf.DUMMYFUNCTION("""COMPUTED_VALUE"""),"Rubble Stabilisation") -> Rubble Stabilisation | E83: =IFERROR(__xludf.DUMMYFUNCTION("""COMPUTED_VALUE"""),"Algal Removal") -> Algal Removal
A84: Asexual Propagation | B84: =IFERROR(__xludf.DUMMYFUNCTION("""COMPUTED_VALUE"""),"Direct Transplantation") -> Direct Transplantation | C84: =IFERROR(__xludf.DUMMYFUNCTION("""COMPUTED_VALUE"""),"Coral Gardening") -> Coral Gardening | D84: =IFERROR(__xludf.DUMMYFUNCTION("""COMPUTED_VALUE"""),"Microfragmentation") -> Microfragmentation
A85: Asexual Propagation | B85: =IFERROR(__xludf.DUMMYFUNCTION("""COMPUTED_VALUE"""),"Direct Transplantation") -> Direct Transplantation | C85: =IFERROR(__xludf.DUMMYFUNCTION("""COMPUTED_VALUE"""),"Coral Gardening") -> Coral Gardening | D85: =IFERROR(__xludf.DUMMYFUNCTION("""COMPUTED_VALUE"""),"Microfragmentation") -> Microfragmentation
